Workbook

Sheet Watchlist Ratings
A1: WATCHLIST RATINGS — JP Morgan Equity Research Framework | Long-Term Investor View
A2: MARKET DATA | J2: RATING 1 — STRUCTURAL QUALITY (Normalized 0–10) | T2: RATING 2 — ECONOMIC QUALITY & VALUE CREATION (Normalized 0–10) | AD2: RATING 3 — DURABILITY & EXISTENTIAL RISK (Normalized 0–10) | AN2: COMPOSITE RATING (0–10 avg) | AO2: Financials information | BJ2: Future valuation range | BN2: Actualizaciones y resultados
A3: Company Name Name | B3: Ticker Symbol | C3: Category | D3: Estilo inversión | E3: Exchange Listing | F3: Currency | G3: Price Local ccy | H3: Shares Outstanding millions | I3: Market Cap local ccy, m | J3: Mission (-1 to 2) | K3: MOAT (0 to 8) | L3: Optionality (0 to 3) | M3: Financials (-1 to 1) | N3: Concentration (-3 to 0) | O3: Glassdoor (-1 to 1) | P3: Founder/CEO (0 to 1) | Q3: Ownership (-1 to 1) | R3: R1 Sum (max 17) | S3: RATING 1 0–10 | T3: Financials (0 to 17) | U3: MOAT (0 to 20) | V3: Potential (0 to 18) | W3: Customers (0 to 10) | X3: Revenue Quality (0 to 10) | Y3: Mgmt & Culture (0 to 14) | Z3: Stock & Ownership (0 to 11) | AA3: Risks (-44 to 0) | AB3: R2 Sum (max 100) | AC3: RATING 2 0–10 | AD3: Durability (0 to 15) | AE3: Risk of Disappearance (-20 to 0) | AF3: Capital Intensity (0 to 10) | AG3: Capital Allocation (0 to 15) | AH3: Financing Source (-10 to 5) | AI3: Incentives (0 to 10) | AJ3: MOAT Structural (0 to 15) | AK3: Terminal Risk (-20 to 0) | AL3: R3 Sum (max 70) | AM3: RATING 3 0–10 | AO3: FX Reporting | AP3: Cash & Equivalents | AQ3: Total Debt | AR3: Enterprise Value | AS3: FCF LTM (unlevered) | AT3: NOPAT LTM | AU3: EBITDA LTM | AV3: Revenue LTM | AW3: EV / FCF | AX3: EV / EBITDA | AY3: EV / Sales | AZ3: Capital Employed | BA3: NOPAT M% | BB3: Asset Turnover | BC3: ROIC | BD3: FCF @5y Min | BE3: FCF min CAGR | BF3: FCF @5y Max | BG3: FCF max CAGR | BH3: Exit Mult Min | BI3: Exit Mult Max | BJ3: FVE min | BK3: FVE max | BL3: Worst IRR | BM3: Best IRR | BN3: Última actualización | BO3: Últimos resultados | BP3: Próximos resultados | BQ3: SBC LTM | BR3: Capex de crecimiento | BS3: FCF normalizado | BT3: Fuente del SBC
A4: #VALUE! | B4: {=_FV(A4,"Símbolo bursátil",TRUE())} -> VEEV | C4: Vertical Saas | D4: Compounder | E4: {=_FV(A4,"Abreviatura de intercambio",TRUE())} -> XNYS | F4: {=_FV(A4,"Moneda")} -> USD | G4: {=_FV(A4,"Precio")} -> 316.55 | H4: {=_FV(A4,"Acciones en circulación",TRUE)/1000000} -> 161.9088 | I4: =G4*H4 -> 51252.231 | J4: 1.5 | K4: 8 | L4: 2 | M4: 1 | N4: -1.5 | O4: 0.72 | P4: 1 | Q4: 1 | R4: =SUM(J4:N4)+SUM(P4:Q4) -> 13 | S4: =ROUND(R4/16*10,2) -> 8.13 | T4: 17 | U4: 18 | V4: 16 | W4: 8 | X4: 9 | Y4: 12 | Z4: 10 | AA4: -8 | AB4: =SUM(T4:AA4) -> 82 | AC4: =ROUND(AB4/10,2) -> 8.2 | AD4: 14 | AE4: 0 | AF4: 10 | AG4: 14 | AH4: 5 | AI4: 8 | AJ4: 14 | AK4: -5 | AL4: =SUM(AD4:AK4) -> 60 | AM4: =ROUND(AL4/70*10,2) -> 8.57 | AN4: =ROUND(S4*0.2+AC4*0.4+AM4*0.4,2) -> 8.33 | AO4: USD | AP4: 7242.9 | AQ4: 0 | AR4: =I4-AP4+AQ4 -> 44009.331 | AS4: 1144.2 | AT4: 791 | AV4: 3458.1 | AW4: =AR4/AS4 -> 38.46297 | AX4: =AR4/AU4 -> #VALUE! | AY4: =AR4/AV4 -> 12.726448 | AZ4: 1500 | BA4: =AT4/AV4 -> 0.22873832 | BB4: =AV4/AZ4 -> 2.3054 | BC4: =BA4*BB4 -> 0.52733333 | BD4: 1068.8 | BE4: =(BD4/AS4)^(1/5)-1 -> -0.013541316 | BF4: 2347.5 | BG4: =(BF4/AS4)^(1/5)-1 -> 0.15457123 | BH4: 18 | BI4: 30 | BJ4: =(BD4*BH4+$AP4-$AQ4)/$H4 -> 163.55689 | BK4: =(BF4*BI4+$AP4-$AQ4)/$H4 -> 479.70154 | BL4: =IF($BJ4<=0,-0.99,MAX(-0.99,($BJ4/G4)^(1/5)-1)) -> -0.12371514 | BM4: =IF(BK4<=0,-0.99,MAX(-0.99,(BK4/G4)^(1/5)-1)) -> 0.086690219 | BN4: 2026-09-27 | BO4: 26/08/2026 | BP4: 19/11/2026 | BQ4: 494.6 | BR4: 0 | BS4: 1144.2 | BT4: FUENTE: 10-Q Q2 FY27 (EDGAR XBRL, LTM = H1 FY27 + FY26 - H1 FY26). OCF 1.665,5 - capex (software capitalizado) 26,7 - SBC 494,6 = 1.144,2. Caja 1.812 + inversiones 5.430,9. Sin deuda financiera (arrend. operativos fuera, US GAAP). EBITDA pendiente (D&A no etiquetada completa). Proximos resultados ESTIMADOS por patron (Q3 FY26 fue el 20-nov-2025)
A5: #VALUE! | B5: {=_FV(A5,"Símbolo bursátil",TRUE())} -> MSFT | C5: Mag 7 | D5: Compounder | E5: {=_FV(A5,"Abreviatura de intercambio",TRUE())} -> XNAS | F5: {=_FV(A5,"Moneda")} -> USD | G5: {=_FV(A5,"Precio")} -> 534.27 | H5: {=_FV(A5,"Acciones en circulación",TRUE())/1000000} -> 7425.545 | I5: =G5*H5 -> 3967245.9 | J5: 1 | K5: 8 | L5: 3 | M5: 1 | N5: 0 | O5: 0.8 | P5: 1 | Q5: 0 | R5: =SUM(J5:N5)+SUM(P5:Q5) -> 14 | S5: =ROUND(R5/16*10,2) -> 8.75 | T5: 16 | U5: 19 | V5: 15 | W5: 10 | X5: 9 | Y5: 13 | Z5: 7 | AA5: -12 | AB5: =SUM(T5:AA5) -> 77 | AC5: =ROUND(AB5/10,2) -> 7.7 | AD5: 14 | AE5: 0 | AF5: 4 | AG5: 14 | AH5: 5 | AI5: 9 | AJ5: 13 | AK5: -6 | AL5: =SUM(AD5:AK5) -> 53 | AM5: =ROUND(AL5/70*10,2) -> 7.57 | AN5: =ROUND(S5*0.2+AC5*0.4+AM5*0.4,2) -> 7.86 | AO5: USD | AP5: 76843 | AQ5: 40294 | AR5: =I5-AP5+AQ5 -> 3930696.9 | AS5: 54582 | AT5: 125127 | AU5: 193771 | AV5: 331839 | AW5: =AR5/AS5 -> 72.014527 | AX5: =AR5/AU5 -> 20.285269 | AY5: =AR5/AV5 -> 11.845193 | AZ5: 589551 | BA5: =AT5/AV5 -> 0.37707141 | BB5: =AV5/AZ5 -> 0.56286733 | BC5: =BA5*BB5 -> 0.21224118 | BD5: 147461.2 | BE5: =(BD5/BS5)^(1/5)-1 -> 0.030193356 | BF5: 223734.1 | BG5: =(BF5/BS5)^(1/5)-1 -> 0.11977206 | BH5: 20 | BI5: 30 | BJ5: =(BD5*BH5+$AP5-$AQ5)/$H5 -> 402.0948 | BK5: =(BF5*BI5+$AP5-$AQ5)/$H5 -> 908.83188 | BL5: =IF($BJ5<=0,-0.99,MAX(-0.99,($BJ5/G5)^(1/5)-1)) -> -0.055257326 | BM5: =IF(BK5<=0,-0.99,MAX(-0.99,(BK5/G5)^(1/5)-1)) -> 0.11210182 | BN5: 46256 | BO5: 29/07/2026 | BP5: 28/10/2026 | BQ5: 12405 | BR5: 72500 | BS5: 127082 | BT5: FCF@5y NORMALIZADO el 4-oct-2026 por decision de Roger: BD/BF del 8-sep x BS/AS (127.082/54.582 = 2,328). BD 63.334,9 -> 147.461,2; BF 96.094,3 -> 223.734,1. CAGR sobre el normalizado 3,0% / 12,0% (las de Roger). BE/BG pasan a medirse contra BS. Multiplos sin cambio por decision de Roger: se calibraron el 22-ago sobre FCF@5y normalizado.
A6: #VALUE! | B6: {=_FV(A6,"Símbolo bursátil",TRUE())} -> ADYEN | C6: Fintech | D6: Compounder | E6: {=_FV(A6,"Abreviatura de intercambio",TRUE())} -> XAMS | F6: {=_FV(A6,"Moneda")} -> EUR | G6: {=_FV(A6,"Precio")} -> 930.4 | H6: {=_FV(A6,"Acciones en circulación",TRUE())/1000000} -> 31.69488 | I6: =G6*H6 -> 29488.916 | J6: 1 | K6: 7 | L6: 2 | M6: 1 | N6: -0.5 | O6: 0.74 | P6: 1 | Q6: 1 | R6: =SUM(J6:N6)+SUM(P6:Q6) -> 12.5 | S6: =ROUND(R6/16*10,2) -> 7.81 | T6: 15.5 | U6: 18 | V6: 13 | W6: 8 | X6: 7.5 | Y6: 11 | Z6: 10 | AA6: -10 | AB6: =SUM(T6:AA6) -> 73 | AC6: =ROUND(AB6/10,2) -> 7.3 | AD6: 13 | AE6: -1 | AF6: 9 | AG6: 14 | AH6: 5 | AI6: 10 | AJ6: 14 | AK6: -6 | AL6: =SUM(AD6:AK6) -> 58 | AM6: =ROUND(AL6/70*10,2) -> 8.29 | AN6: =ROUND(S6*0.2+AC6*0.4+AM6*0.4,2) -> 7.8 | AO6: EUR | AP6: 2710 | AQ6: 0 | AR6: =I6-AP6+AQ6 -> 26778.916 | AS6: 1098 | AT6: 895 | AU6: 1344 | AV6: 2573.6 | AW6: =AR6/AS6 -> 24.388813 | AX6: =AR6/AU6 -> 19.924789 | AY6: =AR6/AV6 -> 10.405236 | AZ6: 2500 | BA6: =AT6/AV6 -> 0.34776189 | BB6: =AV6/AZ6 -> 1.02944 | BC6: =BA6*BB6 -> 0.358 | BD6: 959.1 | BE6: =(BD6/AS6)^(1/5)-1 -> -0.026687479 | BF6: 2581.2 | BG6: =(BF6/AS6)^(1/5)-1 -> 0.18643476 | BH6: 17.5 | BI6: 28 | BJ6: =(BD6*BH6+$AP6-$AQ6)/$H6 -> 615.05991 | BK6: =(BF6*BI6+$AP6-$AQ6)/$H6 -> 2365.7954 | BL6: =IF($BJ6<=0,-0.99,MAX(-0.99,($BJ6/G6)^(1/5)-1)) -> -0.079445419 | BM6: =IF(BK6<=0,-0.99,MAX(-0.99,(BK6/G6)^(1/5)-1)) -> 0.20520658 | BN6: 2026-09-12 | BO6: 13/08/2026 | BP6: 28/10/2026 | BQ6: 43 | BR6: 0 | BS6: 1098 | BT6: LTM H1-26 (H2-25+H1-26). FCF honesto: EBITDA 1.344 - capex 128 - leases 25 - impuestos ~380 + intereses del float ~330 - SBC 43 = ~1.098 (def. Adyen 86% conv. = 1.156 sin impuestos). OJO: ~330 son intereses sobre fondos de comercios, bajan con tipos. Caja neta REAL 2.710 (3.000 - Orb 290), no la del balance. Antes AS=864 venia de OCF yfinance contaminado por fondos de comercios. FCF@5y sin escalar
A7: #VALUE! | B7: {=_FV(A7,"Símbolo bursátil",TRUE())} -> BN | C7: Real Assets | D7: Compounder | E7: {=_FV(A7,"Abreviatura de intercambio",TRUE())} -> XNYS | F7: {=_FV(A7,"Moneda")} -> USD | G7: {=_FV(A7,"Precio")} -> 36.395 | H7: {=_FV(A7,"Acciones en circulación",TRUE())/1000000} -> 2452.011 | I7: =G7*H7 -> 89240.94 | J7: 1 | K7: 7 | L7: 3 | M7: 0.5 | N7: 0 | O7: 0.66 | P7: 1 | Q7: 1 | R7: =SUM(J7:N7)+SUM(P7:Q7) -> 13.5 | S7: =ROUND(R7/16*10,2) -> 8.44 | T7: 13 | U7: 17 | V7: 15 | W7: 10 | X7: 9 | Y7: 14 | Z7: 10 | AA7: -8 | AB7: =SUM(T7:AA7) -> 80 | AC7: =ROUND(AB7/10,2) -> 8 | AD7: 14 | AE7: -1 | AF7: 5 | AG7: 15 | AH7: 2 | AI7: 10 | AJ7: 14 | AK7: -5 | AL7: =SUM(AD7:AK7) -> 54 | AM7: =ROUND(AL7/70*10,2) -> 7.71 | AN7: =ROUND(S7*0.2+AC7*0.4+AM7*0.4,2) -> 7.97 | AO7: USD | AP7: 10000 | AQ7: 17815 | AR7: =I7-AP7+AQ7 -> 97055.94 | AS7: 6080 | AT7: 5700 | AU7: 5700 | AV7: 80690 | AW7: =AR7/AS7 -> 15.963148 | AX7: =AR7/AU7 -> 17.027358 | AY7: =AR7/AV7 -> 1.2028249 | AZ7: 42483 | BA7: =AT7/AV7 -> 0.070640724 | BB7: =AV7/AZ7 -> 1.899348 | BC7: =BA7*BB7 -> 0.13417132 | BD7: 6712.5 | BE7: =(BD7/AS7)^(1/5)-1 -> 0.01999054 | BF7: 11199 | BG7: =(BF7/AS7)^(1/5)-1 -> 0.12993935 | BH7: 17.5 | BI7: 25 | BJ7: =(BD7*BH7+$AP7-$AQ7)/$H7 -> 44.719926 | BK7: =(BF7*BI7+$AP7-$AQ7)/$H7 -> 110.99461 | BL7: =IF($BJ7<=0,-0.99,MAX(-0.99,($BJ7/G7)^(1/5)-1)) -> 0.042057947 | BM7: =IF(BK7<=0,-0.99,MAX(-0.99,(BK7/G7)^(1/5)-1)) -> 0.24983313 | BN7: 2026-08-26 | BO7: 13/08/2026 | BP7: 12/11/2026 | BQ7: 120 | BR7: 0 | BS7: 6080 | BT7: DE non-GAAP LTM Q2-26 (6.200 = 2,61 $/acc) menos SBC equity-settled 120 (40-F FY25). NO usar OCF-capex consolidado | Investor Day 17-sep-2026 (segunda mano): el valor del plan, 140 $/accion, pasa de 2030 a 2031; DE antes de realizaciones 5.300 (2026) -> 11.600 (2031)
A8: #VALUE! | B8: {=_FV(A8,"Símbolo bursátil",TRUE())} -> COST | C8: Defensive | D8: Defensive | E8: {=_FV(A8,"Abreviatura de intercambio",TRUE())} -> XNAS | F8: {=_FV(A8,"Moneda")} -> USD | G8: {=_FV(A8,"Precio")} -> 994.68 | H8: {=_FV(A8,"Acciones en circulación",TRUE())/1000000} -> 443.1294 | I8: =G8*H8 -> 440771.95 | J8: 1.5 | K8: 8 | L8: 1 | M8: 1 | N8: 0 | O8: 0.78 | P8: 1 | Q8: 0 | R8: =SUM(J8:N8)+SUM(P8:Q8) -> 12.5 | S8: =ROUND(R8/16*10,2) -> 7.81 | T8: 15 | U8: 19 | V8: 13 | W8: 10 | X8: 10 | Y8: 13 | Z8: 7 | AA8: -7 | AB8: =SUM(T8:AA8) -> 80 | AC8: =ROUND(AB8/10,2) -> 8 | AD8: 15 | AE8: 0 | AF8: 6 | AG8: 13 | AH8: 5 | AI8: 9 | AJ8: 14 | AK8: -3 | AL8: =SUM(AD8:AK8) -> 59 | AM8: =ROUND(AL8/70*10,2) -> 8.43 | AN8: =ROUND(S8*0.2+AC8*0.4+AM8*0.4,2) -> 8.13 | AO8: USD | AP8: 21301 | AQ8: 6162 | AR8: =I8-AP8+AQ8 -> 425632.95 | AS8: 8479 | AT8: 8799 | AU8: 14250 | AV8: 303154 | AW8: =AR8/AS8 -> 50.198485 | AX8: =AR8/AU8 -> 29.868979 | AY8: =AR8/AV8 -> 1.4040156 | AZ8: 44305 | BA8: =AT8/AV8 -> 0.029024852 | BB8: =AV8/AZ8 -> 6.8424331 | BC8: =BA8*BB8 -> 0.19860061 | BD8: 10565.4 | BE8: =(BD8/AS8)^(1/5)-1 -> 0.044980681 | BF8: 13913.8 | BG8: =(BF8/AS8)^(1/5)-1 -> 0.10413004 | BH8: 20 | BI8: 30 | BJ8: =(BD8*BH8+$AP8-$AQ8)/$H8 -> 511.01777 | BK8: =(BF8*BI8+$AP8-$AQ8)/$H8 -> 976.13248 | BL8: =IF($BJ8<=0,-0.99,MAX(-0.99,($BJ8/G8)^(1/5)-1)) -> -0.12471291 | BM8: =IF(BK8<=0,-0.99,MAX(-0.99,(BK8/G8)^(1/5)-1)) -> -0.0037574755 | BN8: 2026-09-27 | BO8: 24/09/2026 | BP8: 10/12/2026 | BQ8: 911 | BR8: 3870 | BS8: 12349 | BT8: FUENTE: 8-K Q4 FY26 (24-sep-2026): ingresos 303.154, EBIT 11.685, OCF 15.825, capex 6.435, caja 20.207 + inv. 1.094, deuda 2.248 + 3.914. SBC 911 y D&A 2.565 son LTM a Q3 (10-Q) hasta el 10-K de octubre. FCF-SBC 8.479; capex de crecimiento 6.435 - 2.565 = 3.870 -> normalizado 12.349. FCF@5y DEVUELTO a los valores de Roger (el 26-sep los escale sin preguntar). Proximos: estimado 10-dic
A9: #VALUE! | B9: {=_FV(A9,"Símbolo bursátil",TRUE())} -> DSGX | C9: Vertical Saas | D9: Compounder | E9: {=_FV(A9,"Abreviatura de intercambio",TRUE())} -> XNAS | F9: {=_FV(A9,"Moneda")} -> USD | G9: {=_FV(A9,"Precio")} -> 87.415 | H9: {=_FV(A9,"Acciones en circulación",TRUE())/1000000} -> 85.54855 | I9: =G9*H9 -> 7478.2265 | J9: 1 | K9: 7 | L9: 2 | M9: 1 | N9: 0 | O9: 0.8 | P9: 0.5 | Q9: 0 | R9: =SUM(J9:N9)+SUM(P9:Q9) -> 11.5 | S9: =ROUND(R9/16*10,2) -> 7.19 | T9: 16 | U9: 17 | V9: 11 | W9: 10 | X9: 9 | Y9: 13 | Z9: 6 | AA9: -7 | AB9: =SUM(T9:AA9) -> 75 | AC9: =ROUND(AB9/10,2) -> 7.5 | AD9: 14 | AE9: 0 | AF9: 10 | AG9: 13 | AH9: 5 | AI9: 8 | AJ9: 14 | AK9: -3 | AL9: =SUM(AD9:AK9) -> 61 | AM9: =ROUND(AL9/70*10,2) -> 8.71 | AN9: =ROUND(S9*0.2+AC9*0.4+AM9*0.4,2) -> 7.92 | AO9: USD | AP9: 182 | AQ9: 8.1 | AR9: =I9-AP9+AQ9 -> 7304.3265 | AS9: 271.4 | AT9: 178 | AU9: 357 | AV9: 775.1 | AW9: =AR9/AS9 -> 26.91351 | AX9: =AR9/AU9 -> 20.460298 | AY9: =AR9/AV9 -> 9.4237215 | AZ9: 1676 | BA9: =AT9/AV9 -> 0.22964779 | BB9: =AV9/AZ9 -> 0.46247017 | BC9: =BA9*BB9 -> 0.10620525 | BD9: 282.8 | BE9: =(BD9/AS9)^(1/5)-1 -> 0.0082631906 | BF9: 570 | BG9: =(BF9/AS9)^(1/5)-1 -> 0.15998668 | BH9: 17.5 | BI9: 27 | BJ9: =(BD9*BH9+$AP9-$AQ9)/$H9 -> 59.882955 | BK9: =(BF9*BI9+$AP9-$AQ9)/$H9 -> 181.93061 | BL9: =IF($BJ9<=0,-0.99,MAX(-0.99,($BJ9/G9)^(1/5)-1)) -> -0.072863983 | BM9: =IF(BK9<=0,-0.99,MAX(-0.99,(BK9/G9)^(1/5)-1)) -> 0.1578811 | BN9: 2026-09-11 | BO9: 10/09/2026 | BP9: 02/12/2026 | BQ9: 27.1 | BR9: 0 | BS9: 271.4 | BT9: trimestral (Q2 FY27: 8,0 incl. impuestos asociados). Caja PRO FORMA 182 = 401,1 - Tai 99,3 - Extensiv 119,9 (cerradas tras el balance). Proximos resultados: estimacion
A10: #VALUE! | B10: {=_FV(A10,"Símbolo bursátil",TRUE())} -> RAA | C10: Hardware | D10: Compounder | E10: {=_FV(A10,"Abreviatura de intercambio",TRUE())} -> XFRA | F10: {=_FV(A10,"Moneda")} -> EUR | G10: {=_FV(A10,"Precio")} -> 612.5 | H10: {=_FV(A10,"Acciones en circulación",TRUE())/1000000} -> 11.37 | I10: =G10*H10 -> 6964.125 | J10: 1 | K10: 7 | L10: 2 | M10: 1 | N10: -1 | O10: 0.82 | P10: 1 | Q10: 1 | R10: =SUM(J10:N10)+SUM(P10:Q10) -> 12 | S10: =ROUND(R10/16*10,2) -> 7.5 | T10: 15 | U10: 17 | V10: 10 | W10: 9 | X10: 8 | Y10: 13 | Z10: 10 | AA10: -8 | AB10: =SUM(T10:AA10) -> 74 | AC10: =ROUND(AB10/10,2) -> 7.4 | AD10: 14 | AE10: -1 | AF10: 8 | AG10: 13 | AH10: 5 | AI10: 9 | AJ10: 13 | AK10: -3 | AL10: =SUM(AD10:AK10) -> 58 | AM10: =ROUND(AL10/70*10,2) -> 8.29 | AN10: =ROUND(S10*0.2+AC10*0.4+AM10*0.4,2) -> 7.78 | AO10: EUR | AP10: 280 | AQ10: 20 | AR10: =I10-AP10+AQ10 -> 6704.125 | AS10: 235.5 | AT10: 230 | AU10: 350 | AV10: 1296 | AW10: =AR10/AS10 -> 28.467622 | AX10: =AR10/AU10 -> 19.154643 | AY10: =AR10/AV10 -> 5.172936 | AZ10: 600 | BA10: =AT10/AV10 -> 0.17746914 | BB10: =AV10/AZ10 -> 2.16 | BC10: =BA10*BB10 -> 0.38333333 | BD10: 300.7 | BE10: =(BD10/AS10)^(1/5)-1 -> 0.050094789 | BF10: 433.9 | BG10: =(BF10/AS10)^(1/5)-1 -> 0.13000339 | BH10: 15 | BI10: 27 | BJ10: =(BD10*BH10+$AP10-$AQ10)/$H10 -> 419.56904 | BK10: =(BF10*BI10+$AP10-$AQ10)/$H10 -> 1053.2366 | BL10: =IF($BJ10<=0,-0.99,MAX(-0.99,($BJ10/G10)^(1/5)-1)) -> -0.072872488 | BM10: =IF(BK10<=0,-0.99,MAX(-0.99,(BK10/G10)^(1/5)-1)) -> 0.11451 | BN10: 2026-08-25 | BO10: 06/08/2026 | BP10: 05/11/2026 | BQ10: 0 | BR10: 3.2 | BS10: 238.7 | BT10: no reportado (0)
A11: #VALUE! | B11: {=_FV(A11,"Símbolo bursátil",TRUE())} -> ZS | C11: Cyber | D11: Growth | E11: {=_FV(A11,"Abreviatura de intercambio",TRUE())} -> XNAS | F11: {=_FV(A11,"Moneda")} -> USD | G11: {=_FV(A11,"Precio")} -> 213.11 | H11: {=_FV(A11,"Acciones en circulación",TRUE())/1000000} -> 163.0547 | I11: =G11*H11 -> 34748.587 | J11: 1 | K11: 6 | L11: 2 | M11: 1 | N11: 0 | O11: 0.72 | P11: 1 | Q11: 1 | R11: =SUM(J11:N11)+SUM(P11:Q11) -> 12 | S11: =ROUND(R11/16*10,2) -> 7.5 | T11: 13 | U11: 15 | V11: 14 | W11: 8 | X11: 9 | Y11: 12 | Z11: 10 | AA11: -11 | AB11: =SUM(T11:AA11) -> 70 | AC11: =ROUND(AB11/10,2) -> 7 | AD11: 13 | AE11: -2 | AF11: 9 | AG11: 11 | AH11: 4 | AI11: 9 | AJ11: 12 | AK11: -5 | AL11: =SUM(AD11:AK11) -> 51 | AM11: =ROUND(AL11/70*10,2) -> 7.29 | AN11: =ROUND(S11*0.2+AC11*0.4+AM11*0.4,2) -> 7.22 | AO11: USD | AP11: 3474.2 | AQ11: 1696.4 | AR11: =I11-AP11+AQ11 -> 32970.787 | AS11: -42.7 | AT11: -133.3 | AU11: 15.2 | AV11: 3352.5 | AW11: =AR11/AS11 -> -772.14958 | AX11: =AR11/AU11 -> 2169.1307 | AY11: =AR11/AV11 -> 9.8346867 | AZ11: 4597 | BA11: =AT11/AV11 -> -0.039761372 | BB11: =AV11/AZ11 -> 0.72927997 | BC11: =BA11*BB11 -> -0.028997172 | BD11: 125 | BE11: =(BD11/AS11)^(1/5)-1 -> -2.2396424 | BF11: 314.5 | BG11: =(BF11/AS11)^(1/5)-1 -> -2.4908658 | BH11: 20 | BI11: 30 | BJ11: =(BD11*BH11+$AP11-$AQ11)/$H11 -> 26.235368 | BK11: =(BF11*BI11+$AP11-$AQ11)/$H11 -> 68.767107 | BL11: =IF($BJ11<=0,-0.99,MAX(-0.99,($BJ11/G11)^(1/5)-1)) -> -0.34225635 | BM11: =IF(BK11<=0,-0.99,MAX(-0.99,(BK11/G11)^(1/5)-1)) -> -0.20245465 | BN11: 2026-09-27 | BO11: 03/09/2026 | BP11: 24/11/2026 | BQ11: 821.9 | BR11: 202 | BS11: 159.3 | BT11: FUENTE: 10-K FY26 (EDGAR XBRL). OCF 1.129,7 - capex 277,3 - software 73,2 - SBC 821,9 = -42,7. D&A 148,5 -> capex de crecimiento 202,0 -> normalizado 159,3. Caja 928,4 + inversiones 2.545,8. Convertibles 1.696,4. Proximos ESTIMADOS por patron
A12: #VALUE! | B12: {=_FV(A12,"Símbolo bursátil",TRUE())} -> NTO | C12: IP owner | D12: Compounder | E12: {=_FV(A12,"Abreviatura de intercambio",TRUE())} -> XFRA | F12: {=_FV(A12,"Moneda")} -> EUR | G12: {=_FV(A12,"Precio")} -> 47.98 | H12: {=_FV(A12,"Acciones en circulación",TRUE())/1000000} -> 1287.26 | I12: =G12*H12 -> 61762.735 | J12: 1 | K12: 7 | L12: 3 | M12: 1 | N12: -1 | O12: 0.82 | P12: 1 | Q12: 0 | R12: =SUM(J12:N12)+SUM(P12:Q12) -> 12 | S12: =ROUND(R12/16*10,2) -> 7.5 | T12: 16 | U12: 17 | V12: 14 | W12: 10 | X12: 8 | Y12: 12 | Z12: 6 | AA12: -8 | AB12: =SUM(T12:AA12) -> 75 | AC12: =ROUND(AB12/10,2) -> 7.5 | AD12: 14 | AE12: -1 | AF12: 9 | AG12: 12 | AH12: 5 | AI12: 7 | AJ12: 14 | AK12: -3 | AL12: =SUM(AD12:AK12) -> 57 | AM12: =ROUND(AL12/70*10,2) -> 8.14 | AN12: =ROUND(S12*0.2+AC12*0.4+AM12*0.4,2) -> 7.76 | AO12: JPY | AP12: 1967908 | AQ12: 0 | AR12: =I12*'Framework Notes'!E4-AP12+AQ12 -> 9008565.2 | AS12: 262620 | AT12: 325400 | AU12: 461600 | AV12: 2258501 | AW12: =AR12/AS12 -> 34.302663 | AX12: =AR12/AU12 -> 19.515956 | AY12: =AR12/AV12 -> 3.9887364 | AZ12: 1600000 | BA12: =AT12/AV12 -> 0.14407786 | BB12: =AV12/AZ12 -> 1.4115631 | BC12: =BA12*BB12 -> 0.203375 | BD12: 262620 | BE12: =(BD12/AS12)^(1/5)-1 -> 0 | BF12: 483861 | BG12: =(BF12/AS12)^(1/5)-1 -> 0.13000031 | BH12: 15 | BI12: 22.5 | BJ12: =((BD12*BH12+$AP12-$AQ12)/$H12)/'Framework Notes'!E4 -> 25.821394 | BK12: =((BF12*BI12+$AP12-$AQ12)/$H12)/'Framework Notes'!E4 -> 56.190395 | BL12: =IF($BJ12<=0,-0.99,MAX(-0.99,($BJ12/G12)^(1/5)-1)) -> -0.11654611 | BM12: =IF(BK12<=0,-0.99,MAX(-0.99,(BK12/G12)^(1/5)-1)) -> 0.03209665 | BN12: 2026-08-25 | BO12: 06/08/2026 | BP12: 05/11/2026 | BQ12: 0 | BR12: 11315 | BS12: 273935 | BT12: no reportado (0)
A13: #VALUE! | B13: {=_FV(A13,"Símbolo bursátil",TRUE())} -> AMZN | C13: Mag 7 | D13: Compounder | E13: {=_FV(A13,"Abreviatura de intercambio",TRUE())} -> XNAS | F13: {=_FV(A13,"Moneda")} -> USD | G13: {=_FV(A13,"Precio")} -> 262.278 | H13: {=_FV(A13,"Acciones en circulación",TRUE())/1000000} -> 10786.31 | I13: =G13*H13 -> 2829011.8 | J13: 1.5 | K13: 8 | L13: 3 | M13: 1 | N13: 0 | O13: 0.72 | P13: 1 | Q13: 0.5 | R13: =SUM(J13:N13)+SUM(P13:Q13) -> 15 | S13: =ROUND(R13/16*10,2) -> 9.38 | T13: 14 | U13: 19 | V13: 15 | W13: 10 | X13: 9 | Y13: 12 | Z13: 6 | AA13: -8 | AB13: =SUM(T13:AA13) -> 77 | AC13: =ROUND(AB13/10,2) -> 7.7 | AD13: 14 | AE13: -1 | AF13: 3 | AG13: 13 | AH13: 4 | AI13: 8 | AJ13: 14 | AK13: -5 | AL13: =SUM(AD13:AK13) -> 50 | AM13: =ROUND(AL13/70*10,2) -> 7.14 | AN13: =ROUND(S13*0.2+AC13*0.4+AM13*0.4,2) -> 7.81 | AO13: USD | AP13: 78213 | AQ13: 128894 | AR13: =I13-AP13+AQ13 -> 2879692.8 | AS13: 58282 | AT13: 55000 | AU13: 138000 | AV13: 775656 | AW13: =AR13/AS13 -> 49.409643 | AX13: =AR13/AU13 -> 20.867339 | AY13: =AR13/AV13 -> 3.7125901 | AZ13: 300000 | BA13: =AT13/AV13 -> 0.070907722 | BB13: =AV13/AZ13 -> 2.58552 | BC13: =BA13*BB13 -> 0.18333333 | BD13: 70864 | BE13: =(BD13/AS13)^(1/5)-1 -> 0.039868071 | BF13: 122401.4 | BG13: =(BF13/AS13)^(1/5)-1 -> 0.1599797 | BH13: 22.5 | BI13: 30 | BJ13: =(BD13*BH13+$AP13-$AQ13)/$H13 -> 143.12207 | BK13: =(BF13*BI13+$AP13-$AQ13)/$H13 -> 335.73678 | BL13: =IF($BJ13<=0,-0.99,MAX(-0.99,($BJ13/G13)^(1/5)-1)) -> -0.11409134 | BM13: =IF(BK13<=0,-0.99,MAX(-0.99,(BK13/G13)^(1/5)-1)) -> 0.050624228 | BN13: 2026-08-25 | BO13: 30/07/2026 | BP13: 29/10/2026 | BQ13: 19810 | BR13: 80564 | BS13: 58282 | BT13: NORMALIZADO: FCF-SBC -22.282 + capex crecimiento 80.564 (capex 151.003 - D&A 70.439 como mantenimiento). TTM Q2-26. FCF@5y escalado x0,758
A14: #VALUE! | B14: {=_FV(A14,"Símbolo bursátil",TRUE())} -> SU | C14: Electrify | D14: Compounder | E14: {=_FV(A14,"Abreviatura de intercambio",TRUE())} -> XPAR | F14: {=_FV(A14,"Moneda")} -> EUR | G14: {=_FV(A14,"Precio")} -> 252.6 | H14: {=_FV(A14,"Acciones en circulación",TRUE())/1000000} -> 578.6053 | I14: =G14*H14 -> 146155.7 | J14: 1 | K14: 7 | L14: 3 | M14: 1 | N14: 0 | O14: 0.84 | P14: 1 | Q14: 0 | R14: =SUM(J14:N14)+SUM(P14:Q14) -> 13 | S14: =ROUND(R14/16*10,2) -> 8.13 | T14: 15 | U14: 17 | V14: 15 | W14: 10 | X14: 9 | Y14: 13 | Z14: 5 | AA14: -7 | AB14: =SUM(T14:AA14) -> 77 | AC14: =ROUND(AB14/10,2) -> 7.7 | AD14: 14 | AE14: -1 | AF14: 6 | AG14: 13 | AH14: 3 | AI14: 8 | AJ14: 13 | AK14: -3 | AL14: =SUM(AD14:AK14) -> 53 | AM14: =ROUND(AL14/70*10,2) -> 7.57 | AN14: =ROUND(S14*0.2+AC14*0.4+AM14*0.4,2) -> 7.73 | AO14: EUR | AP14: 4520 | AQ14: 20810 | AR14: =I14-AP14+AQ14 -> 162445.7 | AS14: 4588 | AT14: 5727 | AU14: 8520 | AV14: 42040 | AW14: =AR14/AS14 -> 35.406648 | AX14: =AR14/AU14 -> 19.066397 | AY14: =AR14/AV14 -> 3.8640747 | AZ14: 43259 | BA14: =AT14/AV14 -> 0.1362274 | BB14: =AV14/AZ14 -> 0.97182089 | BC14: =BA14*BB14 -> 0.13238864 | BD14: 5855.3 | BE14: =(BD14/AS14)^(1/5)-1 -> 0.049989965 | BF14: 8453.1 | BG14: =(BF14/AS14)^(1/5)-1 -> 0.1300002 | BH14: 17.5 | BI14: 25 | BJ14: =(BD14*BH14+$AP14-$AQ14)/$H14 -> 148.94048 | BK14: =(BF14*BI14+$AP14-$AQ14)/$H14 -> 337.08212 | BL14: =IF($BJ14<=0,-0.99,MAX(-0.99,($BJ14/G14)^(1/5)-1)) -> -0.10026238 | BM14: =IF(BK14<=0,-0.99,MAX(-0.99,(BK14/G14)^(1/5)-1)) -> 0.059401232 | BN14: 2026-08-26 | BO14: 30/07/2026 | BP14: 29/10/2026 | BQ14: 0 | BR14: 0 | BS14: 4588 | BT14: no reportado (0)
A15: #VALUE! | B15: {=_FV(A15,"Símbolo bursátil",TRUE())} -> ITX | C15: Consumo | D15: Compounder | E15: {=_FV(A15,"Abreviatura de intercambio",TRUE())} -> BMEX | F15: {=_FV(A15,"Moneda")} -> EUR | G15: {=_FV(A15,"Precio")} -> 55.42 | H15: {=_FV(A15,"Acciones en circulación",TRUE())/1000000} -> 3116.652 | I15: =G15*H15 -> 172724.85 | J15: 0 | K15: 6.5 | L15: 1.5 | M15: 1 | N15: 0 | O15: 0.74 | P15: 1 | Q15: 1 | R15: =SUM(J15:N15)+SUM(P15:Q15) -> 11 | S15: =ROUND(R15/16*10,2) -> 6.88 | T15: 16 | U15: 17 | V15: 10 | W15: 10 | X15: 9 | Y15: 13 | Z15: 10 | AA15: -8 | AB15: =SUM(T15:AA15) -> 77 | AC15: =ROUND(AB15/10,2) -> 7.7 | AD15: 15 | AE15: -1 | AF15: 8 | AG15: 13 | AH15: 5 | AI15: 9 | AJ15: 13 | AK15: -4 | AL15: =SUM(AD15:AK15) -> 58 | AM15: =ROUND(AL15/70*10,2) -> 8.29 | AN15: =ROUND(S15*0.2+AC15*0.4+AM15*0.4,2) -> 7.77 | AO15: EUR | AP15: 10399 | AQ15: 1 | AR15: =I15-AP15+AQ15 -> 162326.85 | AS15: 5706 | AT15: 6241 | AU15: 9797 | AV15: 41262 | AW15: =AR15/AS15 -> 28.44845 | AX15: =AR15/AU15 -> 16.569037 | AY15: =AR15/AV15 -> 3.934052 | AZ15: 24023 | BA15: =AT15/AV15 -> 0.15125297 | BB15: =AV15/AZ15 -> 1.717604 | BC15: =BA15*BB15 -> 0.2597927 | BD15: 7080.8 | BE15: =(BD15/AS15)^(1/5)-1 -> 0.044119272 | BF15: 8954.9 | BG15: =(BF15/AS15)^(1/5)-1 -> 0.094323674 | BH15: 16 | BI15: 24 | BJ15: =(BD15*BH15+$AP15-$AQ15)/$H15 -> 39.687074 | BK15: =(BF15*BI15+$AP15-$AQ15)/$H15 -> 72.294116 | BL15: =IF($BJ15<=0,-0.99,MAX(-0.99,($BJ15/G15)^(1/5)-1)) -> -0.064601836 | BM15: =IF(BK15<=0,-0.99,MAX(-0.99,(BK15/G15)^(1/5)-1)) -> 0.054598831 | BN15: 2026-09-27 | BO15: 09/09/2026 | BP15: 02/12/2026 | BQ15: 113 | BR15: 0 | BS15: 5706 | BT15: FUENTE: cuentas anuales consolidadas FY25 (nota 8, nota 16, estado de cambios en el patrimonio), nota FY25 y anexos H1-26 de Inditex. LTM = FY25 + H1-26 - H1-25. FCF de Inditex DESPUES DE ALQUILERES: OCF 10.439 - capex 2.750 - pagos fijos de arrendamiento 1.870 = 5.819; menos SBC 113 (reconocimiento de pagos en acciones FY25, proxy LTM) = 5.706. Deuda solo financiera (1); pasivos por arrendamiento 6.197 fuera. EBITDA post-alquileres 11.666 - 1.870. Capex de crecimiento (capex - amortizacion de inmovilizado SIN derechos de uso): FY25 2.712 - 1.545 = 1.167; NO sumado en BS hasta que Roger decida (deep dive 27-sep, pregunta 1). FCF@5y y multiplos provisionales (pregunta 2). 9M: 2-dic-2026 (Inditex)
A16: #VALUE! | B16: {=_FV(A16,"Símbolo bursátil",TRUE())} -> LOTB | C16: Consumo | D16: Compounder | E16: {=_FV(A16,"Abreviatura de intercambio",TRUE())} -> XBRU | F16: {=_FV(A16,"Moneda")} -> EUR | G16: {=_FV(A16,"Precio")} -> 13000 | H16: {=_FV(A16,"Acciones en circulación",TRUE())/1000000} -> 0.81601 | I16: =G16*H16 -> 10608.13 | J16: 0 | K16: 7 | L16: 3 | M16: 1 | N16: -1 | O16: 0.76 | P16: 1 | Q16: 1 | R16: =SUM(J16:N16)+SUM(P16:Q16) -> 12 | S16: =ROUND(R16/16*10,2) -> 7.5 | T16: 16 | U16: 16 | V16: 14 | W16: 9 | X16: 9 | Y16: 13 | Z16: 10 | AA16: -7 | AB16: =SUM(T16:AA16) -> 80 | AC16: =ROUND(AB16/10,2) -> 8 | AD16: 14 | AE16: -1 | AF16: 6 | AG16: 13 | AH16: 4 | AI16: 9 | AJ16: 13 | AK16: -3 | AL16: =SUM(AD16:AK16) -> 55 | AM16: =ROUND(AL16/70*10,2) -> 7.86 | AN16: =ROUND(S16*0.2+AC16*0.4+AM16*0.4,2) -> 7.84 | AO16: EUR | AP16: 274 | AQ16: 409 | AR16: =I16-AP16+AQ16 -> 10743.13 | AS16: 90.8 | AT16: 190 | AU16: 291 | AV16: 1450 | AW16: =AR16/AS16 -> 118.31641 | AX16: =AR16/AU16 -> 36.917973 | AY16: =AR16/AV16 -> 7.4090552 | AZ16: 1309 | BA16: =AT16/AV16 -> 0.13103448 | BB16: =AV16/AZ16 -> 1.1077158 | BC16: =BA16*BB16 -> 0.14514897 | BD16: 127.5 | BE16: =(BD16/AS16)^(1/5)-1 -> 0.07024909 | BF16: 167.5 | BG16: =(BF16/AS16)^(1/5)-1 -> 0.13027935 | BH16: 15 | BI16: 25 | BJ16: =(BD16*BH16+$AP16-$AQ16)/$H16 -> 2178.2821 | BK16: =(BF16*BI16+$AP16-$AQ16)/$H16 -> 4966.2382 | BL16: =IF($BJ16<=0,-0.99,MAX(-0.99,($BJ16/G16)^(1/5)-1)) -> -0.3004252 | BM16: =IF(BK16<=0,-0.99,MAX(-0.99,(BK16/G16)^(1/5)-1)) -> -0.17507049 | BN16: 2026-08-25 | BO16: 07/08/2026 | BP16: 25/02/2027 | BQ16: 2.1 | BR16: 72.8 | BS16: 163.6 | BT16: anual
A17: #VALUE! | B17: {=_FV(A17,"Símbolo bursátil",TRUE())} -> HLMA | C17: Healthcare | D17: Compounder | E17: {=_FV(A17,"Abreviatura de intercambio",TRUE())} -> XLON | F17: {=_FV(A17,"Moneda")} -> GBp | G17: {=_FV(A17,"Precio")} -> 3412 | H17: {=_FV(A17,"Acciones en circulación",TRUE())/1000000} -> 379.6453 | I17: =G17/100*H17 -> 12953.498 | J17: 2 | K17: 6 | L17: 3 | M17: 1 | N17: 0 | O17: 0.86 | P17: 1 | Q17: 0 | R17: =SUM(J17:N17)+SUM(P17:Q17) -> 13 | S17: =ROUND(R17/16*10,2) -> 8.13 | T17: 13 | U17: 15 | V17: 12 | W17: 10 | X17: 10 | Y17: 12 | Z17: 6 | AA17: -7 | AB17: =SUM(T17:AA17) -> 71 | AC17: =ROUND(AB17/10,2) -> 7.1 | AD17: 15 | AE17: -1 | AF17: 8 | AG17: 14 | AH17: 4 | AI17: 8 | AJ17: 13 | AK17: -3 | AL17: =SUM(AD17:AK17) -> 58 | AM17: =ROUND(AL17/70*10,2) -> 8.29 | AN17: =ROUND(S17*0.2+AC17*0.4+AM17*0.4,2) -> 7.78 | AO17: GBP | AP17: 143.4 | AQ17: 913.4 | AR17: =I17-AP17+AQ17 -> 13723.498 | AS17: 392.4 | AT17: 403 | AU17: 622.8 | AV17: 2580 | AW17: =AR17/AS17 -> 34.973236 | AX17: =AR17/AU17 -> 22.03516 | AY17: =AR17/AV17 -> 5.3191851 | AZ17: 3191 | BA17: =AT17/AV17 -> 0.15620155 | BB17: =AV17/AZ17 -> 0.80852397 | BC17: =BA17*BB17 -> 0.1262927 | BD17: 500.8 | BE17: =(BD17/AS17)^(1/5)-1 -> 0.049994597 | BF17: 722.9 | BG17: =(BF17/AS17)^(1/5)-1 -> 0.12997763 | BH17: 18 | BI17: 28 | BJ17: =(BD17*BH17+$AP17-$AQ17)/$H17*100 -> 2171.606 | BK17: =(BF17*BI17+$AP17-$AQ17)/$H17*100 -> 5128.7873 | BL17: =IF($BJ17<=0,-0.99,MAX(-0.99,($BJ17/G17)^(1/5)-1)) -> -0.086403555 | BM17: =IF(BK17<=0,-0.99,MAX(-0.99,(BK17/G17)^(1/5)-1)) -> 0.084928539 | BN17: 2026-08-26 | BO17: 11/06/2026 | BP17: 19/11/2026 | BQ17: 17.2 | BR17: 0 | BS17: 392.4 | BT17: anual | Trading update 24-sep-2026 (RNS): guia de margen EBIT ajustado FY27 sube a 23,5-24% (antes ~22,7%); organico a divisa constante de dos digitos bajos (fotonica ~+30%, aporta ~5 pp); 6 adquisiciones por 515 M GBP (record) y 3 desinversiones por 83; la libra fuerte resta. Semestrales el 19-nov-2026 (confirmado)
A18: #VALUE! | B18: {=_FV(A18,"Símbolo bursátil",TRUE())} -> FICO | C18: Vertical Saas | D18: Compounder | E18: {=_FV(A18,"Abreviatura de intercambio",TRUE())} -> XNYS | F18: {=_FV(A18,"Moneda")} -> USD | G18: {=_FV(A18,"Precio")} -> 778.995 | H18: {=_FV(A18,"Acciones en circulación",TRUE())/1000000} -> 21.59764 | I18: =G18*H18 -> 16824.454 | J18: 0 | K18: 8 | L18: 2 | M18: 1 | N18: -1 | O18: 0.78 | P18: 1 | Q18: 0 | R18: =SUM(J18:N18)+SUM(P18:Q18) -> 11 | S18: =ROUND(R18/16*10,2) -> 6.88 | T18: 16 | U18: 19 | V18: 10 | W18: 7 | X18: 10 | Y18: 12 | Z18: 5 | AA18: -15 | AB18: =SUM(T18:AA18) -> 64 | AC18: =ROUND(AB18/10,2) -> 6.4 | AD18: 14 | AE18: 0 | AF18: 10 | AG18: 14 | AH18: 4 | AI18: 8 | AJ18: 13 | AK18: -7 | AL18: =SUM(AD18:AK18) -> 56 | AM18: =ROUND(AL18/70*10,2) -> 8 | AN18: =ROUND(S18*0.2+AC18*0.4+AM18*0.4,2) -> 7.14 | AO18: USD | AP18: 248.4 | AQ18: 5582.4 | AR18: =I18-AP18+AQ18 -> 22158.454 | AS18: 786.6 | AT18: 946 | AU18: 1252 | AV18: 2393.6 | AW18: =AR18/AS18 -> 28.169913 | AX18: =AR18/AU18 -> 17.698445 | AY18: =AR18/AV18 -> 9.2573753 | AZ18: 2200 | BA18: =AT18/AV18 -> 0.39522059 | BB18: =AV18/AZ18 -> 1.088 | BC18: =BA18*BB18 -> 0.43 | BD18: 730 | BE18: =(BD18/AS18)^(1/5)-1 -> -0.01482409 | BF18: 1670 | BG18: =(BF18/AS18)^(1/5)-1 -> 0.16249878 | BH18: 18 | BI18: 26 | BJ18: =(BD18*BH18+$AP18-$AQ18)/$H18 -> 361.42838 | BK18: =(BF18*BI18+$AP18-$AQ18)/$H18 -> 1763.4334 | BL18: =IF($BJ18<=0,-0.99,MAX(-0.99,($BJ18/G18)^(1/5)-1)) -> -0.14237484 | BM18: =IF(BK18<=0,-0.99,MAX(-0.99,(BK18/G18)^(1/5)-1)) -> 0.17751075 | BN18: 2026-08-26 | BO18: 29/07/2026 | BP18: 05/11/2026 | BQ18: 174.3 | BR18: 0 | BS18: 786.6 | BT18: FUENTE: 10-Q Q3 FY26 (EDGAR XBRL, 30-jun-2026). LTM: OCF 1.001,5 - capex 5,5 - software capitalizado 35,1 - SBC 174,3 = 786,6. Ingresos 2.393,6; EBIT 1.236,3; EBITDA 1.252 (EBIT + D&A 16,1); NOPAT 946 (EBIT x (1-23,5%)). Caja 248,4; deuda 5.582,4 (recompras de 3.046 en 9M financiadas con deuda; la fila llevaba 2.400, dato viejo). 28-sep-2026: la FHFA anuncia una sola tabla de precios (LLPA) para FICO Classic y VantageScore 4.0, sin el ajuste de 20 puntos: el riesgo regulatorio de la tesis se ha materializado. FCF@5y y multiplos pendientes de Roger. Proximos: ~5-nov-2026 (estimado)
A19: #VALUE! | B19: {=_FV(A19,"Símbolo bursátil",TRUE())} -> LIFCO B | C19: Industrial | D19: Compounder | E19: {=_FV(A19,"Abreviatura de intercambio",TRUE())} -> XSTO | F19: {=_FV(A19,"Moneda")} -> SEK | G19: {=_FV(A19,"Precio")} -> 327.6 | H19: {=_FV(A19,"Acciones en circulación",TRUE())/1000000} -> 423.8365 | I19: =G19*H19 -> 138848.84 | J19: 0 | K19: 7 | L19: 3 | M19: 1 | N19: 0 | O19: 0.7 | P19: 0.5 | Q19: 1 | R19: =SUM(J19:N19)+SUM(P19:Q19) -> 12.5 | S19: =ROUND(R19/16*10,2) -> 7.81 | T19: 15 | U19: 15 | V19: 12 | W19: 10 | X19: 9 | Y19: 13 | Z19: 10 | AA19: -7 | AB19: =SUM(T19:AA19) -> 77 | AC19: =ROUND(AB19/10,2) -> 7.7 | AD19: 14 | AE19: -1 | AF19: 7 | AG19: 14 | AH19: 4 | AI19: 9 | AJ19: 13 | AK19: -3 | AL19: =SUM(AD19:AK19) -> 57 | AM19: =ROUND(AL19/70*10,2) -> 8.14 | AN19: =ROUND(S19*0.2+AC19*0.4+AM19*0.4,2) -> 7.9 | AO19: SEK | AP19: 3000 | AQ19: 12500 | AR19: =I19-AP19+AQ19 -> 148348.84 | AS19: 4373 | AT19: 3400 | AU19: 6627 | AV19: 29251 | AW19: =AR19/AS19 -> 33.923814 | AX19: =AR19/AU19 -> 22.385519 | AY19: =AR19/AV19 -> 5.0715817 | AZ19: 22000 | BA19: =AT19/AV19 -> 0.11623534 | BB19: =AV19/AZ19 -> 1.3295909 | BC19: =BA19*BB19 -> 0.15454545 | BD19: 5069.2 | BE19: =(BD19/AS19)^(1/5)-1 -> 0.029987585 | BF19: 8331 | BG19: =(BF19/AS19)^(1/5)-1 -> 0.13758415 | BH19: 16 | BI19: 26 | BJ19: =(BD19*BH19+$AP19-$AQ19)/$H19 -> 168.95006 | BK19: =(BF19*BI19+$AP19-$AQ19)/$H19 -> 488.64598 | BL19: =IF($BJ19<=0,-0.99,MAX(-0.99,($BJ19/G19)^(1/5)-1)) -> -0.1240428 | BM19: =IF(BK19<=0,-0.99,MAX(-0.99,(BK19/G19)^(1/5)-1)) -> 0.083253464 | BN19: 2026-08-26 | BO19: 14/07/2026 | BP19: 22/10/2026 | BQ19: 0 | BR19: 0 | BS19: 4373 | BT19: no reportado (0)
A20: #VALUE! | B20: {=_FV(A20,"Símbolo bursátil",TRUE())} -> EVD | C20: Consumo | D20: Compounder | E20: {=_FV(A20,"Abreviatura de intercambio",TRUE())} -> XFRA | F20: {=_FV(A20,"Moneda")} -> EUR | G20: {=_FV(A20,"Precio")} -> 61 | H20: {=_FV(A20,"Acciones en circulación",TRUE())/1000000} -> 96 | I20: =G20*H20 -> 5856 | J20: 0.5 | K20: 7 | L20: 2 | M20: 0.5 | N20: -0.5 | O20: 0.5 | P20: 0.5 | Q20: 0.5 | R20: =SUM(J20:N20)+SUM(P20:Q20) -> 10.5 | S20: =ROUND(R20/16*10,2) -> 6.56 | T20: 14 | U20: 15.5 | V20: 14 | W20: 8 | X20: 7 | Y20: 12 | Z20: 9 | AA20: -12 | AB20: =SUM(T20:AA20) -> 67.5 | AC20: =ROUND(AB20/10,2) -> 6.75 | AD20: 13 | AE20: -5 | AF20: 8.5 | AG20: 12 | AH20: 3 | AI20: 8 | AJ20: 12.5 | AK20: -5 | AL20: =SUM(AD20:AK20) -> 47 | AM20: =ROUND(AL20/70*10,2) -> 6.71 | AN20: =ROUND(S20*0.2+AC20*0.4+AM20*0.4,2) -> 6.7 | AO20: EUR | AP20: 1605 | AQ20: 1404.2 | AR20: =I20-AP20+AQ20 -> 5655.2 | AS20: 60 | AT20: 331.4 | AU20: 603.1 | AV20: 3297.9 | AW20: =AR20/AS20 -> 94.253333 | AX20: =AR20/AU20 -> 9.3768861 | AY20: =AR20/AV20 -> 1.7147882 | AZ20: 1573 | BA20: =AT20/AV20 -> 0.10048819 | BB20: =AV20/AZ20 -> 2.0965671 | BC20: =BA20*BB20 -> 0.21068023 | BD20: 242.3 | BE20: =(BD20/AS20)^(1/5)-1 -> 0.32202733 | BF20: 445.1 | BG20: =(BF20/AS20)^(1/5)-1 -> 0.49300502 | BH20: 12 | BI20: 20 | BJ20: =(BD20*BH20+$AP20-$AQ20)/$H20 -> 32.379167 | BK20: =(BF20*BI20+$AP20-$AQ20)/$H20 -> 94.820833 | BL20: =IF($BJ20<=0,-0.99,MAX(-0.99,($BJ20/G20)^(1/5)-1)) -> -0.11897716 | BM20: =IF(BK20<=0,-0.99,MAX(-0.99,(BK20/G20)^(1/5)-1)) -> 0.092231724 | BN20: 2026-09-27 | BO20: 20/08/2026 | BP20: 12/11/2026 | BQ20: 0 | BR20: 203.4 | BS20: 263.4 | BT20: FUENTE: informe anual 2025 y semestral 2026 (corporate.eventim.de). OJO: 1.089 de la caja (dic-25) es DINERO DE ENTRADAS DE PROMOTORES; la propia CTS calcula caja neta 200,8 (caja+valores 1.605 - deuda incl. dinero de entradas y arrendamientos 1.404). FCF FY25 tras alquileres: OCF 364,7 - capex 278,9 - arrend. 25,8 = 60,0 (LTM no computable: el semestral no separa capex). Capex de crecimiento (Arena Milano) 278,9 - 75,5 = 203,4. El OCF lleva +49 de dinero de entradas: PREGUNTA ABIERTA de metodo. Proximos estimados | 30-sep-2026: el CFO William Willms sale del consejo con efecto inmediato, sin motivo comunicado; interino Philipp Knigge
A21: #VALUE! | B21: {=_FV(A21,"Símbolo bursátil",TRUE())} -> MNST | C21: Consumo | D21: Compounder | E21: {=_FV(A21,"Abreviatura de intercambio",TRUE())} -> XNAS | F21: {=_FV(A21,"Moneda")} -> USD | G21: {=_FV(A21,"Precio")} -> 47.1 | H21: {=_FV(A21,"Acciones en circulación",TRUE())/1000000} -> 1956.016 | I21: =G21*H21 -> 92128.354 | J21: 0 | K21: 7 | L21: 2 | M21: 1 | N21: -1 | O21: 0.78 | P21: 1 | Q21: 1 | R21: =SUM(J21:N21)+SUM(P21:Q21) -> 11 | S21: =ROUND(R21/16*10,2) -> 6.88 | T21: 16 | U21: 17 | V21: 12 | W21: 9 | X21: 9 | Y21: 12 | Z21: 9 | AA21: -9 | AB21: =SUM(T21:AA21) -> 75 | AC21: =ROUND(AB21/10,2) -> 7.5 | AD21: 13 | AE21: -1 | AF21: 9 | AG21: 12 | AH21: 5 | AI21: 9 | AJ21: 13 | AK21: -4 | AL21: =SUM(AD21:AK21) -> 56 | AM21: =ROUND(AL21/70*10,2) -> 8 | AN21: =ROUND(S21*0.2+AC21*0.4+AM21*0.4,2) -> 7.58 | AO21: USD | AP21: 3419 | AQ21: 93 | AR21: =I21-AP21+AQ21 -> 88802.354 | AS21: 1945.7 | AT21: 2154 | AU21: 2930 | AV21: 9220 | AW21: =AR21/AS21 -> 45.640311 | AX21: =AR21/AU21 -> 30.307971 | AY21: =AR21/AV21 -> 9.6314917 | AZ21: 9665 | BA21: =AT21/AV21 -> 0.23362256 | BB21: =AV21/AZ21 -> 0.95395758 | BC21: =BA21*BB21 -> 0.22286601 | BD21: 2367.3 | BE21: =(BD21/AS21)^(1/5)-1 -> 0.040005136 | BF21: 3745.9 | BG21: =(BF21/AS21)^(1/5)-1 -> 0.13997692 | BH21: 18 | BI21: 24 | BJ21: =(BD21*BH21+$AP21-$AQ21)/$H21 -> 23.485186 | BK21: =(BF21*BI21+$AP21-$AQ21)/$H21 -> 47.661982 | BL21: =IF($BJ21<=0,-0.99,MAX(-0.99,($BJ21/G21)^(1/5)-1)) -> -0.12992915 | BM21: =IF(BK21<=0,-0.99,MAX(-0.99,(BK21/G21)^(1/5)-1)) -> 0.0023750284 | BN21: 2026-08-25 | BO21: 06/08/2026 | BP21: 05/11/2026 | BQ21: 135.8 | BR21: 37.1 | BS21: 1982.8 | BT21: trimestral | 25-sep-2026 (8-K): Rob Gehring, CEO Americas, se va a Coca-Cola el 30-nov
A22: #VALUE! | B22: {=_FV(A22,"Símbolo bursátil",TRUE())} -> ABNB | C22: Consumo | D22: Growth | E22: {=_FV(A22,"Abreviatura de intercambio",TRUE())} -> XNAS | F22: {=_FV(A22,"Moneda")} -> USD | G22: {=_FV(A22,"Precio")} -> 175.025 | H22: {=_FV(A22,"Acciones en circulación",TRUE())/1000000} -> 589.5857 | I22: =G22*H22 -> 103192.24 | J22: 1.5 | K22: 6 | L22: 2 | M22: 1 | N22: 0 | O22: 0.82 | P22: 1 | Q22: 1 | R22: =SUM(J22:N22)+SUM(P22:Q22) -> 12.5 | S22: =ROUND(R22/16*10,2) -> 7.81 | T22: 14 | U22: 17 | V22: 14 | W22: 9 | X22: 7 | Y22: 12 | Z22: 9 | AA22: -10 | AB22: =SUM(T22:AA22) -> 72 | AC22: =ROUND(AB22/10,2) -> 7.2 | AD22: 12 | AE22: -2 | AF22: 10 | AG22: 11 | AH22: 4 | AI22: 8 | AJ22: 12 | AK22: -5 | AL22: =SUM(AD22:AK22) -> 50 | AM22: =ROUND(AL22/70*10,2) -> 7.14 | AN22: =ROUND(S22*0.2+AC22*0.4+AM22*0.4,2) -> 7.3 | AO22: USD | AP22: 12069 | AQ22: 2496 | AR22: =I22-AP22+AQ22 -> 93619.237 | AS22: 3153 | AT22: 2081 | AU22: 2874 | AV22: 13159 | AW22: =AR22/AS22 -> 29.692115 | AX22: =AR22/AU22 -> 32.574543 | AY22: =AR22/AV22 -> 7.1144644 | AZ22: 10662 | BA22: =AT22/AV22 -> 0.15814272 | BB22: =AV22/AZ22 -> 1.2341962 | BC22: =BA22*BB22 -> 0.19517914 | BD22: 3350.1 | BE22: =(BD22/AS22)^(1/5)-1 -> 0.012200995 | BF22: 6342.1 | BG22: =(BF22/AS22)^(1/5)-1 -> 0.15001055 | BH22: 16 | BI22: 24 | BJ22: =(BD22*BH22+$AP22-$AQ22)/$H22 -> 107.15083 | BK22: =(BF22*BI22+$AP22-$AQ22)/$H22 -> 274.40184 | BL22: =IF($BJ22<=0,-0.99,MAX(-0.99,($BJ22/G22)^(1/5)-1)) -> -0.093476442 | BM22: =IF(BK22<=0,-0.99,MAX(-0.99,(BK22/G22)^(1/5)-1)) -> 0.094100927 | BN22: 2026-08-25 | BO22: 06/08/2026 | BP22: 05/11/2026 | BQ22: 1707 | BR22: 0 | BS22: 3153 | BT22: trimestral
A23: #VALUE! | B23: {=_FV(A23,"Símbolo bursátil",TRUE())} -> DNP | C23: Defensive | D23: Defensive | E23: {=_FV(A23,"Abreviatura de intercambio",TRUE())} -> XWAR | F23: {=_FV(A23,"Moneda")} -> PLN | G23: {=_FV(A23,"Precio")} -> 38.7 | H23: {=_FV(A23,"Acciones en circulación",TRUE())/1000000} -> 980.4 | I23: =G23*H23 -> 37941.48 | J23: 0.5 | K23: 7 | L23: 2 | M23: 1 | N23: 0 | O23: 0.3 | P23: 1 | Q23: 1 | R23: =SUM(J23:N23)+SUM(P23:Q23) -> 12.5 | S23: =ROUND(R23/16*10,2) -> 7.81 | T23: 14 | U23: 16 | V23: 14 | W23: 10 | X23: 9 | Y23: 12 | Z23: 10 | AA23: -7 | AB23: =SUM(T23:AA23) -> 78 | AC23: =ROUND(AB23/10,2) -> 7.8 | AD23: 13 | AE23: -2 | AF23: 4 | AG23: 13 | AH23: 3 | AI23: 9 | AJ23: 13 | AK23: -4 | AL23: =SUM(AD23:AK23) -> 49 | AM23: =ROUND(AL23/70*10,2) -> 7 | AN23: =ROUND(S23*0.2+AC23*0.4+AM23*0.4,2) -> 7.48 | AO23: PLN | AP23: 771 | AQ23: 852 | AR23: =I23-AP23+AQ23 -> 38022.48 | AS23: 669.1 | AT23: 1656 | AU23: 2609 | AV23: 35628 | AW23: =AR23/AS23 -> 56.826304 | AX23: =AR23/AU23 -> 14.573584 | AY23: =AR23/AV23 -> 1.0672078 | AZ23: 9909 | BA23: =AT23/AV23 -> 0.046480296 | BB23: =AV23/AZ23 -> 3.5955192 | BC23: =BA23*BB23 -> 0.1671208 | BD23: 756.3 | BE23: =(BD23/AS23)^(1/5)-1 -> 0.024803533 | BF23: 1345.8 | BG23: =(BF23/AS23)^(1/5)-1 -> 0.15000015 | BH23: 15 | BI23: 20 | BJ23: =(BD23*BH23+$AP23-$AQ23)/$H23 -> 11.488678 | BK23: =(BF23*BI23+$AP23-$AQ23)/$H23 -> 27.371481 | BL23: =IF($BJ23<=0,-0.99,MAX(-0.99,($BJ23/G23)^(1/5)-1)) -> -0.21564654 | BM23: =IF(BK23<=0,-0.99,MAX(-0.99,(BK23/G23)^(1/5)-1)) -> -0.066923039 | BN23: 2026-08-25 | BO23: 13/08/2026 | BP23: 12/11/2026 | BQ23: 0 | BR23: 1460.2 | BS23: 2129.3 | BT23: no reportado (0)
A24: #VALUE! | B24: {=_FV(A24,"Símbolo bursátil",TRUE())} -> VLTO | C24: Industrial | D24: Compounder | E24: {=_FV(A24,"Abreviatura de intercambio",TRUE())} -> XNYS | F24: {=_FV(A24,"Moneda")} -> USD | G24: {=_FV(A24,"Precio")} -> 100.55 | H24: {=_FV(A24,"Acciones en circulación",TRUE())/1000000} -> 243.7933 | I24: =G24*H24 -> 24513.416 | J24: 2 | K24: 6.5 | L24: 1 | M24: 1 | N24: 0 | O24: 0 | P24: 0 | Q24: 0 | R24: =SUM(J24:N24)+SUM(P24:Q24) -> 10.5 | S24: =ROUND(R24/16*10,2) -> 6.56 | T24: 14 | U24: 17 | V24: 11 | W24: 10 | X24: 10 | Y24: 12 | Z24: 5 | AA24: -7 | AB24: =SUM(T24:AA24) -> 72 | AC24: =ROUND(AB24/10,2) -> 7.2 | AD24: 14 | AE24: -1 | AF24: 7 | AG24: 13 | AH24: 4 | AI24: 8 | AJ24: 13 | AK24: -3 | AL24: =SUM(AD24:AK24) -> 55 | AM24: =ROUND(AL24/70*10,2) -> 7.86 | AN24: =ROUND(S24*0.2+AC24*0.4+AM24*0.4,2) -> 7.34 | AO24: USD | AP24: 2120 | AQ24: 3590 | AR24: =I24-AP24+AQ24 -> 25983.416 | AS24: 973 | AT24: 1062 | AU24: 1390 | AV24: 5700 | AW24: =AR24/AS24 -> 26.704436 | AX24: =AR24/AU24 -> 18.693105 | AY24: =AR24/AV24 -> 4.5584941 | AZ24: 6501 | BA24: =AT24/AV24 -> 0.18631579 | BB24: =AV24/AZ24 -> 0.87678819 | BC24: =BA24*BB24 -> 0.16335948 | BD24: 1183.5 | BE24: =(BD24/AS24)^(1/5)-1 -> 0.039946708 | BF24: 1715.2 | BG24: =(BF24/AS24)^(1/5)-1 -> 0.12005767 | BH24: 12.5 | BI24: 20 | BJ24: =(BD24*BH24+$AP24-$AQ24)/$H24 -> 54.65183 | BK24: =(BF24*BI24+$AP24-$AQ24)/$H24 -> 134.67967 | BL24: =IF($BJ24<=0,-0.99,MAX(-0.99,($BJ24/G24)^(1/5)-1)) -> -0.11479364 | BM24: =IF(BK24<=0,-0.99,MAX(-0.99,(BK24/G24)^(1/5)-1)) -> 0.060190701 | BN24: 2026-08-26 | BO24: 28/07/2026 | BP24: 27/10/2026 | BQ24: 74 | BR24: 0 | BS24: 973 | BT24: trimestral
A25: #VALUE! | B25: {=_FV(A25,"Símbolo bursátil",TRUE())} -> LR | C25: Electrify | D25: Compounder | E25: {=_FV(A25,"Abreviatura de intercambio",TRUE())} -> XPAR | F25: {=_FV(A25,"Moneda")} -> EUR | G25: {=_FV(A25,"Precio")} -> 131.3 | H25: {=_FV(A25,"Acciones en circulación",TRUE())/1000000} -> 262.2457 | I25: =G25*H25 -> 34432.86 | J25: 1 | K25: 6 | L25: 2 | M25: 1 | N25: 0 | O25: 1 | P25: 0 | Q25: 0 | R25: =SUM(J25:N25)+SUM(P25:Q25) -> 10 | S25: =ROUND(R25/16*10,2) -> 6.25 | T25: 14 | U25: 14 | V25: 15 | W25: 10 | X25: 9 | Y25: 11 | Z25: 5 | AA25: -8 | AB25: =SUM(T25:AA25) -> 70 | AC25: =ROUND(AB25/10,2) -> 7 | AD25: 13 | AE25: -1 | AF25: 6 | AG25: 13 | AH25: 4 | AI25: 8 | AJ25: 12 | AK25: -3 | AL25: =SUM(AD25:AK25) -> 52 | AM25: =ROUND(AL25/70*10,2) -> 7.43 | AN25: =ROUND(S25*0.2+AC25*0.4+AM25*0.4,2) -> 7.02 | AO25: EUR | AP25: 1971 | AQ25: 7724 | AR25: =I25-AP25+AQ25 -> 40185.86 | AS25: 1256.4 | AT25: 1409 | AU25: 2319 | AV25: 10107 | AW25: =AR25/AS25 -> 31.984926 | AX25: =AR25/AU25 -> 17.328961 | AY25: =AR25/AV25 -> 3.9760424 | AZ25: 15683 | BA25: =AT25/AV25 -> 0.13940833 | BB25: =AV25/AZ25 -> 0.64445578 | BC25: =BA25*BB25 -> 0.089842505 | BD25: 1682.1 | BE25: =(BD25/AS25)^(1/5)-1 -> 0.060094977 | BF25: 2527.8 | BG25: =(BF25/AS25)^(1/5)-1 -> 0.15006651 | BH25: 13 | BI25: 24 | BJ25: =(BD25*BH25+$AP25-$AQ25)/$H25 -> 61.447337 | BK25: =(BF25*BI25+$AP25-$AQ25)/$H25 -> 209.39981 | BL25: =IF($BJ25<=0,-0.99,MAX(-0.99,($BJ25/G25)^(1/5)-1)) -> -0.14089219 | BM25: =IF(BK25<=0,-0.99,MAX(-0.99,(BK25/G25)^(1/5)-1)) -> 0.097848245 | BN25: 2026-08-26 | BO25: 06/08/2026 | BP25: 05/11/2026 | BQ25: 0 | BR25: 0 | BS25: 1256.4 | BT25: SBC no reportado (0). Capital Markets Day 28/29-sep-2026: objetivos 2027-30 suben a organico +6-8%/anio (antes +3-5%) + ~5% de perimetro, margen operativo ajustado 21-22%, FCF 13-15% de ventas, ~60% del FCF a adquisiciones, payout ~50%, deuda neta/EBITDA 1,5-2,5x, desinversiones de 0,5-1,0 mil M EUR de ventas; centros de datos 32% de ventas (>3.000 M EUR en 2026). Cifras LTM pendientes de fuente primaria (revisar NIIF 16)
A26: #VALUE! | B26: {=_FV(A26,"Símbolo bursátil",TRUE())} -> JDG | C26: Healthcare | D26: Compounder | E26: {=_FV(A26,"Abreviatura de intercambio",TRUE())} -> XLON | F26: {=_FV(A26,"Moneda")} -> GBp | G26: {=_FV(A26,"Precio")} -> 3430 | H26: {=_FV(A26,"Acciones en circulación",TRUE())/1000000} -> 6.66069 | I26: =G26/100*H26 -> 228.46167 | J26: 1 | K26: 5 | L26: 2 | M26: 0 | N26: 0 | O26: 1 | P26: 1 | Q26: 1 | R26: =SUM(J26:N26)+SUM(P26:Q26) -> 10 | S26: =ROUND(R26/16*10,2) -> 6.25 | T26: 12 | U26: 13 | V26: 12 | W26: 10 | X26: 8 | Y26: 13 | Z26: 10 | AA26: -9 | AB26: =SUM(T26:AA26) -> 69 | AC26: =ROUND(AB26/10,2) -> 6.9 | AD26: 13 | AE26: -2 | AF26: 6 | AG26: 13 | AH26: 2 | AI26: 9 | AJ26: 11 | AK26: -4 | AL26: =SUM(AD26:AK26) -> 48 | AM26: =ROUND(AL26/70*10,2) -> 6.86 | AN26: =ROUND(S26*0.2+AC26*0.4+AM26*0.4,2) -> 6.75 | AO26: GBP | AP26: 15.6 | AQ26: 60.9 | AR26: =I26-AP26+AQ26 -> 273.76167 | AS26: 11.8 | AT26: 3 | AU26: 21.6 | AV26: 131.3 | AW26: =AR26/AS26 -> 23.200141 | AX26: =AR26/AU26 -> 12.674151 | AY26: =AR26/AV26 -> 2.0850089 | AZ26: 158 | BA26: =AT26/AV26 -> 0.022848439 | BB26: =AV26/AZ26 -> 0.83101266 | BC26: =BA26*BB26 -> 0.018987342 | BD26: 22.5 | BE26: =(BD26/AS26)^(1/5)-1 -> 0.13778473 | BF26: 48.3 | BG26: =(BF26/AS26)^(1/5)-1 -> 0.32560162 | BH26: 10 | BI26: 20 | BJ26: =(BD26*BH26+$AP26-$AQ26)/$H26*100 -> 2697.9187 | BK26: =(BF26*BI26+$AP26-$AQ26)/$H26*100 -> 13822.892 | BL26: =IF($BJ26<=0,-0.99,MAX(-0.99,($BJ26/G26)^(1/5)-1)) -> -0.046881395 | BM26: =IF(BK26<=0,-0.99,MAX(-0.99,(BK26/G26)^(1/5)-1)) -> 0.32148111 | BN26: 2026-09-27 | BO26: 23/09/2026 | BP26: 21/01/2027 | BQ26: 1.2 | BR26: 0 | BS26: 11.8 | BT26: FUENTE: RNS interinos 23-sep-2026 + preliminares FY25. FCF sin intereses, tras alquileres y SBC: FY25 ~19,8 - 1S25 6,1 + 1S26 (-1,9) = 11,8 LTM (arrend. FY25 ~1,8 estimado). Deuda 58,6 + contraprestaciones 2,3 (excl. NIIF 16); caja 15,6 -> 45,3 = deuda neta ajustada de la compania, 2,1x su EBITDA de covenant (21,6). NOPAT estatutario LTM ~3. FCF@5y SIN escalar. Proximo: trading update (estimado)
A27: #VALUE! | B27: {=_FV(A27,"Símbolo bursátil",TRUE())} -> STMN | C27: Healthcare | D27: Compounder | E27: {=_FV(A27,"Abreviatura de intercambio",TRUE())} -> XSWX | F27: {=_FV(A27,"Moneda")} -> CHF | G27: {=_FV(A27,"Precio")} -> 92.96 | H27: {=_FV(A27,"Acciones en circulación",TRUE())/1000000} -> 159.4552 | I27: =G27*H27 -> 14822.955 | J27: 2 | K27: 6 | L27: 2 | M27: 0 | N27: 0 | O27: 1 | P27: 0 | Q27: 0 | R27: =SUM(J27:N27)+SUM(P27:Q27) -> 10 | S27: =ROUND(R27/16*10,2) -> 6.25 | T27: 12 | U27: 15 | V27: 12 | W27: 9 | X27: 9 | Y27: 11 | Z27: 5 | AA27: -8 | AB27: =SUM(T27:AA27) -> 65 | AC27: =ROUND(AB27/10,2) -> 6.5 | AD27: 13 | AE27: -1 | AF27: 7 | AG27: 12 | AH27: 3 | AI27: 7 | AJ27: 12 | AK27: -3 | AL27: =SUM(AD27:AK27) -> 50 | AM27: =ROUND(AL27/70*10,2) -> 7.14 | AN27: =ROUND(S27*0.2+AC27*0.4+AM27*0.4,2) -> 6.71 | AO27: CHF | AP27: 415 | AQ27: 475 | AR27: =I27-AP27+AQ27 -> 14882.955 | AS27: 261.6 | AT27: 528 | AU27: 779 | AV27: 2637 | AW27: =AR27/AS27 -> 56.892031 | AX27: =AR27/AU27 -> 19.105206 | AY27: =AR27/AV27 -> 5.6438966 | AZ27: 3139 | BA27: =AT27/AV27 -> 0.20022753 | BB27: =AV27/AZ27 -> 0.84007646 | BC27: =BA27*BB27 -> 0.16820644 | BD27: 350.2 | BE27: =(BD27/AS27)^(1/5)-1 -> 0.060072774 | BF27: 549.8 | BG27: =(BF27/AS27)^(1/5)-1 -> 0.16014801 | BH27: 18 | BI27: 25 | BJ27: =(BD27*BH27+$AP27-$AQ27)/$H27 -> 39.155826 | BK27: =(BF27*BI27+$AP27-$AQ27)/$H27 -> 85.823479 | BL27: =IF($BJ27<=0,-0.99,MAX(-0.99,($BJ27/G27)^(1/5)-1)) -> -0.15879847 | BM27: =IF(BK27<=0,-0.99,MAX(-0.99,(BK27/G27)^(1/5)-1)) -> -0.015848406 | BN27: 2026-08-25 | BO27: 19/08/2026 | BP27: 29/10/2026 | BQ27: 18.9 | BR27: 65.4 | BS27: 327 | BT27: anual
A28: #VALUE! | B28: {=_FV(A28,"Símbolo bursátil",TRUE())} -> META | C28: Mag 7 | D28: Compounder | E28: {=_FV(A28,"Abreviatura de intercambio",TRUE())} -> XNAS | F28: {=_FV(A28,"Moneda")} -> USD | G28: {=_FV(A28,"Precio")} -> 704.29 | H28: {=_FV(A28,"Acciones en circulación",TRUE())/1000000} -> 2547.506 | I28: =G28*H28 -> 1794183 | J28: -0.5 | K28: 7 | L28: 2 | M28: 1 | N28: -1 | O28: 0 | P28: 1 | Q28: 1 | R28: =SUM(J28:N28)+SUM(P28:Q28) -> 10.5 | S28: =ROUND(R28/16*10,2) -> 6.56 | T28: 15 | U28: 18 | V28: 12 | W28: 8 | X28: 8 | Y28: 10 | Z28: 9 | AA28: -15 | AB28: =SUM(T28:AA28) -> 65 | AC28: =ROUND(AB28/10,2) -> 6.5 | AD28: 12 | AE28: -3 | AF28: 5 | AG28: 12 | AH28: 3 | AI28: 8 | AJ28: 13 | AK28: -6 | AL28: =SUM(AD28:AK28) -> 44 | AM28: =ROUND(AL28/70*10,2) -> 6.29 | AN28: =ROUND(S28*0.2+AC28*0.4+AM28*0.4,2) -> 6.43 | AO28: USD | AP28: 90260 | AQ28: 112320 | AR28: =I28-AP28+AQ28 -> 1816243 | AS28: 15840 | AT28: 67631 | AU28: 109660 | AV28: 228250 | AW28: =AR28/AS28 -> 114.66181 | AX28: =AR28/AU28 -> 16.562493 | AY28: =AR28/AV28 -> 7.957253 | AZ28: 393577 | BA28: =AT28/AV28 -> 0.2963023 | BB28: =AV28/AZ28 -> 0.57993734 | BC28: =BA28*BB28 -> 0.17183677 | BD28: 62609.7 | BE28: =(BD28/BS28)^(1/5)-1 -> -0.053534163 | BF28: 173143.7 | BG28: =(BF28/BS28)^(1/5)-1 -> 0.15999991 | BH28: 18 | BI28: 26 | BJ28: =(BD28*BH28+$AP28-$AQ28)/$H28 -> 433.72404 | BK28: =(BF28*BI28+$AP28-$AQ28)/$H28 -> 1758.4556 | BL28: =IF($BJ28<=0,-0.99,MAX(-0.99,($BJ28/G28)^(1/5)-1)) -> -0.092404372 | BM28: =IF(BK28<=0,-0.99,MAX(-0.99,(BK28/G28)^(1/5)-1)) -> 0.20081465 | BN28: 2026-08-26 | BO28: 29/07/2026 | BP28: 28/10/2026 | BQ28: 25136 | BR28: 66596 | BS28: 82436 | BT28: FCF@5y NORMALIZADO el 4-oct-2026 por decision de Roger: BD/BF del 8-sep x BS/AS (82.436/15.840 = 5,204). BD 12.030,4 -> 62.609,7; BF 33.269,4 -> 173.143,7. CAGR sobre el normalizado -5,4% / 16,0% (las de Roger). BE/BG pasan a medirse contra BS. Multiplos sin cambio por decision de Roger: se calibraron el 22-ago sobre FCF@5y normalizado.
A29: #VALUE! | B29: {=_FV(A29,"Símbolo bursátil",TRUE())} -> KKR | C29: Real Assets | D29: Compounder | E29: {=_FV(A29,"Abreviatura de intercambio",TRUE())} -> XNYS | F29: {=_FV(A29,"Moneda")} -> USD | G29: {=_FV(A29,"Precio")} -> 86.855 | H29: {=_FV(A29,"Acciones en circulación",TRUE())/1000000} -> 897.6356 | I29: =G29*H29 -> 77964.14 | J29: 0 | K29: 6 | L29: 2 | M29: 0 | N29: 0 | O29: 0 | P29: 1 | Q29: 1 | R29: =SUM(J29:N29)+SUM(P29:Q29) -> 10 | S29: =ROUND(R29/16*10,2) -> 6.25 | T29: 13 | U29: 15 | V29: 14 | W29: 9 | X29: 9 | Y29: 13 | Z29: 9 | AA29: -10 | AB29: =SUM(T29:AA29) -> 72 | AC29: =ROUND(AB29/10,2) -> 7.2 | AD29: 13 | AE29: -3 | AF29: 7 | AG29: 13 | AH29: 2 | AI29: 9 | AJ29: 12 | AK29: -5 | AL29: =SUM(AD29:AK29) -> 48 | AM29: =ROUND(AL29/70*10,2) -> 6.86 | AN29: =ROUND(S29*0.2+AC29*0.4+AM29*0.4,2) -> 6.87 | AO29: USD | AP29: 21080 | AQ29: 56164 | AR29: =I29-AP29+AQ29 -> 113048.14 | AS29: 5000 | AT29: 5176 | AU29: 6752 | AV29: 25833 | AW29: =AR29/AS29 -> 22.609628 | AX29: =AR29/AU29 -> 16.742912 | AY29: =AR29/AV29 -> 4.3761135 | AZ29: 34500 | BA29: =AT29/AV29 -> 0.20036388 | BB29: =AV29/AZ29 -> 0.74878261 | BC29: =BA29*BB29 -> 0.15002899 | BD29: 7013 | BE29: =(BD29/AS29)^(1/5)-1 -> 0.070007365 | BF29: 12442 | BG29: =(BF29/AS29)^(1/5)-1 -> 0.20000772 | BH29: 15 | BI29: 25 | BJ29: =(BD29*BH29+$AP29-$AQ29)/$H29 -> 78.106305 | BK29: =(BF29*BI29+$AP29-$AQ29)/$H29 -> 307.43656 | BL29: =IF($BJ29<=0,-0.99,MAX(-0.99,($BJ29/G29)^(1/5)-1)) -> -0.021010004 | BM29: =IF(BK29<=0,-0.99,MAX(-0.99,(BK29/G29)^(1/5)-1)) -> 0.28763311 | BN29: 2026-08-26 | BO29: 30/07/2026 | BP29: 04/11/2026
A30: #VALUE! | B30: {=_FV(A30,"Símbolo bursátil",TRUE())} -> NET | C30: Cyber | D30: Growth | E30: {=_FV(A30,"Abreviatura de intercambio",TRUE())} -> XNYS | F30: {=_FV(A30,"Moneda")} -> USD | G30: {=_FV(A30,"Precio")} -> 299.195 | H30: {=_FV(A30,"Acciones en circulación",TRUE())/1000000} -> 356.0797 | I30: =G30*H30 -> 106537.27 | J30: 1 | K30: 5 | L30: 3 | M30: 0 | N30: 0 | O30: 1 | P30: 1 | Q30: 0 | R30: =SUM(J30:N30)+SUM(P30:Q30) -> 10 | S30: =ROUND(R30/16*10,2) -> 6.25 | T30: 7 | U30: 13 | V30: 16 | W30: 9 | X30: 7 | Y30: 12 | Z30: 6 | AA30: -12 | AB30: =SUM(T30:AA30) -> 58 | AC30: =ROUND(AB30/10,2) -> 5.8 | AD30: 13 | AE30: -1 | AF30: 6 | AG30: 10 | AH30: 3 | AI30: 8 | AJ30: 11 | AK30: -4 | AL30: =SUM(AD30:AK30) -> 46 | AM30: =ROUND(AL30/70*10,2) -> 6.57 | AN30: =ROUND(S30*0.2+AC30*0.4+AM30*0.4,2) -> 6.2 | AO30: USD | AP30: 4163 | AQ30: 3529 | AR30: =I30-AP30+AQ30 -> 105903.27 | AS30: -192.8 | AT30: -195 | AU30: -2 | AV30: 2512 | AW30: =AR30/AS30 -> -549.2908 | AX30: =AR30/AU30 -> -52951.633 | AY30: =AR30/AV30 -> 42.158943 | AZ30: 3846 | BA30: =AT30/AV30 -> -0.077627389 | BB30: =AV30/AZ30 -> 0.65314613 | BC30: =BA30*BB30 -> -0.050702028 | BD30: -109 | BE30: =(BD30/AS30)^(1/5)-1 -> -0.10779656 | BF30: 408 | BG30: =(BF30/AS30)^(1/5)-1 -> -2.1617445 | BH30: 20 | BI30: 30 | BJ30: =(BD30*BH30+$AP30-$AQ30)/$H30 -> -4.3417246 | BK30: =(BF30*BI30+$AP30-$AQ30)/$H30 -> 36.154827 | BL30: =IF($BJ30<=0,-0.99,MAX(-0.99,($BJ30/G30)^(1/5)-1)) -> -0.99 | BM30: =IF(BK30<=0,-0.99,MAX(-0.99,(BK30/G30)^(1/5)-1)) -> -0.34469664 | BN30: 2026-08-25 | BO30: 06/08/2026 | BP30: 05/11/2026 | BQ30: 507.7 | BR30: 93.4 | BS30: -99.4 | BT30: FCF-SBC NEGATIVO: SBC = 20% ingresos. FCF@5y pasado a post-SBC: ingresos y5 7.666 (25%/a) x SBC 10% = -767 sobre 658/1.175. EV/FCF no computable a este precio
A31: #VALUE! | B31: {=_FV(A31,"Símbolo bursátil",TRUE())} -> CRWD | C31: Cyber | D31: Growth | E31: {=_FV(A31,"Abreviatura de intercambio",TRUE())} -> XNAS | F31: {=_FV(A31,"Moneda")} -> USD | G31: {=_FV(A31,"Precio")} -> 228.59 | H31: {=_FV(A31,"Acciones en circulación",TRUE())/1000000} -> 1023.935 | I31: =G31*H31 -> 234061.3 | J31: 1 | K31: 6 | L31: 2 | M31: 0 | N31: 0 | O31: 0 | P31: 1 | Q31: 0 | R31: =SUM(J31:N31)+SUM(P31:Q31) -> 10 | S31: =ROUND(R31/16*10,2) -> 6.25 | T31: 12 | U31: 16 | V31: 16 | W31: 8 | X31: 9 | Y31: 10 | Z31: 5 | AA31: -10 | AB31: =SUM(T31:AA31) -> 66 | AC31: =ROUND(AB31/10,2) -> 6.6 | AD31: 12 | AE31: -2 | AF31: 9 | AG31: 11 | AH31: 3 | AI31: 7 | AJ31: 12 | AK31: -5 | AL31: =SUM(AD31:AK31) -> 47 | AM31: =ROUND(AL31/70*10,2) -> 6.71 | AN31: =ROUND(S31*0.2+AC31*0.4+AM31*0.4,2) -> 6.57 | AO31: USD | AP31: 5013.8 | AQ31: 746.2 | AR31: =I31-AP31+AQ31 -> 229793.7 | AS31: 281.6 | AT31: -133 | AV31: 5396.1 | AW31: =AR31/AS31 -> 816.02877 | AX31: =AR31/AU31 -> #VALUE! | AY31: =AR31/AV31 -> 42.585145 | AZ31: 7154 | BA31: =AT31/AV31 -> -0.024647431 | BB31: =AV31/AZ31 -> 0.75427733 | BC31: =BA31*BB31 -> -0.018590998 | BD31: 491 | BE31: =(BD31/AS31)^(1/5)-1 -> 0.11760869 | BF31: 884.8 | BG31: =(BF31/AS31)^(1/5)-1 -> 0.25731036 | BH31: 20 | BI31: 30 | BJ31: =(BD31*BH31+$AP31-$AQ31)/$H31 -> 13.758295 | BK31: =(BF31*BI31+$AP31-$AQ31)/$H31 -> 30.091363 | BL31: =IF($BJ31<=0,-0.99,MAX(-0.99,($BJ31/G31)^(1/5)-1)) -> -0.42996506 | BM31: =IF(BK31<=0,-0.99,MAX(-0.99,(BK31/G31)^(1/5)-1)) -> -0.33338217 | BN31: 2026-09-27 | BO31: 26/08/2026 | BP31: 01/12/2026 | BQ31: 1244 | BR31: 0 | BS31: 281.6 | BT31: FUENTE: 10-Q Q2 FY27 (EDGAR XBRL). OCF 2.016,6 - capex 407,9 - software 83,1 - SBC 1.244 = 281,6. D&A no etiquetada de forma completa: sin normalizar y EBITDA pendiente. Deuda 746,2. Proximos estimados
A32: #VALUE! | B32: {=_FV(A32,"Símbolo bursátil",TRUE())} -> GOOG | C32: Mag 7 | D32: Compounder | E32: {=_FV(A32,"Abreviatura de intercambio",TRUE())} -> XNAS | F32: {=_FV(A32,"Moneda")} -> USD | G32: {=_FV(A32,"Precio")} -> 340.38 | H32: {=_FV(A32,"Acciones en circulación",TRUE())/1000000} -> 12230 | I32: =G32*H32 -> 4162847.4 | J32: 1 | K32: 7 | L32: 3 | M32: 1 | N32: -1 | O32: 1 | P32: 1 | Q32: 0 | R32: =SUM(J32:N32)+SUM(P32:Q32) -> 12 | S32: =ROUND(R32/16*10,2) -> 7.5 | T32: 16 | U32: 18 | V32: 13 | W32: 8 | X32: 8 | Y32: 11 | Z32: 6 | AA32: -14 | AB32: =SUM(T32:AA32) -> 66 | AC32: =ROUND(AB32/10,2) -> 6.6 | AD32: 12 | AE32: -4 | AF32: 5 | AG32: 11 | AH32: 4 | AI32: 7 | AJ32: 13 | AK32: -6 | AL32: =SUM(AD32:AK32) -> 42 | AM32: =ROUND(AL32/70*10,2) -> 6 | AN32: =ROUND(S32*0.2+AC32*0.4+AM32*0.4,2) -> 6.54 | AO32: USD | AP32: 242470 | AQ32: 120790 | AR32: =I32-AP32+AQ32 -> 4041167.4 | AS32: 25126 | AT32: 120466 | AU32: 173160 | AV32: 445870 | AW32: =AR32/AS32 -> 160.83608 | AX32: =AR32/AU32 -> 23.337765 | AY32: =AR32/AV32 -> 9.0635553 | AZ32: 795872 | BA32: =AT32/AV32 -> 0.27018189 | BB32: =AV32/AZ32 -> 0.56022828 | BC32: =BA32*BB32 -> 0.15136354 | BD32: 168840.3 | BE32: =(BD32/BS32)^(1/5)-1 -> 0.049999671 | BF32: 266084.7 | BG32: =(BF32/BS32)^(1/5)-1 -> 0.15000021 | BH32: 20 | BI32: 30 | BJ32: =(BD32*BH32+$AP32-$AQ32)/$H32 -> 286.05773 | BK32: =(BF32*BI32+$AP32-$AQ32)/$H32 -> 662.65094 | BL32: =IF($BJ32<=0,-0.99,MAX(-0.99,($BJ32/G32)^(1/5)-1)) -> -0.034176141 | BM32: =IF(BK32<=0,-0.99,MAX(-0.99,(BK32/G32)^(1/5)-1)) -> 0.14252091 | BN32: 2026-08-25 | BO32: 22/07/2026 | BP32: 27/10/2026 | BQ32: 28147 | BR32: 107165 | BS32: 132291 | BT32: FCF@5y NORMALIZADO el 4-oct-2026 por decision de Roger: BD/BF del 8-sep x BS/AS (132.291/25.126 = 5,265). BD 32.067,8 -> 168.840,3; BF 50.537,4 -> 266.084,7. CAGR sobre el normalizado 5,0% / 15,0% (las de Roger). BE/BG pasan a medirse contra BS. Multiplos sin cambio por decision de Roger: se calibraron el 22-ago sobre FCF@5y normalizado.
A33: #VALUE! | B33: {=_FV(A33,"Símbolo bursátil",TRUE())} -> ABBNE | C33: Electrify | D33: Compounder | E33: {=_FV(A33,"Abreviatura de intercambio",TRUE())} -> XSWX | F33: {=_FV(A33,"Moneda")} -> CHF | G33: {=_FV(A33,"Precio")} -> 74.62 | H33: {=_FV(A33,"Acciones en circulación",TRUE())/1000000} -> 1823.154 | I33: =G33*H33 -> 136043.75 | J33: 1 | K33: 6 | L33: 2 | M33: 1 | N33: 0 | O33: 0 | P33: 0 | Q33: 0 | R33: =SUM(J33:N33)+SUM(P33:Q33) -> 10 | S33: =ROUND(R33/16*10,2) -> 6.25 | T33: 13 | U33: 14 | V33: 13 | W33: 9 | X33: 8 | Y33: 11 | Z33: 4 | AA33: -8 | AB33: =SUM(T33:AA33) -> 64 | AC33: =ROUND(AB33/10,2) -> 6.4 | AD33: 12 | AE33: -2 | AF33: 5 | AG33: 12 | AH33: 4 | AI33: 7 | AJ33: 11 | AK33: -4 | AL33: =SUM(AD33:AK33) -> 45 | AM33: =ROUND(AL33/70*10,2) -> 6.43 | AN33: =ROUND(S33*0.2+AC33*0.4+AM33*0.4,2) -> 6.38 | AO33: USD | AP33: 5860 | AQ33: 9150 | AR33: =I33*'Framework Notes'!E5-AP33+AQ33 -> 167875.73 | AS33: 4159 | AT33: 4811 | AU33: 7150 | AV33: 35750 | AW33: =AR33/AS33 -> 40.364446 | AX33: =AR33/AU33 -> 23.479123 | AY33: =AR33/AV33 -> 4.6958246 | AZ33: 27296 | BA33: =AT33/AV33 -> 0.13457343 | BB33: =AV33/AZ33 -> 1.3097157 | BC33: =BA33*BB33 -> 0.17625293 | BD33: 5060.1 | BE33: =(BD33/AS33)^(1/5)-1 -> 0.040001668 | BF33: 7329.7 | BG33: =(BF33/AS33)^(1/5)-1 -> 0.1200037 | BH33: 14 | BI33: 25 | BJ33: =((BD33*BH33+$AP33-$AQ33)/$H33)/'Framework Notes'!E5 -> 30.626504 | BK33: =((BF33*BI33+$AP33-$AQ33)/$H33)/'Framework Notes'!E5 -> 81.586997 | BL33: =IF($BJ33<=0,-0.99,MAX(-0.99,($BJ33/G33)^(1/5)-1)) -> -0.16314843 | BM33: =IF(BK33<=0,-0.99,MAX(-0.99,(BK33/G33)^(1/5)-1)) -> 0.018012571 | BN33: 2026-08-25 | BO33: 16/07/2026 | BP33: 22/10/2026 | BQ33: 0 | BR33: 175 | BS33: 4334 | BT33: no reportado (0)
A34: #VALUE! | B34: {=_FV(A34,"Símbolo bursátil",TRUE())} -> GRMN | C34: Sports | D34: Compounder | E34: {=_FV(A34,"Abreviatura de intercambio",TRUE())} -> XNYS | F34: {=_FV(A34,"Moneda")} -> USD | G34: {=_FV(A34,"Precio")} -> 285.15 | H34: {=_FV(A34,"Acciones en circulación",TRUE())/1000000} -> 192.8525 | I34: =G34*H34 -> 54991.89 | J34: 0 | K34: 5 | L34: 2 | M34: 1 | N34: 0 | O34: 1 | P34: 0 | Q34: 0 | R34: =SUM(J34:N34)+SUM(P34:Q34) -> 8 | S34: =ROUND(R34/16*10,2) -> 5 | T34: 14 | U34: 13 | V34: 10 | W34: 8 | X34: 8 | Y34: 10 | Z34: 6 | AA34: -7 | AB34: =SUM(T34:AA34) -> 62 | AC34: =ROUND(AB34/10,2) -> 6.2 | AD34: 12 | AE34: -2 | AF34: 8 | AG34: 10 | AH34: 5 | AI34: 7 | AJ34: 10 | AK34: -3 | AL34: =SUM(AD34:AK34) -> 47 | AM34: =ROUND(AL34/70*10,2) -> 6.71 | AN34: =ROUND(S34*0.2+AC34*0.4+AM34*0.4,2) -> 6.16 | AO34: USD | AP34: 2670 | AQ34: 227 | AR34: =I34-AP34+AQ34 -> 52548.89 | AS34: 1427.3 | AT34: 1754 | AU34: 2310 | AV34: 7670 | AW34: =AR34/AS34 -> 36.81699 | AX34: =AR34/AU34 -> 22.748437 | AY34: =AR34/AV34 -> 6.8512243 | AZ34: 9341 | BA34: =AT34/AV34 -> 0.22868318 | BB34: =AV34/AZ34 -> 0.82111123 | BC34: =BA34*BB34 -> 0.18777433 | BD34: 1736.9 | BE34: =(BD34/AS34)^(1/5)-1 -> 0.040044472 | BF34: 2629.5 | BG34: =(BF34/AS34)^(1/5)-1 -> 0.12998215 | BH34: 18 | BI34: 26 | BJ34: =(BD34*BH34+$AP34-$AQ34)/$H34 -> 174.78228 | BK34: =(BF34*BI34+$AP34-$AQ34)/$H34 -> 367.1718 | BL34: =IF($BJ34<=0,-0.99,MAX(-0.99,($BJ34/G34)^(1/5)-1)) -> -0.093255759 | BM34: =IF(BK34<=0,-0.99,MAX(-0.99,(BK34/G34)^(1/5)-1)) -> 0.051863025 | BN34: 2026-08-25 | BO34: 29/07/2026 | BP34: 29/10/2026 | BQ34: 172.5 | BR34: 185.8 | BS34: 1613.1 | BT34: trimestral
A35: #VALUE! | B35: {=_FV(A35,"Símbolo bursátil",TRUE())} -> KRX | C35: construction | D35: Compounder | E35: XDUB | F35: {=_FV(A35,"Moneda")} -> EUR | G35: {=_FV(A35,"Precio")} -> 95.65 | H35: {=_FV(A35,"Acciones en circulación",TRUE())/1000000} -> 182.9161 | I35: =G35*H35 -> 17495.925 | J35: 1 | K35: 5 | L35: 2 | M35: 0 | N35: 0 | O35: 0 | P35: 1 | Q35: 1 | R35: =SUM(J35:N35)+SUM(P35:Q35) -> 10 | S35: =ROUND(R35/16*10,2) -> 6.25 | T35: 12 | U35: 13 | V35: 14 | W35: 9 | X35: 7 | Y35: 9 | Z35: 8 | AA35: -9 | AB35: =SUM(T35:AA35) -> 63 | AC35: =ROUND(AB35/10,2) -> 6.3 | AD35: 12 | AE35: -2 | AF35: 4 | AG35: 11 | AH35: 2 | AI35: 8 | AJ35: 10 | AK35: -5 | AL35: =SUM(AD35:AK35) -> 40 | AM35: =ROUND(AL35/70*10,2) -> 5.71 | AN35: =ROUND(S35*0.2+AC35*0.4+AM35*0.4,2) -> 6.05 | AO35: EUR | AP35: 590 | AQ35: 2450 | AR35: =I35-AP35+AQ35 -> 19355.925 | AS35: 433.5 | AT35: 780 | AU35: 1277 | AV35: 9561 | AW35: =AR35/AS35 -> 44.650346 | AX35: =AR35/AU35 -> 15.157341 | AY35: =AR35/AV35 -> 2.0244666 | AZ35: 6500 | BA35: =AT35/AV35 -> 0.081581425 | BB35: =AV35/AZ35 -> 1.4709231 | BC35: =BA35*BB35 -> 0.12 | BD35: 527.6 | BE35: =(BD35/AS35)^(1/5)-1 -> 0.040071359 | BF35: 872.1 | BG35: =(BF35/AS35)^(1/5)-1 -> 0.1500466 | BH35: 14 | BI35: 22 | BJ35: =(BD35*BH35+$AP35-$AQ35)/$H35 -> 30.212759 | BK35: =(BF35*BI35+$AP35-$AQ35)/$H35 -> 94.722116 | BL35: =IF($BJ35<=0,-0.99,MAX(-0.99,($BJ35/G35)^(1/5)-1)) -> -0.20585267 | BM35: =IF(BK35<=0,-0.99,MAX(-0.99,(BK35/G35)^(1/5)-1)) -> -0.0019477383 | BN35: 2026-08-26 | BO35: 07/08/2026 | BP35: 20/11/2026 | BQ35: 21 | BR35: 50.5 | BS35: 484 | BT35: anual
A36: #VALUE! | B36: {=_FV(A36,"Símbolo bursátil",TRUE())} -> KSPI | C36: Fintech | D36: Growth | E36: {=_FV(A36,"Abreviatura de intercambio",TRUE())} -> XNAS | F36: {=_FV(A36,"Moneda")} -> USD | G36: {=_FV(A36,"Precio")} -> 92.125 | H36: {=_FV(A36,"Acciones en circulación",TRUE())/1000000} -> 189.3335 | I36: =G36*H36 -> 17442.349 | J36: 1 | K36: 6 | L36: 2 | M36: 1 | N36: -2 | O36: 0 | P36: 1 | Q36: 1 | R36: =SUM(J36:N36)+SUM(P36:Q36) -> 10 | S36: =ROUND(R36/16*10,2) -> 6.25 | T36: 15 | U36: 16 | V36: 10 | W36: 7 | X36: 8 | Y36: 11 | Z36: 10 | AA36: -16 | AB36: =SUM(T36:AA36) -> 61 | AC36: =ROUND(AB36/10,2) -> 6.1 | AD36: 10 | AE36: -6 | AF36: 8 | AG36: 11 | AH36: 3 | AI36: 9 | AJ36: 11 | AK36: -9 | AL36: =SUM(AD36:AK36) -> 37 | AM36: =ROUND(AL36/70*10,2) -> 5.29 | AN36: =ROUND(S36*0.2+AC36*0.4+AM36*0.4,2) -> 5.81 | AO36: KZT | AP36: 900000 | AQ36: 100000 | AR36: =I36*'Framework Notes'!E6-AP36+AQ36 -> 7082022.9 | AS36: 1054825 | AT36: 1065825 | AU36: 1606052 | AV36: 4449504 | AW36: =AR36/AS36 -> 6.7139316 | AX36: =AR36/AU36 -> 4.4095851 | AY36: =AR36/AV36 -> 1.5916432 | AZ36: 2601577 | BA36: =AT36/AV36 -> 0.23953794 | BB36: =AV36/AZ36 -> 1.7103103 | BC36: =BA36*BB36 -> 0.4096842 | BD36: 795760.2 | BE36: =(BD36/AS36)^(1/5)-1 -> -0.054807297 | BF36: 2772489.4 | BG36: =(BF36/AS36)^(1/5)-1 -> 0.21321535 | BH36: 8 | BI36: 15 | BJ36: =((BD36*BH36+$AP36-$AQ36)/$H36)/'Framework Notes'!E6 -> 83.757085 | BK36: =((BF36*BI36+$AP36-$AQ36)/$H36)/'Framework Notes'!E6 -> 495.42279 | BL36: =IF($BJ36<=0,-0.99,MAX(-0.99,($BJ36/G36)^(1/5)-1)) -> -0.018864904 | BM36: =IF(BK36<=0,-0.99,MAX(-0.99,(BK36/G36)^(1/5)-1)) -> 0.39997312 | BN36: 2026-09-27 | BO36: 10/08/2026 | BP36: 09/11/2026 | BQ36: 11000 | BR36: 0 | BS36: 941971 | BT36: FUENTE: 6-K trimestrales (beneficio neto 3T25 278.046 + 4T25 276.983 + 1T26 251.907 + 2T26 258.889 = 1.065.825) - SBC ~11.000 (5.484 en 6M26 x2, estimado). Marco de la tesis: FCF distribuible ~ beneficio neto (hibrido banco). Sept-26: Kaspi sube al 93,5% de Hepsiburada (ampliacion TRY 9.321 M + 57,7 M$ a VR Global); Kim (presidente) vende a diario acciones (Form 4). Deep dive 12-sep-2026 | 28-30 sep: Kim sigue vendiendo (51.000 ADS a ~95 $; le quedan 36,57 M)
A37: #VALUE! | B37: {=_FV(A37,"Símbolo bursátil",TRUE())} -> CBAV | C37: Healthcare | D37: Compounder | E37: {=_FV(A37,"Abreviatura de intercambio",TRUE())} -> BMEX | F37: {=_FV(A37,"Moneda")} -> EUR | G37: {=_FV(A37,"Precio")} -> 54.2 | H37: {=_FV(A37,"Acciones en circulación",TRUE())/1000000} -> 16.30758 | I37: =G37*H37 -> 883.87084 | J37: 2 | K37: 5 | L37: 2 | M37: 0 | N37: -1 | O37: 0 | P37: 0 | Q37: 1 | R37: =SUM(J37:N37)+SUM(P37:Q37) -> 9 | S37: =ROUND(R37/16*10,2) -> 5.63 | T37: 12 | U37: 12 | V37: 12 | W37: 8 | X37: 8 | Y37: 10 | Z37: 8 | AA37: -9 | AB37: =SUM(T37:AA37) -> 61 | AC37: =ROUND(AB37/10,2) -> 6.1 | AD37: 12 | AE37: -2 | AF37: 6 | AG37: 11 | AH37: 3 | AI37: 7 | AJ37: 10 | AK37: -4 | AL37: =SUM(AD37:AK37) -> 43 | AM37: =ROUND(AL37/70*10,2) -> 6.14 | AN37: =ROUND(S37*0.2+AC37*0.4+AM37*0.4,2) -> 6.02 | AO37: EUR | AP37: 51.6 | AQ37: 70 | AR37: =I37-AP37+AQ37 -> 902.27084 | AS37: 46.3 | AT37: 50 | AU37: 95 | AV37: 320 | AW37: =AR37/AS37 -> 19.487491 | AX37: =AR37/AU37 -> 9.4975877 | AY37: =AR37/AV37 -> 2.8195964 | AZ37: 220 | BA37: =AT37/AV37 -> 0.15625 | BB37: =AV37/AZ37 -> 1.4545455 | BC37: =BA37*BB37 -> 0.22727273 | BD37: 61.7 | BE37: =(BD37/AS37)^(1/5)-1 -> 0.059109429 | BF37: 101.4 | BG37: =(BF37/AS37)^(1/5)-1 -> 0.16974553 | BH37: 12 | BI37: 16.5 | BJ37: =(BD37*BH37+$AP37-$AQ37)/$H37 -> 44.27389 | BK37: =(BF37*BI37+$AP37-$AQ37)/$H37 -> 101.46815 | BL37: =IF($BJ37<=0,-0.99,MAX(-0.99,($BJ37/G37)^(1/5)-1)) -> -0.039649695 | BM37: =IF(BK37<=0,-0.99,MAX(-0.99,(BK37/G37)^(1/5)-1)) -> 0.13361633 | BN37: 2026-08-25 | BO37: 29/07/2026 | BP37: 25/02/2027 | BQ37: 0 | BR37: 4.8 | BS37: 51.1 | BT37: no reportado (0)
A38: #VALUE! | B38: {=_FV(A38,"Símbolo bursátil",TRUE())} -> NVDA | C38: IA | D38: Growth | E38: {=_FV(A38,"Abreviatura de intercambio",TRUE())} -> XNAS | F38: {=_FV(A38,"Moneda")} -> USD | G38: {=_FV(A38,"Precio")} -> 217.3 | H38: {=_FV(A38,"Acciones en circulación",TRUE())/1000000} -> 24100 | I38: =G38*H38 -> 5236930 | J38: 1 | K38: 7 | L38: 2 | M38: 1 | N38: -2 | O38: 0 | P38: 1 | Q38: 0 | R38: =SUM(J38:N38)+SUM(P38:Q38) -> 10 | S38: =ROUND(R38/16*10,2) -> 6.25 | T38: 17 | U38: 17 | V38: 15 | W38: 6 | X38: 6 | Y38: 12 | Z38: 5 | AA38: -20 | AB38: =SUM(T38:AA38) -> 58 | AC38: =ROUND(AB38/10,2) -> 5.8 | AD38: 11 | AE38: -5 | AF38: 6 | AG38: 11 | AH38: 4 | AI38: 8 | AJ38: 12 | AK38: -8 | AL38: =SUM(AD38:AK38) -> 39 | AM38: =ROUND(AL38/70*10,2) -> 5.57 | AN38: =ROUND(S38*0.2+AC38*0.4+AM38*0.4,2) -> 5.8 | AO38: USD | AP38: 56586 | AQ38: 33366 | AR38: =I38-AP38+AQ38 -> 5213710 | AS38: 119765 | AT38: 165966 | AU38: 201266 | AV38: 302970 | AW38: =AR38/AS38 -> 43.532835 | AX38: =AR38/AU38 -> 25.904574 | AY38: =AR38/AV38 -> 17.208668 | AZ38: 215590 | BA38: =AT38/AV38 -> 0.54779681 | BB38: =AV38/AZ38 -> 1.4053064 | BC38: =BA38*BB38 -> 0.76982235 | BD38: 179795 | BE38: =(BD38/AS38)^(1/5)-1 -> 0.084649794 | BF38: 279941.5 | BG38: =(BF38/AS38)^(1/5)-1 -> 0.18507947 | BH38: 20 | BI38: 30 | BJ38: =(BD38*BH38+$AP38-$AQ38)/$H38 -> 150.17095 | BK38: =(BF38*BI38+$AP38-$AQ38)/$H38 -> 349.43838 | BL38: =IF($BJ38<=0,-0.99,MAX(-0.99,($BJ38/G38)^(1/5)-1)) -> -0.071236279 | BM38: =IF(BK38<=0,-0.99,MAX(-0.99,(BK38/G38)^(1/5)-1)) -> 0.09966949 | BN38: 2026-09-27 | BO38: 26/08/2026 | BP38: 18/11/2026 | BQ38: 7241 | BR38: 3667 | BS38: 123432 | BT38: FUENTE: 10-Q Q2 FY27 (EDGAR XBRL) y nota de prensa. OCF 134.360 - capex 7.354 - SBC 7.241 = 119.765; D&A 3.687 -> capex de crecimiento 3.667. Caja 22.443 + valores de deuda 34.143 (fuera 42.783 de participaciones en acciones). DEUDA 33.366 (bonos nuevos; antes 12.810). FCF@5y DEVUELTO a los valores de Roger. Proximos estimados
A39: #VALUE! | B39: {=_FV(A39,"Símbolo bursátil",TRUE())} -> COR | C39: Alcohol | D39: Defensive | E39: {=_FV(A39,"Abreviatura de intercambio",TRUE())} -> XLIS | F39: {=_FV(A39,"Moneda")} -> EUR | G39: {=_FV(A39,"Precio")} -> 6.85 | H39: {=_FV(A39,"Acciones en circulación",TRUE())/1000000} -> 133 | I39: =G39*H39 -> 911.05 | J39: 1 | K39: 6 | L39: 1 | M39: 0 | N39: -1 | O39: 0 | P39: 0 | Q39: 1 | R39: =SUM(J39:N39)+SUM(P39:Q39) -> 8 | S39: =ROUND(R39/16*10,2) -> 5 | T39: 11 | U39: 14 | V39: 8 | W39: 8 | X39: 7 | Y39: 10 | Z39: 9 | AA39: -9 | AB39: =SUM(T39:AA39) -> 58 | AC39: =ROUND(AB39/10,2) -> 5.8 | AD39: 12 | AE39: -2 | AF39: 5 | AG39: 9 | AH39: 2 | AI39: 8 | AJ39: 12 | AK39: -4 | AL39: =SUM(AD39:AK39) -> 42 | AM39: =ROUND(AL39/70*10,2) -> 6 | AN39: =ROUND(S39*0.2+AC39*0.4+AM39*0.4,2) -> 5.72 | AO39: EUR | AP39: 40 | AQ39: 140 | AR39: =I39-AP39+AQ39 -> 1011.05 | AS39: 175.3 | AT39: 100 | AU39: 170 | AV39: 900 | AW39: =AR39/AS39 -> 5.7675414 | AX39: =AR39/AU39 -> 5.9473529 | AY39: =AR39/AV39 -> 1.1233889 | AZ39: 750 | BA39: =AT39/AV39 -> 0.11111111 | BB39: =AV39/AZ39 -> 1.2 | BC39: =BA39*BB39 -> 0.13333333 | BD39: 175.3 | BE39: =(BD39/AS39)^(1/5)-1 -> 0 | BF39: 269.5 | BG39: =(BF39/AS39)^(1/5)-1 -> 0.089821498 | BH39: 8.5 | BI39: 12 | BJ39: =(BD39*BH39+$AP39-$AQ39)/$H39 -> 10.451504 | BK39: =(BF39*BI39+$AP39-$AQ39)/$H39 -> 23.56391 | BL39: =IF($BJ39<=0,-0.99,MAX(-0.99,($BJ39/G39)^(1/5)-1)) -> 0.088172238 | BM39: =IF(BK39<=0,-0.99,MAX(-0.99,(BK39/G39)^(1/5)-1)) -> 0.28029885 | BN39: 2026-07-29 | BO39: 29/07/2026 | BP39: 05/11/2026 | BQ39: 0 | BR39: 0 | BS39: 175.3 | BT39: no reportado (0)
A40: #VALUE! | B40: {=_FV(A40,"Símbolo bursátil",TRUE())} -> TSM | C40: IA | D40: Compounder | E40: {=_FV(A40,"Abreviatura de intercambio",TRUE())} -> XNYS | F40: {=_FV(A40,"Moneda")} -> USD | G40: {=_FV(A40,"Precio")} -> 421.685 | H40: {=_FV(A40,"Acciones en circulación",TRUE())/1000000} -> 5186.474 | I40: =G40*H40 -> 2187058.3 | J40: 2 | K40: 7 | L40: 1 | M40: 1 | N40: -2 | O40: 0 | P40: 1 | Q40: 0 | R40: =SUM(J40:N40)+SUM(P40:Q40) -> 10 | S40: =ROUND(R40/16*10,2) -> 6.25 | T40: 15 | U40: 18 | V40: 13 | W40: 6 | X40: 7 | Y40: 12 | Z40: 6 | AA40: -18 | AB40: =SUM(T40:AA40) -> 59 | AC40: =ROUND(AB40/10,2) -> 5.9 | AD40: 11 | AE40: -8 | AF40: 2 | AG40: 11 | AH40: 4 | AI40: 7 | AJ40: 13 | AK40: -10 | AL40: =SUM(AD40:AK40) -> 30 | AM40: =ROUND(AL40/70*10,2) -> 4.29 | AN40: =ROUND(S40*0.2+AC40*0.4+AM40*0.4,2) -> 5.33 | AO40: USD | AP40: 111330 | AQ40: 32648 | AR40: =I40-AP40+AQ40 -> 2108376.3 | AS40: 35739 | AT40: 66093 | AU40: 100634 | AV40: 140522 | AW40: =AR40/AS40 -> 58.993712 | AX40: =AR40/AU40 -> 20.950934 | AY40: =AR40/AV40 -> 15.003888 | AZ40: 244100 | BA40: =AT40/AV40 -> 0.47033916 | BB40: =AV40/AZ40 -> 0.5756739 | BC40: =BA40*BB40 -> 0.27076198 | BD40: 87064.2 | BE40: =(BD40/AS40)^(1/5)-1 -> 0.19492169 | BF40: 124455.7 | BG40: =(BF40/AS40)^(1/5)-1 -> 0.28343677 | BH40: 14 | BI40: 22 | BJ40: =(BD40*BH40+$AP40-$AQ40)/$H40 -> 250.18554 | BK40: =(BF40*BI40+$AP40-$AQ40)/$H40 -> 543.08715 | BL40: =IF($BJ40<=0,-0.99,MAX(-0.99,($BJ40/G40)^(1/5)-1)) -> -0.099145172 | BM40: =IF(BK40<=0,-0.99,MAX(-0.99,(BK40/G40)^(1/5)-1)) -> 0.051904409 | BN40: 2026-08-25 | BO40: 16/07/2026 | BP40: 15/10/2026 | BQ40: 22 | BR40: 25685 | BS40: 61424 | BT40: FUENTE: estados consolidados de TSMC (6-K del 26-feb-2026, FY25, y del 14-ago-2026, H1-26; en NT$). LTM = FY25 + H1-26 - H1-25. Convertido a USD a 31,6 NT$/$ (cambio implicito de TSMC en el H1-26: Q2 NT$1.270.380 M = US$40.200 M). Ingresos NT$4.440.492 M; EBIT 2.491.157; D&A 688.888; flujo de explotacion 2.634.679 - capex 1.500.530 - SBC 683 - arrendamientos 4.101 = FCF-SBC NT$1.129.365 M (35.739 M$). Capex de crecimiento (capex - D&A) 811.642 (25.685 M$) -> normalizado 61.424 M$ en BS. Hasta el 2-oct la columna AS llevaba el normalizado y BS vacia. Caja: efectivo + activos financieros corrientes; deuda: bonos + prestamos (sin arrendamientos). Q3 2026: 15-oct (estimado)
A41: #VALUE! | B41: {=_FV(A41,"Símbolo bursátil",TRUE())} -> SPOT | C41: Consumo | D41: Growth | E41: {=_FV(A41,"Abreviatura de intercambio",TRUE())} -> XNYS | F41: {=_FV(A41,"Moneda")} -> USD | G41: {=_FV(A41,"Precio")} -> 518.94 | H41: {=_FV(A41,"Acciones en circulación",TRUE())/1000000} -> 205.5342 | I41: =G41*H41 -> 106659.92 | J41: 1 | K41: 4 | L41: 2 | M41: 0 | N41: -2 | O41: 0 | P41: 1 | Q41: 1 | R41: =SUM(J41:N41)+SUM(P41:Q41) -> 7 | S41: =ROUND(R41/16*10,2) -> 4.38 | T41: 15 | U41: 11 | V41: 12 | W41: 9 | X41: 7 | Y41: 11 | Z41: 8 | AA41: -12 | AB41: =SUM(T41:AA41) -> 61 | AC41: =ROUND(AB41/10,2) -> 6.1 | AD41: 10 | AE41: -3 | AF41: 7 | AG41: 9 | AH41: 4 | AI41: 8 | AJ41: 9 | AK41: -5 | AL41: =SUM(AD41:AK41) -> 39 | AM41: =ROUND(AL41/70*10,2) -> 5.57 | AN41: =ROUND(S41*0.2+AC41*0.4+AM41*0.4,2) -> 5.54 | AO41: EUR | AP41: 6985 | AQ41: 466 | AR41: =I41*'Framework Notes'!E8-AP41+AQ41 -> 88589.649 | AS41: 2993 | AT41: 2122 | AU41: 2750 | AV41: 18113 | AW41: =AR41/AS41 -> 29.598947 | AX41: =AR41/AU41 -> 32.214418 | AY41: =AR41/AV41 -> 4.8909429 | AZ41: 8834 | BA41: =AT41/AV41 -> 0.11715343 | BB41: =AV41/AZ41 -> 2.0503736 | BC41: =BA41*BB41 -> 0.24020829 | BD41: 3469.4 | BE41: =(BD41/AS41)^(1/5)-1 -> 0.029981754 | BF41: 4820.7 | BG41: =(BF41/AS41)^(1/5)-1 -> 0.10002024 | BH41: 18 | BI41: 25 | BJ41: =((BD41*BH41+$AP41-$AQ41)/$H41)/'Framework Notes'!E8 -> 376.31023 | BK41: =((BF41*BI41+$AP41-$AQ41)/$H41)/'Framework Notes'!E8 -> 693.14749 | BL41: =IF($BJ41<=0,-0.99,MAX(-0.99,($BJ41/G41)^(1/5)-1)) -> -0.0622528 | BM41: =IF(BK41<=0,-0.99,MAX(-0.99,(BK41/G41)^(1/5)-1)) -> 0.059599395 | BN41: 2026-08-25 | BO41: 29/07/2026 | BP41: 28/10/2026 | BQ41: 274 | BR41: 0 | BS41: 2993 | BT41: trimestral
A42: #VALUE! | B42: {=_FV(A42,"Símbolo bursátil",TRUE())} -> PRY | C42: Electrify | D42: Compounder | E42: {=_FV(A42,"Abreviatura de intercambio",TRUE())} -> XMIL | F42: {=_FV(A42,"Moneda")} -> EUR | G42: {=_FV(A42,"Precio")} -> 107.1 | H42: {=_FV(A42,"Acciones en circulación",TRUE())/1000000} -> 308.8616 | I42: =G42*H42 -> 33079.077 | J42: 1 | K42: 5.5 | L42: 2 | M42: 1 | N42: -1 | O42: 0.5 | P42: 1 | Q42: 0 | R42: =SUM(J42:N42)+SUM(P42:Q42) -> 9.5 | S42: =ROUND(R42/16*10,2) -> 5.94 | T42: 12 | U42: 13 | V42: 14 | W42: 9 | X42: 7 | Y42: 10 | Z42: 4 | AA42: -11 | AB42: =SUM(T42:AA42) -> 58 | AC42: =ROUND(AB42/10,2) -> 5.8 | AD42: 12 | AE42: -1 | AF42: 4 | AG42: 12 | AH42: 3 | AI42: 7 | AJ42: 10 | AK42: -6 | AL42: =SUM(AD42:AK42) -> 41 | AM42: =ROUND(AL42/70*10,2) -> 5.86 | AN42: =ROUND(S42*0.2+AC42*0.4+AM42*0.4,2) -> 5.85 | AO42: EUR | AP42: 2600 | AQ42: 4917 | AR42: =I42-AP42+AQ42 -> 35396.077 | AS42: 1418 | AT42: 1419 | AU42: 2398 | AV42: 19650 | AW42: =AR42/AS42 -> 24.961973 | AX42: =AR42/AU42 -> 14.760666 | AY42: =AR42/AV42 -> 1.8013271 | AZ42: 13130 | BA42: =AT42/AV42 -> 0.07221374 | BB42: =AV42/AZ42 -> 1.4965727 | BC42: =BA42*BB42 -> 0.10807312 | BD42: 2059.8 | BE42: =(BD42/AS42)^(1/5)-1 -> 0.077530978 | BF42: 4233.4 | BG42: =(BF42/AS42)^(1/5)-1 -> 0.24452211 | BH42: 18 | BI42: 22.5 | BJ42: =(BD42*BH42+$AP42-$AQ42)/$H42 -> 112.54037 | BK42: =(BF42*BI42+$AP42-$AQ42)/$H42 -> 300.89367 | BL42: =IF($BJ42<=0,-0.99,MAX(-0.99,($BJ42/G42)^(1/5)-1)) -> 0.0099590769 | BM42: =IF(BK42<=0,-0.99,MAX(-0.99,(BK42/G42)^(1/5)-1)) -> 0.22948919 | BN42: 2026-08-20 | BO42: 30/07/2026 | BP42: 05/11/2026 | BQ42: 86 | BR42: 89 | BS42: 1507 | BT42: trimestral
A43: #VALUE! | B43: {=_FV(A43,"Símbolo bursátil",TRUE())} -> JFN | C43: Sports | D43: Defensive | E43: {=_FV(A43,"Abreviatura de intercambio",TRUE())} -> XSWX | F43: {=_FV(A43,"Moneda")} -> CHF | G43: {=_FV(A43,"Precio")} -> 233 | H43: {=_FV(A43,"Acciones en circulación",TRUE())/1000000} -> 5.835 | I43: =G43*H43 -> 1359.555 | J43: 0 | K43: 7 | L43: 0 | M43: 1 | N43: -1 | O43: 0 | P43: 0 | Q43: 0 | R43: =SUM(J43:N43)+SUM(P43:Q43) -> 7 | S43: =ROUND(R43/16*10,2) -> 4.38 | T43: 14 | U43: 17 | V43: 6 | W43: 7 | X43: 7 | Y43: 10 | Z43: 4 | AA43: -9 | AB43: =SUM(T43:AA43) -> 56 | AC43: =ROUND(AB43/10,2) -> 5.6 | AD43: 13 | AE43: -2 | AF43: 3 | AG43: 10 | AH43: 3 | AI43: 6 | AJ43: 13 | AK43: -4 | AL43: =SUM(AD43:AK43) -> 42 | AM43: =ROUND(AL43/70*10,2) -> 6 | AN43: =ROUND(S43*0.2+AC43*0.4+AM43*0.4,2) -> 5.52 | AO43: CHF | AP43: 75 | AQ43: 0 | AR43: =I43-AP43+AQ43 -> 1284.555 | AS43: 76.5 | AT43: 70 | AU43: 129.3 | AV43: 293.1 | AW43: =AR43/AS43 -> 16.791569 | AX43: =AR43/AU43 -> 9.9346868 | AY43: =AR43/AV43 -> 4.382651 | AZ43: 450 | BA43: =AT43/AV43 -> 0.23882634 | BB43: =AV43/AZ43 -> 0.65133333 | BC43: =BA43*BB43 -> 0.15555556 | BD43: 54.6 | BE43: =(BD43/AS43)^(1/5)-1 -> -0.065226824 | BF43: 76.4 | BG43: =(BF43/AS43)^(1/5)-1 -> -0.00026157472 | BH43: 15 | BI43: 22 | BJ43: =(BD43*BH43+$AP43-$AQ43)/$H43 -> 153.21337 | BK43: =(BF43*BI43+$AP43-$AQ43)/$H43 -> 300.90831 | BL43: =IF($BJ43<=0,-0.99,MAX(-0.99,($BJ43/G43)^(1/5)-1)) -> -0.0804229 | BM43: =IF(BK43<=0,-0.99,MAX(-0.99,(BK43/G43)^(1/5)-1)) -> 0.052484364 | BN43: 2026-09-27 | BO43: 28/08/2026 | BP43: 25/03/2027 | BQ43: 0 | BR43: 0 | BS43: 74.4 | BT43: FUENTE: Geschaeftsbericht 2025 (Betriebsertrag 305,7, EBITDA 138,4, FCF 74,5, Gewinn 78,2) + ad hoc H1-26 (137,0 / 56,8 / FCF 18,7 / 28,9; H1-25 149,6 / 65,9 / 16,7 / 37,1). LTM = FY + H1-26 - H1-25. El 26-sep corregi los ingresos a 259 con yfinance: ERROR, el 306 de la fila era el dato bueno. Proximos: anual (estimado)
A44: #VALUE! | B44: {=_FV(A44,"Símbolo bursátil",TRUE())} -> CPR | C44: Alcohol | D44: Defensive | E44: {=_FV(A44,"Abreviatura de intercambio",TRUE())} -> XMIL | F44: {=_FV(A44,"Moneda")} -> EUR | G44: {=_FV(A44,"Precio")} -> 6.61 | H44: {=_FV(A44,"Acciones en circulación",TRUE())/1000000} -> 1231.268 | I44: =G44*H44 -> 8138.6815 | J44: 0 | K44: 6 | L44: 1 | M44: -1 | N44: 0 | O44: 0 | P44: 0 | Q44: 1 | R44: =SUM(J44:N44)+SUM(P44:Q44) -> 7 | S44: =ROUND(R44/16*10,2) -> 4.38 | T44: 9 | U44: 15 | V44: 9 | W44: 8 | X44: 8 | Y44: 10 | Z44: 9 | AA44: -11 | AB44: =SUM(T44:AA44) -> 57 | AC44: =ROUND(AB44/10,2) -> 5.7 | AD44: 13 | AE44: -2 | AF44: 6 | AG44: 8 | AH44: 0 | AI44: 8 | AJ44: 12 | AK44: -5 | AL44: =SUM(AD44:AK44) -> 40 | AM44: =ROUND(AL44/70*10,2) -> 5.71 | AN44: =ROUND(S44*0.2+AC44*0.4+AM44*0.4,2) -> 5.44 | AO44: EUR | AP44: 711 | AQ44: 2806 | AR44: =I44-AP44+AQ44 -> 10233.681 | AS44: 365.1 | AT44: 412 | AU44: 664 | AV44: 3035 | AW44: =AR44/AS44 -> 28.029804 | AX44: =AR44/AU44 -> 15.412171 | AY44: =AR44/AV44 -> 3.3718885 | AZ44: 7090 | BA44: =AT44/AV44 -> 0.13574959 | BB44: =AV44/AZ44 -> 0.4280677 | BC44: =BA44*BB44 -> 0.058110014 | BD44: 423.1 | BE44: =(BD44/AS44)^(1/5)-1 -> 0.029926514 | BF44: 614.9 | BG44: =(BF44/AS44)^(1/5)-1 -> 0.10988641 | BH44: 15 | BI44: 20 | BJ44: =(BD44*BH44+$AP44-$AQ44)/$H44 -> 3.4529444 | BK44: =(BF44*BI44+$AP44-$AQ44)/$H44 -> 8.2865794 | BL44: =IF($BJ44<=0,-0.99,MAX(-0.99,($BJ44/G44)^(1/5)-1)) -> -0.12179152 | BM44: =IF(BK44<=0,-0.99,MAX(-0.99,(BK44/G44)^(1/5)-1)) -> 0.046248304 | BN44: 2026-08-26 | BO44: 29/07/2026 | BP44: 28/10/2026 | BQ44: 23.2 | BR44: 151 | BS44: 516.1 | BT44: anual
A45: #VALUE! | B45: {=_FV(A45,"Símbolo bursátil",TRUE())} -> SIKA | C45: construction | D45: Compounder | E45: {=_FV(A45,"Abreviatura de intercambio",TRUE())} -> XSWX | F45: {=_FV(A45,"Moneda")} -> CHF | G45: {=_FV(A45,"Precio")} -> 183.3 | H45: {=_FV(A45,"Acciones en circulación",TRUE())/1000000} -> 160.4793 | I45: =G45*H45 -> 29415.856 | J45: 1 | K45: 6 | L45: 1 | M45: 0 | N45: 0 | O45: 0 | P45: 0 | Q45: 0 | R45: =SUM(J45:N45)+SUM(P45:Q45) -> 8 | S45: =ROUND(R45/16*10,2) -> 5 | T45: 11 | U45: 13 | V45: 10 | W45: 9 | X45: 7 | Y45: 10 | Z45: 5 | AA45: -9 | AB45: =SUM(T45:AA45) -> 56 | AC45: =ROUND(AB45/10,2) -> 5.6 | AD45: 12 | AE45: -2 | AF45: 5 | AG45: 10 | AH45: 1 | AI45: 7 | AJ45: 11 | AK45: -5 | AL45: =SUM(AD45:AK45) -> 39 | AM45: =ROUND(AL45/70*10,2) -> 5.57 | AN45: =ROUND(S45*0.2+AC45*0.4+AM45*0.4,2) -> 5.47 | AO45: CHF | AP45: 625 | AQ45: 6080 | AR45: =I45-AP45+AQ45 -> 34870.856 | AS45: 1332.5 | AT45: 1173 | AU45: 1940 | AV45: 11110 | AW45: =AR45/AS45 -> 26.169498 | AX45: =AR45/AU45 -> 17.974668 | AY45: =AR45/AV45 -> 3.1386909 | AZ45: 12207 | BA45: =AT45/AV45 -> 0.10558056 | BB45: =AV45/AZ45 -> 0.91013353 | BC45: =BA45*BB45 -> 0.096092406 | BD45: 1544.5 | BE45: =(BD45/AS45)^(1/5)-1 -> 0.029968966 | BF45: 2245.9 | BG45: =(BF45/AS45)^(1/5)-1 -> 0.11005536 | BH45: 18 | BI45: 22.5 | BJ45: =(BD45*BH45+$AP45-$AQ45)/$H45 -> 139.24537 | BK45: =(BF45*BI45+$AP45-$AQ45)/$H45 -> 280.89448 | BL45: =IF($BJ45<=0,-0.99,MAX(-0.99,($BJ45/G45)^(1/5)-1)) -> -0.053493367 | BM45: =IF(BK45<=0,-0.99,MAX(-0.99,(BK45/G45)^(1/5)-1)) -> 0.089121042 | BN45: 2026-08-25 | BO45: 28/07/2026 | BP45: 22/10/2026 | BQ45: 0 | BR45: 0 | BS45: 1332.5 | BT45: no reportado (0)
A46: #VALUE! | B46: {=_FV(A46,"Símbolo bursátil",TRUE())} -> CHKP | C46: Cyber | D46: Special situation | E46: {=_FV(A46,"Abreviatura de intercambio",TRUE())} -> XNAS | F46: {=_FV(A46,"Moneda")} -> USD | G46: {=_FV(A46,"Precio")} -> 139.95 | H46: {=_FV(A46,"Acciones en circulación",TRUE())/1000000} -> 102.1006 | I46: =G46*H46 -> 14288.979 | J46: 1 | K46: 5 | L46: 1 | M46: 1 | N46: 0 | O46: 0 | P46: 0 | Q46: 0 | R46: =SUM(J46:N46)+SUM(P46:Q46) -> 8 | S46: =ROUND(R46/16*10,2) -> 5 | T46: 15 | U46: 11 | V46: 9 | W46: 7 | X46: 8 | Y46: 9 | Z46: 6 | AA46: -12 | AB46: =SUM(T46:AA46) -> 53 | AC46: =ROUND(AB46/10,2) -> 5.3 | AD46: 11 | AE46: -5 | AF46: 10 | AG46: 11 | AH46: 4 | AI46: 6 | AJ46: 9 | AK46: -8 | AL46: =SUM(AD46:AK46) -> 38 | AM46: =ROUND(AL46/70*10,2) -> 5.43 | AN46: =ROUND(S46*0.2+AC46*0.4+AM46*0.4,2) -> 5.29 | AO46: USD | AP46: 2280 | AQ46: 1970 | AR46: =I46-AP46+AQ46 -> 13978.979 | AS46: 865.5 | AT46: 682 | AU46: 846 | AV46: 2760 | AW46: =AR46/AS46 -> 16.151333 | AX46: =AR46/AU46 -> 16.523616 | AY46: =AR46/AV46 -> 5.0648475 | AZ46: 5759 | BA46: =AT46/AV46 -> 0.24710145 | BB46: =AV46/AZ46 -> 0.47924987 | BC46: =BA46*BB46 -> 0.11842334 | BD46: 955.4 | BE46: =(BD46/AS46)^(1/5)-1 -> 0.019961157 | BF46: 1394.1 | BG46: =(BF46/AS46)^(1/5)-1 -> 0.10003213 | BH46: 6 | BI46: 15 | BJ46: =(BD46*BH46+$AP46-$AQ46)/$H46 -> 59.180847 | BK46: =(BF46*BI46+$AP46-$AQ46)/$H46 -> 207.84893 | BL46: =IF($BJ46<=0,-0.99,MAX(-0.99,($BJ46/G46)^(1/5)-1)) -> -0.15813655 | BM46: =IF(BK46<=0,-0.99,MAX(-0.99,(BK46/G46)^(1/5)-1)) -> 0.082318237 | BN46: 2026-08-26 | BO46: 30/07/2026 | BP46: 28/10/2026 | BQ46: 234.2 | BR46: 0 | BS46: 865.5 | BT46: trimestral
A47: #VALUE! | B47: {=_FV(A47,"Símbolo bursátil",TRUE())} -> TGYM | C47: Sports | D47: Compounder | E47: {=_FV(A47,"Abreviatura de intercambio",TRUE())} -> XMIL | F47: {=_FV(A47,"Moneda")} -> EUR | G47: {=_FV(A47,"Precio")} -> 12.94 | H47: {=_FV(A47,"Acciones en circulación",TRUE())/1000000} -> 201.3275 | I47: =G47*H47 -> 2605.1778 | J47: 0 | K47: 4 | L47: 2 | M47: 0 | N47: 0 | O47: 0 | P47: 0 | Q47: 1 | R47: =SUM(J47:N47)+SUM(P47:Q47) -> 7 | S47: =ROUND(R47/16*10,2) -> 4.38 | T47: 12 | U47: 10 | V47: 11 | W47: 7 | X47: 6 | Y47: 10 | Z47: 9 | AA47: -10 | AB47: =SUM(T47:AA47) -> 55 | AC47: =ROUND(AB47/10,2) -> 5.5 | AD47: 10 | AE47: -3 | AF47: 6 | AG47: 10 | AH47: 3 | AI47: 8 | AJ47: 9 | AK47: -4 | AL47: =SUM(AD47:AK47) -> 39 | AM47: =ROUND(AL47/70*10,2) -> 5.57 | AN47: =ROUND(S47*0.2+AC47*0.4+AM47*0.4,2) -> 5.3 | AO47: EUR | AP47: 100 | AQ47: 50 | AR47: =I47-AP47+AQ47 -> 2555.1778 | AS47: 95 | AT47: 90 | AU47: 140 | AV47: 840 | AW47: =AR47/AS47 -> 26.896609 | AX47: =AR47/AU47 -> 18.25127 | AY47: =AR47/AV47 -> 3.0418784 | AZ47: 450 | BA47: =AT47/AV47 -> 0.10714286 | BB47: =AV47/AZ47 -> 1.8666667 | BC47: =BA47*BB47 -> 0.2 | BD47: 116 | BE47: =(BD47/AS47)^(1/5)-1 -> 0.040751096 | BF47: 183 | BG47: =(BF47/AS47)^(1/5)-1 -> 0.1401067 | BH47: 15 | BI47: 22.5 | BJ47: =(BD47*BH47+$AP47-$AQ47)/$H47 -> 8.8909861 | BK47: =(BF47*BI47+$AP47-$AQ47)/$H47 -> 20.700103 | BL47: =IF($BJ47<=0,-0.99,MAX(-0.99,($BJ47/G47)^(1/5)-1)) -> -0.072309454 | BM47: =IF(BK47<=0,-0.99,MAX(-0.99,(BK47/G47)^(1/5)-1)) -> 0.098519186 | BN47: 2026-07-30 | BO47: 30/07/2026 | BP47: 05/11/2026
A48: #VALUE! | B48: {=_FV(A48,"Símbolo bursátil",TRUE())} -> VID | C48: Alcohol | D48: Defensive | E48: {=_FV(A48,"Abreviatura de intercambio",TRUE())} -> BMEX | F48: {=_FV(A48,"Moneda")} -> EUR | G48: {=_FV(A48,"Precio")} -> 90.8 | H48: {=_FV(A48,"Acciones en circulación",TRUE())/1000000} -> 35.20626 | I48: =G48*H48 -> 3196.7284 | J48: 0.75 | K48: 6 | L48: 1 | M48: 0.75 | N48: -0.5 | O48: 0 | P48: 0 | Q48: 1 | R48: =SUM(J48:N48)+SUM(P48:Q48) -> 9 | S48: =ROUND(R48/16*10,2) -> 5.63 | T48: 13 | U48: 10 | V48: 7 | W48: 8 | X48: 7 | Y48: 11.5 | Z48: 9 | AA48: -8 | AB48: =SUM(T48:AA48) -> 57.5 | AC48: =ROUND(AB48/10,2) -> 5.75 | AD48: 10 | AE48: -2 | AF48: 3 | AG48: 10 | AH48: 3 | AI48: 8 | AJ48: 9 | AK48: -4 | AL48: =SUM(AD48:AK48) -> 37 | AM48: =ROUND(AL48/70*10,2) -> 5.29 | AN48: =ROUND(S48*0.2+AC48*0.4+AM48*0.4,2) -> 5.54 | AO48: EUR | AP48: 130 | AQ48: 235 | AR48: =I48-AP48+AQ48 -> 3301.7284 | AS48: 191.8 | AT48: 210 | AU48: 385 | AV48: 1465 | AW48: =AR48/AS48 -> 17.214434 | AX48: =AR48/AU48 -> 8.5759179 | AY48: =AR48/AV48 -> 2.2537395 | AZ48: 1200 | BA48: =AT48/AV48 -> 0.14334471 | BB48: =AV48/AZ48 -> 1.2208333 | BC48: =BA48*BB48 -> 0.175 | BD48: 201.4 | BE48: =(BD48/AS48)^(1/5)-1 -> 0.0098158258 | BF48: 295.4 | BG48: =(BF48/AS48)^(1/5)-1 -> 0.090215564 | BH48: 10 | BI48: 18 | BJ48: =(BD48*BH48+$AP48-$AQ48)/$H48 -> 54.223311 | BK48: =(BF48*BI48+$AP48-$AQ48)/$H48 -> 148.04753 | BL48: =IF($BJ48<=0,-0.99,MAX(-0.99,($BJ48/G48)^(1/5)-1)) -> -0.097971961 | BM48: =IF(BK48<=0,-0.99,MAX(-0.99,(BK48/G48)^(1/5)-1)) -> 0.10271445 | BN48: 2026-07-29 | BO48: 23/07/2026 | BP48: 22/10/2026 | BQ48: 0 | BR48: 55.6 | BS48: 247.4 | BT48: no reportado (0)
A49: #VALUE! | B49: {=_FV(A49,"Símbolo bursátil",TRUE())} -> TFPM | C49: Materials | D49: Raw materials | E49: {=_FV(A49,"Abreviatura de intercambio",TRUE())} -> XTSE | F49: {=_FV(A49,"Moneda")} -> CAD | G49: {=_FV(A49,"Precio")} -> 43.095 | H49: {=_FV(A49,"Acciones en circulación",TRUE())/1000000} -> 205.6855 | I49: =G49*H49 -> 8864.0166 | J49: 0 | K49: 6 | L49: 1 | M49: 1 | N49: -1 | O49: 0 | P49: 0 | Q49: 0 | R49: =SUM(J49:N49)+SUM(P49:Q49) -> 7 | S49: =ROUND(R49/16*10,2) -> 4.38 | T49: 14 | U49: 12 | V49: 12 | W49: 6 | X49: 8 | Y49: 10 | Z49: 5 | AA49: -10 | AB49: =SUM(T49:AA49) -> 57 | AC49: =ROUND(AB49/10,2) -> 5.7 | AD49: 11 | AE49: -4 | AF49: 10 | AG49: 11 | AH49: 4 | AI49: 7 | AJ49: 9 | AK49: -6 | AL49: =SUM(AD49:AK49) -> 42 | AM49: =ROUND(AL49/70*10,2) -> 6 | AN49: =ROUND(S49*0.2+AC49*0.4+AM49*0.4,2) -> 5.56 | AO49: USD | AP49: 35 | AQ49: 236 | AR49: =I49*'Framework Notes'!E7-AP49+AQ49 -> 6484.7014 | AS49: 209 | AT49: 257 | AU49: 377 | AV49: 489 | AW49: =AR49/AS49 -> 31.027279 | AX49: =AR49/AU49 -> 17.200799 | AY49: =AR49/AV49 -> 13.261148 | AZ49: 2539 | BA49: =AT49/AV49 -> 0.52556237 | BB49: =AV49/AZ49 -> 0.19259551 | BC49: =BA49*BB49 -> 0.10122095 | BD49: 174.6 | BE49: =(BD49/AS49)^(1/5)-1 -> -0.035328183 | BF49: 321.7 | BG49: =(BF49/AS49)^(1/5)-1 -> 0.090086484 | BH49: 18 | BI49: 22 | BJ49: =((BD49*BH49+$AP49-$AQ49)/$H49)/'Framework Notes'!E7 -> 20.175509 | BK49: =((BF49*BI49+$AP49-$AQ49)/$H49)/'Framework Notes'!E7 -> 47.159857 | BL49: =IF($BJ49<=0,-0.99,MAX(-0.99,($BJ49/G49)^(1/5)-1)) -> -0.14082918 | BM49: =IF(BK49<=0,-0.99,MAX(-0.99,(BK49/G49)^(1/5)-1)) -> 0.018190683 | BN49: 2026-08-26 | BO49: 05/08/2026 | BP49: 04/11/2026 | BQ49: 5.6 | BR49: 244 | BS49: 453 | BT49: trimestral
A50: #VALUE! | B50: {=_FV(A50,"Símbolo bursátil",TRUE())} -> NFLX | C50: Consumo | D50: Growth | E50: {=_FV(A50,"Abreviatura de intercambio",TRUE())} -> XNAS | F50: {=_FV(A50,"Moneda")} -> USD | G50: {=_FV(A50,"Precio")} -> 69.68 | H50: {=_FV(A50,"Acciones en circulación",TRUE())/1000000} -> 4163.939 | I50: =G50*H50 -> 290143.27 | J50: 0.5 | K50: 6.5 | L50: 2 | M50: 0.5 | N50: -0.5 | O50: =4.1/5 -> 0.82 | P50: 1 | Q50: 0 | R50: =SUM(J50:N50)+SUM(P50:Q50) -> 10 | S50: =ROUND(R50/16*10,2) -> 6.25 | T50: 14.5 | U50: 17 | V50: 14 | W50: 8 | X50: 6.5 | Y50: 12 | Z50: 7 | AA50: -18 | AB50: =SUM(T50:AA50) -> 61 | AC50: =ROUND(AB50/10,2) -> 6.1 | AD50: 10 | AE50: -3 | AF50: 6.5 | AG50: 13 | AH50: 2 | AI50: 6.5 | AJ50: 12.5 | AK50: -6 | AL50: =SUM(AD50:AK50) -> 41.5 | AM50: =ROUND(AL50/70*10,2) -> 5.93 | AN50: =ROUND(S50*0.2+AC50*0.4+AM50*0.4,2) -> 6.06 | AO50: USD | AP50: 9130 | AQ50: =1000+13360 -> 14360 | AR50: =I50-AP50+AQ50 -> 295373.27 | AS50: 10664.7 | AT50: 11876 | AU50: 14730 | AV50: 48370 | AW50: =AR50/AS50 -> 27.696351 | AX50: =AR50/AU50 -> 20.052496 | AY50: =AR50/AV50 -> 6.1065385 | AZ50: 46315 | BA50: =AT50/AV50 -> 0.24552409 | BB50: =AV50/AZ50 -> 1.0443701 | BC50: =BA50*BB50 -> 0.25641801 | BD50: 12994.8 | BE50: =(BD50/AS50)^(1/5)-1 -> 0.040313397 | BF50: 17923.9 | BG50: =(BF50/AS50)^(1/5)-1 -> 0.109422 | BH50: 17 | BI50: 25 | BJ50: =(BD50*BH50+$AP50-$AQ50)/$H50 -> 51.797493 | BK50: =(BF50*BI50+$AP50-$AQ50)/$H50 -> 106.35783 | BL50: =IF($BJ50<=0,-0.99,MAX(-0.99,($BJ50/G50)^(1/5)-1)) -> -0.057589494 | BM50: =IF(BK50<=0,-0.99,MAX(-0.99,(BK50/G50)^(1/5)-1)) -> 0.088258986 | BN50: 2026-08-25 | BO50: 16/07/2026 | BP50: 20/10/2026 | BQ50: 487.3 | BR50: 0 | BS50: 10664.7 | BT50: trimestral
A51: #VALUE! | B51: {=_FV(A51,"Símbolo bursátil",TRUE())} -> NKE | C51: Consumo | D51: Special situation | E51: {=_FV(A51,"Abreviatura de intercambio",TRUE())} -> XNYS | F51: {=_FV(A51,"Moneda")} -> USD | G51: {=_FV(A51,"Precio")} -> 37.085 | H51: {=_FV(A51,"Acciones en circulación",TRUE())/1000000} -> 1485.309 | I51: =G51*H51 -> 55082.684 | J51: 0 | K51: 5 | L51: 1 | M51: 0 | N51: 0 | O51: 0 | P51: 1 | Q51: 0 | R51: =SUM(J51:N51)+SUM(P51:Q51) -> 7 | S51: =ROUND(R51/16*10,2) -> 4.38 | T51: 10 | U51: 13 | V51: 8 | W51: 7 | X51: 6 | Y51: 9 | Z51: 5 | AA51: -10 | AB51: =SUM(T51:AA51) -> 48 | AC51: =ROUND(AB51/10,2) -> 4.8 | AD51: 11 | AE51: -2 | AF51: 7 | AG51: 9 | AH51: 3 | AI51: 6 | AJ51: 10 | AK51: -4 | AL51: =SUM(AD51:AK51) -> 40 | AM51: =ROUND(AL51/70*10,2) -> 5.71 | AN51: =ROUND(S51*0.2+AC51*0.4+AM51*0.4,2) -> 5.08 | AO51: USD | AP51: 8368 | AQ51: 7893 | AR51: =I51-AP51+AQ51 -> 54607.684 | AS51: 1469 | AT51: 3331 | AU51: 4930 | AV51: 45891 | AW51: =AR51/AS51 -> 37.173373 | AX51: =AR51/AU51 -> 11.076609 | AY51: =AR51/AV51 -> 1.1899432 | AZ51: 25863 | BA51: =AT51/AV51 -> 0.072585038 | BB51: =AV51/AZ51 -> 1.7743881 | BC51: =BA51*BB51 -> 0.12879403 | BD51: 2823 | BE51: =(BD51/AS51)^(1/5)-1 -> 0.13956163 | BF51: 6005 | BG51: =(BF51/AS51)^(1/5)-1 -> 0.32525131 | BH51: 14 | BI51: 21 | BJ51: =(BD51*BH51+$AP51-$AQ51)/$H51 -> 26.928403 | BK51: =(BF51*BI51+$AP51-$AQ51)/$H51 -> 85.221324 | BL51: =IF($BJ51<=0,-0.99,MAX(-0.99,($BJ51/G51)^(1/5)-1)) -> -0.062000808 | BM51: =IF(BK51<=0,-0.99,MAX(-0.99,(BK51/G51)^(1/5)-1)) -> 0.18105466 | BN51: 2026-08-25 | BO51: 01/10/2026 | BP51: 18/12/2026 | BQ51: 715 | BR51: 0 | BS51: 1469 | BT51: FUENTE: 10-K FY26 (EDGAR XBRL) + 8-K Q1 FY27 (1-oct-2026). Ingresos LTM = 46.398 + 11.213 - 11.720 = 45.891. FCF - SBC FY26 = OCF 2.868 - capex 684 - SBC 715 = 1.469 (el 10-Q del Q1 aun no esta: LTM de caja pendiente). Caja 6.903 + 1.465 = 8.368; deuda financiera 2.000 + 5.893 = 7.893 (sin arrendamientos operativos; la fila llevaba 11.040). EBITDA y NOPAT pendientes del 10-Q. Guia FY27: ventas -HSD, BPA aj. 1,15-1,35; plan Pace (1.000 M$ de cargos, 2.500 de ahorro hasta FY31). Investor Day en noviembre. Proximos: ~18-dic-2026 (estimado) | 2-oct: FCF@5y 2.823 / 6.005 (escenarios 'marca madura estancada' y 'recuperacion completa' del deep dive NKE_Deep_Dive.md), por decision de Roger; multiplos 14x / 21x sin cambio
A52: #VALUE! | B52: {=_FV(A52,"Símbolo bursátil",TRUE())} -> MIPS | C52: IP owner | D52: Compounder | E52: {=_FV(A52,"Abreviatura de intercambio",TRUE())} -> XSTO | F52: {=_FV(A52,"Moneda")} -> SEK | G52: {=_FV(A52,"Precio")} -> 409.8 | H52: {=_FV(A52,"Acciones en circulación",TRUE())/1000000} -> 26.49799 | I52: =G52*H52 -> 10858.876 | J52: 2 | K52: 4 | L52: 2 | M52: 0 | N52: -1 | O52: 0 | P52: 0 | Q52: 0 | R52: =SUM(J52:N52)+SUM(P52:Q52) -> 7 | S52: =ROUND(R52/16*10,2) -> 4.38 | T52: 11 | U52: 11 | V52: 12 | W52: 6 | X52: 6 | Y52: 9 | Z52: 4 | AA52: -13 | AB52: =SUM(T52:AA52) -> 46 | AC52: =ROUND(AB52/10,2) -> 4.6 | AD52: 10 | AE52: -3 | AF52: 9 | AG52: 9 | AH52: 3 | AI52: 6 | AJ52: 9 | AK52: -5 | AL52: =SUM(AD52:AK52) -> 38 | AM52: =ROUND(AL52/70*10,2) -> 5.43 | AN52: =ROUND(S52*0.2+AC52*0.4+AM52*0.4,2) -> 4.89 | AO52: SEK | AP52: 187 | AQ52: 331 | AR52: =I52-AP52+AQ52 -> 11002.876 | AS52: 133 | AT52: 191 | AU52: 259 | AV52: 664 | AW52: =AR52/AS52 -> 82.728393 | AX52: =AR52/AU52 -> 42.482148 | AY52: =AR52/AV52 -> 16.570597 | AZ52: 1185 | BA52: =AT52/AV52 -> 0.2876506 | BB52: =AV52/AZ52 -> 0.56033755 | BC52: =BA52*BB52 -> 0.16118143 | BD52: 71.2 | BE52: =(BD52/AS52)^(1/5)-1 -> -0.11747774 | BF52: 213.8 | BG52: =(BF52/AS52)^(1/5)-1 -> 0.09959109 | BH52: 17.5 | BI52: 22.5 | BJ52: =(BD52*BH52+$AP52-$AQ52)/$H52 -> 41.58806 | BK52: =(BF52*BI52+$AP52-$AQ52)/$H52 -> 176.1077 | BL52: =IF($BJ52<=0,-0.99,MAX(-0.99,($BJ52/G52)^(1/5)-1)) -> -0.36718125 | BM52: =IF(BK52<=0,-0.99,MAX(-0.99,(BK52/G52)^(1/5)-1)) -> -0.15541906 | BN52: 2026-08-25 | BO52: 16/07/2026 | BP52: 23/10/2026 | BQ52: 0 | BR52: 0 | BS52: 133 | BT52: no reportado (0)
A53: #VALUE! | B53: {=_FV(A53,"Símbolo bursátil",TRUE())} -> FERG | C53: construction | D53: Defensive | E53: {=_FV(A53,"Abreviatura de intercambio",TRUE())} -> XNYS | F53: {=_FV(A53,"Moneda")} -> USD | G53: {=_FV(A53,"Precio")} -> 227.28 | H53: {=_FV(A53,"Acciones en circulación",TRUE())/1000000} -> 193.4527 | I53: =G53*H53 -> 43967.93 | J53: 0 | K53: 5 | L53: 1 | M53: 1 | N53: 0 | O53: 0 | P53: 0 | Q53: 0 | R53: =SUM(J53:N53)+SUM(P53:Q53) -> 7 | S53: =ROUND(R53/16*10,2) -> 4.38 | T53: 12 | U53: 11 | V53: 10 | W53: 9 | X53: 7 | Y53: 10 | Z53: 4 | AA53: -8 | AB53: =SUM(T53:AA53) -> 55 | AC53: =ROUND(AB53/10,2) -> 5.5 | AD53: 11 | AE53: -2 | AF53: 5 | AG53: 10 | AH53: 3 | AI53: 7 | AJ53: 9 | AK53: -4 | AL53: =SUM(AD53:AK53) -> 39 | AM53: =ROUND(AL53/70*10,2) -> 5.57 | AN53: =ROUND(S53*0.2+AC53*0.4+AM53*0.4,2) -> 5.3 | AO53: USD | AP53: 437 | AQ53: 6887 | AR53: =I53-AP53+AQ53 -> 50417.93 | AS53: 1160 | AT53: 2015 | AU53: 3071 | AV53: 31446 | AW53: =AR53/AS53 -> 43.463732 | AX53: =AR53/AU53 -> 16.417431 | AY53: =AR53/AV53 -> 1.6033177 | AZ53: 12926 | BA53: =AT53/AV53 -> 0.064078102 | BB53: =AV53/AZ53 -> 2.4327712 | BC53: =BA53*BB53 -> 0.15588736 | BD53: 2616.7 | BE53: =(BD53/AS53)^(1/5)-1 -> 0.17668221 | BF53: 4044 | BG53: =(BF53/AS53)^(1/5)-1 -> 0.28372096 | BH53: 12 | BI53: 18 | BJ53: =(BD53*BH53+$AP53-$AQ53)/$H53 -> 128.97416 | BK53: =(BF53*BI53+$AP53-$AQ53)/$H53 -> 342.93654 | BL53: =IF($BJ53<=0,-0.99,MAX(-0.99,($BJ53/G53)^(1/5)-1)) -> -0.10712986 | BM53: =IF(BK53<=0,-0.99,MAX(-0.99,(BK53/G53)^(1/5)-1)) -> 0.085751677 | BN53: 2026-08-25 | BO53: 04/08/2026 | BP53: 03/11/2026 | BQ53: 105 | BR53: 35 | BS53: 1195 | BT53: trimestral
A54: #VALUE! | B54: {=_FV(A54,"Símbolo bursátil",TRUE())} -> S | C54: Cyber | D54: Growth | E54: {=_FV(A54,"Abreviatura de intercambio",TRUE())} -> XNYS | F54: {=_FV(A54,"Moneda")} -> USD | G54: {=_FV(A54,"Precio")} -> 21.755 | H54: {=_FV(A54,"Acciones en circulación",TRUE())/1000000} -> 348.0491 | I54: =G54*H54 -> 7571.8082 | J54: 1 | K54: 4 | L54: 2 | M54: -1 | N54: 0 | O54: 0 | P54: 1 | Q54: 0 | R54: =SUM(J54:N54)+SUM(P54:Q54) -> 7 | S54: =ROUND(R54/16*10,2) -> 4.38 | T54: 7 | U54: 10 | V54: 15 | W54: 7 | X54: 7 | Y54: 9 | Z54: 5 | AA54: -18 | AB54: =SUM(T54:AA54) -> 42 | AC54: =ROUND(AB54/10,2) -> 4.2 | AD54: 9 | AE54: -5 | AF54: 7 | AG54: 7 | AH54: 1 | AI54: 6 | AJ54: 9 | AK54: -8 | AL54: =SUM(AD54:AK54) -> 26 | AM54: =ROUND(AL54/70*10,2) -> 3.71 | AN54: =ROUND(S54*0.2+AC54*0.4+AM54*0.4,2) -> 4.04 | AO54: USD | AP54: 655.3 | AQ54: 0 | AR54: =I54-AP54+AQ54 -> 6916.5082 | AS54: -291.1 | AT54: -323.7 | AU54: -256.1 | AV54: 1098.7 | AW54: =AR54/AS54 -> -23.759904 | AX54: =AR54/AU54 -> -27.00706 | AY54: =AR54/AV54 -> 6.2951745 | AZ54: 1684 | BA54: =AT54/AV54 -> -0.29462092 | BB54: =AV54/AZ54 -> 0.65243468 | BC54: =BA54*BB54 -> -0.1922209 | BD54: -286.5 | BE54: =(BD54/AS54)^(1/5)-1 -> -0.0031805941 | BF54: -146.4 | BG54: =(BF54/AS54)^(1/5)-1 -> -0.12843501 | BH54: 18 | BI54: 26 | BJ54: =(BD54*BH54+$AP54-$AQ54)/$H54 -> -12.934095 | BK54: =(BF54*BI54+$AP54-$AQ54)/$H54 -> -9.0536077 | BL54: =IF($BJ54<=0,-0.99,MAX(-0.99,($BJ54/G54)^(1/5)-1)) -> -0.99 | BM54: =IF(BK54<=0,-0.99,MAX(-0.99,(BK54/G54)^(1/5)-1)) -> -0.99 | BN54: 2026-09-27 | BO54: 27/08/2026 | BP54: 01/12/2026 | BQ54: 322.1 | BR54: 0 | BS54: -291.1 | BT54: FUENTE: 10-Q Q2 FY27 (EDGAR XBRL). OCF 57,3 - capex 0,8 - software 25,5 - SBC 322,1 = -291,1. D&A 67,6 > capex: nada que normalizar. Caja 201 + inversiones 454,3. FCF@5y post-SBC -287/-146 (propuesta de agosto, pendiente de Roger). Proximos estimados
A55: #VALUE! | B55: {=_FV(A55,"Símbolo bursátil",TRUE())} -> TREX | C55: construction | D55: Compounder | E55: {=_FV(A55,"Abreviatura de intercambio",TRUE())} -> XNYS | F55: {=_FV(A55,"Moneda")} -> USD | G55: {=_FV(A55,"Precio")} -> 46.615 | H55: {=_FV(A55,"Acciones en circulación",TRUE())/1000000} -> 101.8652 | I55: =G55*H55 -> 4748.4463 | J55: 1 | K55: 4 | L55: 1 | M55: 0 | N55: -1 | O55: 0 | P55: 0 | Q55: 0 | R55: =SUM(J55:N55)+SUM(P55:Q55) -> 5 | S55: =ROUND(R55/16*10,2) -> 3.13 | T55: 10 | U55: 10 | V55: 9 | W55: 7 | X55: 6 | Y55: 9 | Z55: 4 | AA55: -11 | AB55: =SUM(T55:AA55) -> 44 | AC55: =ROUND(AB55/10,2) -> 4.4 | AD55: 10 | AE55: -3 | AF55: 5 | AG55: 8 | AH55: 2 | AI55: 6 | AJ55: 8 | AK55: -5 | AL55: =SUM(AD55:AK55) -> 31 | AM55: =ROUND(AL55/70*10,2) -> 4.43 | AN55: =ROUND(S55*0.2+AC55*0.4+AM55*0.4,2) -> 4.16 | AO55: USD | AP55: 6.5 | AQ55: 303 | AR55: =I55-AP55+AQ55 -> 5044.9463 | AS55: 189.1 | AT55: 183 | AU55: 313 | AV55: 1208 | AW55: =AR55/AS55 -> 26.678722 | AX55: =AR55/AU55 -> 16.118039 | AY55: =AR55/AV55 -> 4.17628 | AZ55: 1176 | BA55: =AT55/AV55 -> 0.15149007 | BB55: =AV55/AZ55 -> 1.0272109 | BC55: =BA55*BB55 -> 0.15561224 | BD55: 189.1 | BE55: =(BD55/AS55)^(1/5)-1 -> 0 | BF55: 364.2 | BG55: =(BF55/AS55)^(1/5)-1 -> 0.14006518 | BH55: 12 | BI55: 18 | BJ55: =(BD55*BH55+$AP55-$AQ55)/$H55 -> 19.365789 | BK55: =(BF55*BI55+$AP55-$AQ55)/$H55 -> 61.444929 | BL55: =IF($BJ55<=0,-0.99,MAX(-0.99,($BJ55/G55)^(1/5)-1)) -> -0.16111602 | BM55: =IF(BK55<=0,-0.99,MAX(-0.99,(BK55/G55)^(1/5)-1)) -> 0.056798217 | BN55: 2026-08-25 | BO55: 04/08/2026 | BP55: 03/11/2026 | BQ55: 9.3 | BR55: 89.1 | BS55: 278.2 | BT55: trimestral
A56: #VALUE! | B56: {=_FV(A56,"Símbolo bursátil",TRUE())} -> SGO | C56: construction | D56: Special situation | E56: {=_FV(A56,"Abreviatura de intercambio",TRUE())} -> XPAR | F56: {=_FV(A56,"Moneda")} -> EUR | G56: {=_FV(A56,"Precio")} -> 66.42 | H56: {=_FV(A56,"Acciones en circulación",TRUE())/1000000} -> 494.834 | I56: =G56*H56 -> 32866.874 | J56: 0 | K56: 4 | L56: 1 | M56: 0 | N56: 0 | O56: 0 | P56: 0 | Q56: 0 | R56: =SUM(J56:N56)+SUM(P56:Q56) -> 5 | S56: =ROUND(R56/16*10,2) -> 3.13 | T56: 10 | U56: 10 | V56: 9 | W56: 8 | X56: 6 | Y56: 9 | Z56: 4 | AA56: -11 | AB56: =SUM(T56:AA56) -> 45 | AC56: =ROUND(AB56/10,2) -> 4.5 | AD56: 10 | AE56: -3 | AF56: 3 | AG56: 8 | AH56: 1 | AI56: 6 | AJ56: 8 | AK56: -6 | AL56: =SUM(AD56:AK56) -> 27 | AM56: =ROUND(AL56/70*10,2) -> 3.86 | AN56: =ROUND(S56*0.2+AC56*0.4+AM56*0.4,2) -> 3.97 | AO56: EUR | AP56: 5751 | AQ56: 17270 | AR56: =I56-AP56+AQ56 -> 44385.874 | AS56: 3312 | AT56: 3632 | AU56: 7337 | AV56: 46226 | AW56: =AR56/AS56 -> 13.401532 | AX56: =AR56/AU56 -> 6.0495944 | AY56: =AR56/AV56 -> 0.96019284 | AZ56: 43914 | BA56: =AT56/AV56 -> 0.078570501 | BB56: =AV56/AZ56 -> 1.0526484 | BC56: =BA56*BB56 -> 0.082707109 | BD56: 3480.6 | BE56: =(BD56/AS56)^(1/5)-1 -> 0.0099799622 | BF56: 5096.4 | BG56: =(BF56/AS56)^(1/5)-1 -> 0.090020425 | BH56: 12 | BI56: 16 | BJ56: =(BD56*BH56+$AP56-$AQ56)/$H56 -> 61.127974 | BK56: =(BF56*BI56+$AP56-$AQ56)/$H56 -> 141.50887 | BL56: =IF($BJ56<=0,-0.99,MAX(-0.99,($BJ56/G56)^(1/5)-1)) -> -0.016468607 | BM56: =IF(BK56<=0,-0.99,MAX(-0.99,(BK56/G56)^(1/5)-1)) -> 0.16331401 | BN56: 2026-08-25 | BO56: 30/07/2026 | BP56: 29/10/2026 | BQ56: 136 | BR56: 0 | BS56: 3312 | BT56: anual
A57: #VALUE! | B57: {=_FV(A57,"Símbolo bursátil",TRUE())} -> TFF | C57: Alcohol | D57: Special situation | E57: {=_FV(A57,"Abreviatura de intercambio",TRUE())} -> XPAR | F57: {=_FV(A57,"Moneda")} -> EUR | G57: {=_FV(A57,"Precio")} -> 13.8 | H57: {=_FV(A57,"Acciones en circulación",TRUE())/1000000} -> 21.68 | I57: =G57*H57 -> 299.184 | J57: 0 | K57: 5 | L57: 1 | M57: -1 | N57: -2 | O57: 0 | P57: 0 | Q57: 1 | R57: =SUM(J57:N57)+SUM(P57:Q57) -> 4 | S57: =ROUND(R57/16*10,2) -> 2.5 | T57: 7 | U57: 11 | V57: 7 | W57: 6 | X57: 5 | Y57: 9 | Z57: 8 | AA57: -14 | AB57: =SUM(T57:AA57) -> 39 | AC57: =ROUND(AB57/10,2) -> 3.9 | AD57: 9 | AE57: -4 | AF57: 3 | AG57: 8 | AH57: -1 | AI57: 7 | AJ57: 9 | AK57: -6 | AL57: =SUM(AD57:AK57) -> 25 | AM57: =ROUND(AL57/70*10,2) -> 3.57 | AN57: =ROUND(S57*0.2+AC57*0.4+AM57*0.4,2) -> 3.49 | AO57: EUR | AP57: 97 | AQ57: 382 | AR57: =I57-AP57+AQ57 -> 584.184 | AS57: 59 | AT57: 21 | AU57: 48 | AV57: 313 | AW57: =AR57/AS57 -> 9.9014237 | AX57: =AR57/AU57 -> 12.1705 | AY57: =AR57/AV57 -> 1.8664026 | AZ57: 624 | BA57: =AT57/AV57 -> 0.067092652 | BB57: =AV57/AZ57 -> 0.50160256 | BC57: =BA57*BB57 -> 0.033653846 | BD57: 12 | BE57: =(BD57/AS57)^(1/5)-1 -> -0.27277995 | BF57: 42 | BG57: =(BF57/AS57)^(1/5)-1 -> -0.065714829 | BH57: 6.5 | BI57: 12.5 | BJ57: =(BD57*BH57+$AP57-$AQ57)/$H57 -> -9.5479705 | BK57: =(BF57*BI57+$AP57-$AQ57)/$H57 -> 11.070111 | BL57: =IF($BJ57<=0,-0.99,MAX(-0.99,($BJ57/G57)^(1/5)-1)) -> -0.99 | BM57: =IF(BK57<=0,-0.99,MAX(-0.99,(BK57/G57)^(1/5)-1)) -> -0.043126394 | BN57: 2026-08-25 | BO57: 08/07/2026 | BP57: 30/01/2027
A58: #VALUE! | B58: {=_FV(A58,"Símbolo bursátil",TRUE)} -> CELH | C58: Consumo | D58: Growth | E58: {=_FV(A58,"Abreviatura de intercambio",TRUE())} -> XNAS | F58: {=_FV(A58,"Moneda")} -> USD | G58: {=_FV(A58,"Precio")} -> 29.77 | H58: {=_FV(A58,"Acciones en circulación",TRUE())/1000000} -> 253.035 | I58: =G58*H58 -> 7532.852 | J58: 0 | K58: 4 | L58: 2 | M58: 0 | N58: -3 | O58: 0 | P58: 0 | Q58: 0 | R58: =SUM(J58:N58)+SUM(P58:Q58) -> 3 | S58: =ROUND(R58/16*10,2) -> 1.88 | T58: 10 | U58: 10 | V58: 11 | W58: 6 | X58: 5 | Y58: 8 | Z58: 4 | AA58: -18 | AB58: =SUM(T58:AA58) -> 36 | AC58: =ROUND(AB58/10,2) -> 3.6 | AD58: 8 | AE58: -4 | AF58: 7 | AG58: 7 | AH58: 1 | AI58: 5 | AJ58: 7 | AK58: -7 | AL58: =SUM(AD58:AK58) -> 24 | AM58: =ROUND(AL58/70*10,2) -> 3.43 | AN58: =ROUND(S58*0.2+AC58*0.4+AM58*0.4,2) -> 3.19 | AO58: USD | AP58: 631 | AQ58: 668 | AR58: =I58-AP58+AQ58 -> 7569.852 | AS58: 428 | AT58: 430 | AU58: 719 | AV58: 3047 | AW58: =AR58/AS58 -> 17.68657 | AX58: =AR58/AU58 -> 10.528306 | AY58: =AR58/AV58 -> 2.4843623 | AZ58: 3400 | BA58: =AT58/AV58 -> 0.14112242 | BB58: =AV58/AZ58 -> 0.89617647 | BC58: =BA58*BB58 -> 0.12647059 | BD58: 408.9 | BE58: =(BD58/AS58)^(1/5)-1 -> -0.0090889571 | BF58: 1404.6 | BG58: =(BF58/AS58)^(1/5)-1 -> 0.26829938 | BH58: 16 | BI58: 22.5 | BJ58: =(BD58*BH58+$AP58-$AQ58)/$H58 -> 25.709487 | BK58: =(BF58*BI58+$AP58-$AQ58)/$H58 -> 124.75152 | BL58: =IF($BJ58<=0,-0.99,MAX(-0.99,($BJ58/G58)^(1/5)-1)) -> -0.028902324 | BM58: =IF(BK58<=0,-0.99,MAX(-0.99,(BK58/G58)^(1/5)-1)) -> 0.33184413 | BN58: 2026-08-25 | BO58: 06/08/2026 | BP58: 05/11/2026 | BQ58: 34.8 | BR58: 8.9 | BS58: 436.9 | BT58: trimestral
A59: #VALUE! | B59: {=_FV(A59,"Símbolo bursátil",TRUE())} -> BFIT | C59: Sports | D59: Growth | E59: {=_FV(A59,"Abreviatura de intercambio",TRUE())} -> XAMS | F59: {=_FV(A59,"Moneda")} -> EUR | G59: {=_FV(A59,"Precio")} -> 30.36 | H59: {=_FV(A59,"Acciones en circulación",TRUE())/1000000} -> 65 | I59: =G59*H59 -> 1973.4 | J59: 0 | K59: 4 | L59: 1 | M59: -1 | N59: 0 | O59: 0 | P59: 0 | Q59: 0 | R59: =SUM(J59:N59)+SUM(P59:Q59) -> 4 | S59: =ROUND(R59/16*10,2) -> 2.5 | T59: 7 | U59: 9 | V59: 10 | W59: 8 | X59: 6 | Y59: 9 | Z59: 5 | AA59: -15 | AB59: =SUM(T59:AA59) -> 39 | AC59: =ROUND(AB59/10,2) -> 3.9 | AD59: 8 | AE59: -5 | AF59: 2 | AG59: 8 | AH59: -2 | AI59: 6 | AJ59: 8 | AK59: -7 | AL59: =SUM(AD59:AK59) -> 18 | AM59: =ROUND(AL59/70*10,2) -> 2.57 | AN59: =ROUND(S59*0.2+AC59*0.4+AM59*0.4,2) -> 3.09 | AO59: EUR | AP59: 40 | AQ59: 740 | AR59: =I59-AP59+AQ59 -> 2673.4 | AS59: 367.1 | AT59: 50 | AU59: 260 | AV59: 1250 | AW59: =AR59/AS59 -> 7.2824843 | AX59: =AR59/AU59 -> 10.282308 | AY59: =AR59/AV59 -> 2.13872 | AZ59: 1500 | BA59: =AT59/AV59 -> 0.04 | BB59: =AV59/AZ59 -> 0.83333333 | BC59: =BA59*BB59 -> 0.033333333 | BD59: 403.8 | BE59: =(BD59/AS59)^(1/5)-1 -> 0.019239828 | BF59: 770.9 | BG59: =(BF59/AS59)^(1/5)-1 -> 0.15995925 | BH59: 12 | BI59: 18 | BJ59: =(BD59*BH59+$AP59-$AQ59)/$H59 -> 63.778462 | BK59: =(BF59*BI59+$AP59-$AQ59)/$H59 -> 202.71077 | BL59: =IF($BJ59<=0,-0.99,MAX(-0.99,($BJ59/G59)^(1/5)-1)) -> 0.16004398 | BM59: =IF(BK59<=0,-0.99,MAX(-0.99,(BK59/G59)^(1/5)-1)) -> 0.46189106 | BN59: 2026-07-29 | BO59: 28/07/2026 | BP59: 27/10/2026 | BQ59: 2.3 | BR59: 0 | BS59: 367.1 | BT59: anual
A60: #VALUE! | B60: {=_FV(A60,"Símbolo bursátil",TRUE())} -> VRLA | C60: Alcohol | D60: Special situation | E60: XPAR | F60: {=_FV(A60,"Moneda")} -> EUR | G60: {=_FV(A60,"Precio")} -> 18.39 | H60: {=_FV(A60,"Acciones en circulación",TRUE())/1000000} -> 127.5873 | I60: =G60*H60 -> 2346.3304 | J60: 0.75 | K60: 5.5 | L60: 0.5 | M60: -0.75 | N60: -0.75 | O60: 0 | P60: 0 | Q60: 0 | R60: =SUM(J60:N60)+SUM(P60:Q60) -> 5.25 | S60: =ROUND(R60/16*10,2) -> 3.28 | T60: 9 | U60: 11 | V60: 8 | W60: 6.5 | X60: 6.5 | Y60: 9 | Z60: 5 | AA60: -18 | AB60: =SUM(T60:AA60) -> 37 | AC60: =ROUND(AB60/10,2) -> 3.7 | AD60: 12 | AE60: -2 | AF60: 3 | AG60: 9 | AH60: 0 | AI60: 7 | AJ60: 9 | AK60: -6 | AL60: =SUM(AD60:AK60) -> 32 | AM60: =ROUND(AL60/70*10,2) -> 4.57 | AN60: =ROUND(S60*0.2+AC60*0.4+AM60*0.4,2) -> 3.96 | AO60: EUR | AP60: 413.9 | AQ60: 2131.9 | AR60: =I60-AP60+AQ60 -> 4064.3304 | AS60: 195.6 | AT60: 270 | AU60: 693 | AV60: 3307.7 | AW60: =AR60/AS60 -> 20.778786 | AX60: =AR60/AU60 -> 5.8648347 | AY60: =AR60/AV60 -> 1.2287482 | AZ60: 3400 | BA60: =AT60/AV60 -> 0.081627717 | BB60: =AV60/AZ60 -> 0.97285294 | BC60: =BA60*BB60 -> 0.079411765 | BD60: 300 | BE60: =(BD60/AS60)^(1/5)-1 -> 0.089307468 | BF60: 490 | BG60: =(BF60/AS60)^(1/5)-1 -> 0.20161529 | BH60: 8 | BI60: 15 | BJ60: =(BD60*BH60+$AP60-$AQ60)/$H60 -> 5.3453596 | BK60: =(BF60*BI60+$AP60-$AQ60)/$H60 -> 44.142325 | BL60: =IF($BJ60<=0,-0.99,MAX(-0.99,($BJ60/G60)^(1/5)-1)) -> -0.21894964 | BM60: =IF(BK60<=0,-0.99,MAX(-0.99,(BK60/G60)^(1/5)-1)) -> 0.19139204 | BN60: 2026-07-29 | BO60: 28/07/2026 | BP60: 27/10/2026 | BQ60: 6.2 | BR60: 0 | BS60: 195.6 | BT60: FUENTE: notas de resultados FY25 (24-feb-2026) y H1-26 (28-jul-2026) e informe financiero semestral 2026 de Verallia. LTM = FY25 + H1-26 - H1-25. Ingresos 3.331,5 + 1.698,8 - 1.722,6 = 3.307,7; EBITDA ajustado LTM 693,0 (de la compania). FCF de Verallia (EBITDA aj. - capex +/- circulante - otros impactos operativos, que incluyen el efecto de caja de la NIIF 16 - intereses - impuestos): 166,0 + 102,0 - 66,2 = 201,8, menos SBC 6,2 (estado de cambios en el patrimonio) = 195,6 (incluye 19 de reestructuracion en el H1-26). La fila llevaba 249 (sin fuente). Caja 413,9; deuda bruta 2.192,8 - arrendamientos 60,9 = 2.131,9 (deuda neta de la compania 1.778,9). Capex 246 < amortizacion: sin normalizar. NOPAT pendiente. Q3: 27-oct-2026 (calendario de la compania)
A61: #VALUE! | B61: {=_FV(A61,"Símbolo bursátil",TRUE())} -> KIST | C61: Materials | D61: Raw materials | E61: {=_FV(A61,"Abreviatura de intercambio",TRUE())} -> XLON | F61: {=_FV(A61,"Moneda")} -> GBp | G61: {=_FV(A61,"Precio")} -> 298 | H61: {=_FV(A61,"Acciones en circulación",TRUE())/1000000} -> 83.11765 | I61: =G61/100*H61 -> 247.6906 | J61: 0 | K61: 2 | L61: 1 | M61: 0 | N61: -2 | O61: 0 | P61: 1 | Q61: 1 | R61: =SUM(J61:N61)+SUM(P61:Q61) -> 3 | S61: =ROUND(R61/16*10,2) -> 1.88 | T61: 9 | U61: 5 | V61: 8 | W61: 5 | X61: 4 | Y61: 10 | Z61: 10 | AA61: -20 | AB61: =SUM(T61:AA61) -> 31 | AC61: =ROUND(AB61/10,2) -> 3.1 | AD61: 5 | AE61: -10 | AF61: 2 | AG61: 10 | AH61: 1 | AI61: 8 | AJ61: 5 | AK61: -10 | AL61: =SUM(AD61:AK61) -> 11 | AM61: =ROUND(AL61/70*10,2) -> 1.57 | AN61: =ROUND(S61*0.2+AC61*0.4+AM61*0.4,2) -> 2.24 | AO61: USD | AP61: 199.5 | AQ61: 300 | AR61: =I61*'Framework Notes'!$E$9-AP61+AQ61 -> 430.05234 | AS61: 147.8 | AT61: =390-230 -> 160 | AU61: 226.9 | AV61: 336.9 | AW61: =AR61/AS61 -> 2.9096911 | AX61: =AR61/AU61 -> 1.8953386 | AY61: =AR61/AV61 -> 1.2764985 | AZ61: 300 | BA61: =AT61/AV61 -> 0.47491837 | BB61: =AV61/AZ61 -> 1.123 | BC61: =BA61*BB61 -> 0.53333333 | BD61: 40 | BE61: =(BD61/AS61)^(1/5)-1 -> -0.23002414 | BF61: 65 | BG61: =(BF61/AS61)^(1/5)-1 -> -0.15150794 | BH61: 6 | BI61: 10 | BJ61: =((BD61*BH61+$AP61-$AQ61)/$H61)/'Framework Notes'!$E$9*100 -> 126.14385 | BK61: =((BF61*BI61+$AP61-$AQ61)/$H61)/'Framework Notes'!$E$9*100 -> 496.88921 | BL61: =IF($BJ61<=0,-0.99,MAX(-0.99,($BJ61/G61)^(1/5)-1)) -> -0.15796535 | BM61: =IF(BK61<=0,-0.99,MAX(-0.99,(BK61/G61)^(1/5)-1)) -> 0.10766558 | BN61: 2026-10-19 | BO61: 19/10/2026 | BP61: 08/01/2027 | BQ61: 3.6 | BR61: 0 | BS61: 147.8 | BT61: FUENTE: informe anual 2025 + informe intermedio 1S26 + trading statement 3T26 (RNS 19-oct-2026, kistosplc.com). LTM a 30-jun (el 3T no publica flujo de caja; se queda el semestral): OCF 257,2 (incl. devoluciones fiscales noruegas) - capex 105,6 - arrend. 0,2 - SBC 3,6 = 147,8. D&A 112,1 > capex: sin capex de crecimiento por regla. Ingresos/EBITDA SIN Oman. CAJA/DEUDA a 30-sep (RNS 19-oct, notas 3 y 4): deuda = bono 300 nominal; caja = 165 de caja y casi caja (109 libre + 20 escrow del bono para el B9 + 36 devolucion fiscal noruega de dic-26) + 17 otros restringidos + 15 SPS holandes reembolsable + 2,5 prepago B9 = 199,5. Deuda neta ajustada de la compania 101 (30-jun: 23). NO incluye ~42 de impuestos devengados pendientes (netos de devoluciones) ni el pago del Bloque 9 (~29-32, cierre 4T26): deuda neta economica ~231 tras el B9 (kistos_update_3T26.py). FCF@5y Y MULTIPLOS (decididos por Roger el 19-oct-2026): ESPEJO DEL MODELO POR ACTIVOS v4, caso compania. BD 40 / BF 65 = FCF desapalancado de 2031 en S1 Ormuz se resuelve (38,8) y S3 prima geopolitica persistente (66,6). BH 6x / BI 10x son multiplos IMPLICITOS: incluyen la caja que se acumula hasta 2031 y el repago del bono, porque la formula de la fila usa la deuda neta de hoy. Reproducen 126p / 497p (modelo: 127p / 486p). NO comparables con los multiplos de salida de otras filas. Proximo: trading update ~8-ene-2027 (ESTIMADO: 8-ene-2025 y 8-ene-2026; la web de RI no publica calendario).
A62: #VALUE! | B62: {=_FV(A62,"Símbolo bursátil",TRUE())} -> WOSG | C62: Consumo | D62: Special situation | E62: {=_FV(A62,"Abreviatura de intercambio",TRUE())} -> XLON | F62: {=_FV(A62,"Moneda")} -> GBp | G62: {=_FV(A62,"Precio")} -> 698.5 | H62: {=_FV(A62,"Acciones en circulación",TRUE())/1000000} -> 233.3016 | I62: =G62/100*H62 -> 1629.6117 | J62: 0.5 | K62: 3 | L62: 1 | M62: -1 | N62: -2 | O62: 0 | P62: 0 | Q62: 0 | R62: =SUM(J62:N62)+SUM(P62:Q62) -> 1.5 | S62: =ROUND(R62/16*10,2) -> 0.94 | T62: 7 | U62: 8 | V62: 7 | W62: 4 | X62: 4 | Y62: 7 | Z62: 4 | AA62: -16 | AB62: =SUM(T62:AA62) -> 25 | AC62: =ROUND(AB62/10,2) -> 2.5 | AD62: 7 | AE62: -5 | AF62: 5 | AG62: 7 | AH62: 1 | AI62: 5 | AJ62: 6 | AK62: -6 | AL62: =SUM(AD62:AK62) -> 20 | AM62: =ROUND(AL62/70*10,2) -> 2.86 | AN62: =ROUND(S62*0.2+AC62*0.4+AM62*0.4,2) -> 2.33 | AO62: GBP | AP62: 70 | AQ62: 270 | AR62: =I62-AP62+AQ62 -> 1829.6117 | AS62: 183.9 | AT62: 80 | AU62: 170 | AV62: 1700 | AW62: =AR62/AS62 -> 9.9489488 | AX62: =AR62/AU62 -> 10.762422 | AY62: =AR62/AV62 -> 1.0762422 | AZ62: 900 | BA62: =AT62/AV62 -> 0.047058824 | BB62: =AV62/AZ62 -> 1.8888889 | BC62: =BA62*BB62 -> 0.088888889 | BD62: 183.9 | BE62: =(BD62/AS62)^(1/5)-1 -> 0 | BF62: 353.5 | BG62: =(BF62/AS62)^(1/5)-1 -> 0.13962387 | BH62: 8 | BI62: 14 | BJ62: =(BD62*BH62+$AP62-$AQ62)/$H62*100 -> 544.8741 | BK62: =(BF62*BI62+$AP62-$AQ62)/$H62*100 -> 2035.5626 | BL62: =IF($BJ62<=0,-0.99,MAX(-0.99,($BJ62/G62)^(1/5)-1)) -> -0.048462406 | BM62: =IF(BK62<=0,-0.99,MAX(-0.99,(BK62/G62)^(1/5)-1)) -> 0.23852167 | BN62: 2026-07-18 | BO62: 14/07/2026 | BP62: 02/12/2026 | BQ62: 1.8 | BR62: 0 | BS62: 183.9 | BT62: anual
A63: #VALUE! | B63: {=_FV(A63,"Símbolo bursátil",TRUE())} -> IPCO | C63: Materials | D63: Raw materials | E63: {=_FV(A63,"Abreviatura de intercambio",TRUE())} -> XTSE | F63: {=_FV(A63,"Moneda")} -> CAD | G63: {=_FV(A63,"Precio")} -> 40 | H63: {=_FV(A63,"Acciones en circulación",TRUE())/1000000} -> 111.7277 | I63: =G63*H63 -> 4469.108 | J63: 0 | K63: 2 | L63: 1 | M63: 0 | N63: -2 | O63: 0 | P63: 0 | Q63: 1 | R63: =SUM(J63:N63)+SUM(P63:Q63) -> 2 | S63: =ROUND(R63/16*10,2) -> 1.25 | T63: 9 | U63: 5 | V63: 8 | W63: 6 | X63: 4 | Y63: 9 | Z63: 9 | AA63: -22 | AB63: =SUM(T63:AA63) -> 28 | AC63: =ROUND(AB63/10,2) -> 2.8 | AD63: 6 | AE63: -10 | AF63: 2 | AG63: 9 | AH63: 0 | AI63: 7 | AJ63: 5 | AK63: -11 | AL63: =SUM(AD63:AK63) -> 8 | AM63: =ROUND(AL63/70*10,2) -> 1.14 | AN63: =ROUND(S63*0.2+AC63*0.4+AM63*0.4,2) -> 1.83 | AO63: USD | AP63: 11.3 | AQ63: 517 | AR63: =I63*'Framework Notes'!E7-AP63+AQ63 -> 3673.8507 | AS63: 50.7 | AT63: 76 | AU63: 253 | AV63: 707 | AW63: =AR63/AS63 -> 72.462538 | AX63: =AR63/AU63 -> 14.521149 | AY63: =AR63/AV63 -> 5.1963941 | AZ63: 1833 | BA63: =AT63/AV63 -> 0.10749646 | BB63: =AV63/AZ63 -> 0.38570649 | BC63: =BA63*BB63 -> 0.041462084 | BD63: 178 | BE63: =(BD63/AS63)^(1/5)-1 -> 0.28553057 | BF63: 405 | BG63: =(BF63/AS63)^(1/5)-1 -> 0.51526786 | BH63: 10 | BI63: 15 | BJ63: =((BD63*BH63+$AP63-$AQ63)/$H63)/'Framework Notes'!$E$7 -> 16.088881 | BK63: =((BF63*BI63+$AP63-$AQ63)/$H63)/'Framework Notes'!$E$7 -> 70.3161 | BL63: =IF($BJ63<=0,-0.99,MAX(-0.99,($BJ63/G63)^(1/5)-1)) -> -0.16652386 | BM63: =IF(BK63<=0,-0.99,MAX(-0.99,(BK63/G63)^(1/5)-1)) -> 0.1194352 | BN63: 2026-08-25 | BO63: 04/08/2026 | BP63: 03/11/2026 | BQ63: 10.5 | BR63: 155.3 | BS63: 50.7 | BT63: NORMALIZADO: FCF-SBC -104,6 + capex crecimiento 155,3 (Blackrod; capex 285,8 - DD&A 130,5). FCF@5y sin escalar (base anterior 18,6 no comparable). BF era texto
A64: #VALUE! | B64: {=_FV(A64,"Símbolo bursátil",TRUE())} -> OTLY | C64: Consumo | D64: Special situation | E64: {=_FV(A64,"Abreviatura de intercambio",TRUE())} -> XNAS | F64: {=_FV(A64,"Moneda")} -> USD | G64: {=_FV(A64,"Precio")} -> 11.81 | H64: {=_FV(A64,"Acciones en circulación",TRUE())/1000000} -> 31.91226 | I64: =G64*H64 -> 376.88379 | J64: 1 | K64: 4 | L64: 2 | M64: -1 | N64: -1 | O64: 0 | P64: 0 | Q64: 0 | R64: =SUM(J64:N64)+SUM(P64:Q64) -> 5 | S64: =ROUND(R64/16*10,2) -> 3.13 | T64: 10 | U64: 6 | V64: 13 | W64: 6 | X64: 5.5 | Y64: 9 | Z64: 6 | AA64: -22 | AB64: =SUM(T64:AA64) -> 33.5 | AC64: =ROUND(AB64/10,2) -> 3.35 | AD64: 8 | AE64: -10 | AF64: 4 | AG64: 7 | AH64: -4 | AI64: 4 | AJ64: 7 | AK64: -9 | AL64: =SUM(AD64:AK64) -> 7 | AM64: =ROUND(AL64/70*10,2) -> 1 | AN64: =ROUND(S64*0.2+AC64*0.4+AM64*0.4,2) -> 2.37 | AO64: USD | AP64: 44.6 | AQ64: 549 | AR64: =I64-AP64+AQ64 -> 881.28379 | AS64: -38.2 | AT64: -49 | AU64: -14 | AV64: 925 | AW64: =AR64/AS64 -> -23.070256 | AX64: =AR64/AU64 -> -62.948842 | AY64: =AR64/AV64 -> 0.95273923 | AZ64: 169 | BA64: =AT64/AV64 -> -0.052972973 | BB64: =AV64/AZ64 -> 5.4733728 | BC64: =BA64*BB64 -> -0.28994083 | BD64: -15 | BE64: =(BD64/AS64)^(1/5)-1 -> -0.17052065 | BF64: 99 | BG64: =(BF64/AS64)^(1/5)-1 -> -2.2098022 | BH64: 12 | BI64: 16 | BJ64: =(BD64*BH64+$AP64-$AQ64)/$H64 -> -21.446303 | BK64: =(BF64*BI64+$AP64-$AQ64)/$H64 -> 33.830258 | BL64: =IF($BJ64<=0,-0.99,MAX(-0.99,($BJ64/G64)^(1/5)-1)) -> -0.99 | BM64: =IF(BK64<=0,-0.99,MAX(-0.99,(BK64/G64)^(1/5)-1)) -> 0.23427259 | BN64: 2026-08-25 | BO64: 22/07/2026 | BP64: 04/11/2026 | BQ64: 12.6 | BR64: 0 | BS64: -38.2 | BT64: FCF-SBC NEGATIVO (turnaround, sin capex que normalizar). FCF@5y post-SBC: -15 sobre 0/114 (SBC 1,4% ingresos)
A65: #VALUE! | B65: {=_FV(A65,"Símbolo bursátil",TRUE())} -> CSU | C65: Vertical Saas | D65: Compounder | E65: {=_FV(A65,"Abreviatura de intercambio",TRUE())} -> XTSE | F65: {=_FV(A65,"Moneda")} -> CAD | G65: {=_FV(A65,"Precio")} -> 3170.8 | H65: {=_FV(A65,"Acciones en circulación",TRUE())/1000000} -> 21.19153 | I65: =G65*H65 -> 67194.103 | J65: 2 | K65: 7.5 | L65: 2.5 | M65: 0.75 | N65: -0.5 | O65: 0.5 | P65: 1 | Q65: 1 | R65: =SUM(J65:N65)+SUM(P65:Q65) -> 14.25 | S65: =ROUND(R65/16*10,2) -> 8.91 | T65: 15 | U65: 18 | V65: 15 | W65: 9 | X65: 9 | Y65: 13 | Z65: 9 | AA65: -7 | AB65: =SUM(T65:AA65) -> 81 | AC65: =ROUND(AB65/10,2) -> 8.1 | AD65: 15 | AE65: 0 | AF65: 9 | AG65: 13 | AH65: 3 | AI65: 9 | AJ65: 14 | AK65: -3 | AL65: =SUM(AD65:AK65) -> 60 | AM65: =ROUND(AL65/70*10,2) -> 8.57 | AN65: =ROUND(S65*0.2+AC65*0.4+AM65*0.4,2) -> 8.45 | AO65: USD | AP65: 3089 | AQ65: 4131 | AR65: =I65*'Framework Notes'!$E$7-AP65+AQ65 -> 48675.9 | AS65: 2771 | AT65: 1400 | AU65: 3428 | AV65: 12641 | AW65: =AR65/AS65 -> 17.566185 | AX65: =AR65/AU65 -> 14.199504 | AY65: =AR65/AV65 -> 3.8506368 | AZ65: 5000 | BA65: =AT65/AV65 -> 0.11075073 | BB65: =AV65/AZ65 -> 2.5282 | BC65: =BA65*BB65 -> 0.28 | BD65: 3181.5 | BE65: =(BD65/AS65)^(1/5)-1 -> 0.028014121 | BF65: 5336.7 | BG65: =(BF65/AS65)^(1/5)-1 -> 0.1400588 | BH65: 12 | BI65: 22 | BJ65: =((BD65*BH65+$AP65-$AQ65)/$H65)/'Framework Notes'!$E$7 -> 2471.9964 | BK65: =((BF65*BI65+$AP65-$AQ65)/$H65)/'Framework Notes'!$E$7 -> 7745.9837 | BL65: =IF($BJ65<=0,-0.99,MAX(-0.99,($BJ65/G65)^(1/5)-1)) -> -0.048572288 | BM65: =IF(BK65<=0,-0.99,MAX(-0.99,(BK65/G65)^(1/5)-1)) -> 0.19558799 | BN65: 2026-08-25 | BO65: 11/08/2026 | BP65: 05/11/2026 | BQ65: 0 | BR65: 0 | BS65: 2771 | BT65: no reportado (0)
A66: #VALUE! | B66: {=_FV(A66,"Símbolo bursátil",TRUE())} -> UBER | C66: Marketplace | D66: Compounder | E66: {=_FV(A66,"Abreviatura de intercambio",TRUE())} -> XNYS | F66: {=_FV(A66,"Moneda")} -> USD | G66: {=_FV(A66,"Precio")} -> 70.34 | H66: {=_FV(A66,"Acciones en circulación",TRUE())/1000000} -> 2042.56 | I66: =G66*H66 -> 143673.67 | J66: 1 | K66: 6 | L66: 2.5 | M66: 0.5 | N66: 0 | O66: 0 | P66: 0.5 | Q66: 0 | R66: =SUM(J66:N66)+SUM(P66:Q66) -> 10.5 | S66: =ROUND(R66/16*10,2) -> 6.56 | T66: 13 | U66: 15 | V66: 14 | W66: 7 | X66: 6 | Y66: 9 | Z66: 6 | AA66: -12 | AB66: =SUM(T66:AA66) -> 58 | AC66: =ROUND(AB66/10,2) -> 5.8 | AD66: 10 | AE66: -2 | AF66: 9 | AG66: 8 | AH66: 3 | AI66: 5 | AJ66: 10 | AK66: -8 | AL66: =SUM(AD66:AK66) -> 35 | AM66: =ROUND(AL66/70*10,2) -> 5 | AN66: =ROUND(S66*0.2+AC66*0.4+AM66*0.4,2) -> 5.63 | AO66: USD | AP66: 5391 | AQ66: 14731 | AR66: =I66-AP66+AQ66 -> 153013.67 | AS66: 8177 | AT66: 5025 | AU66: 7475 | AV66: 55227 | AW66: =AR66/AS66 -> 18.712691 | AX66: =AR66/AU66 -> 20.470056 | AY66: =AR66/AV66 -> 2.7706316 | AZ66: 37739 | BA66: =AT66/AV66 -> 0.090988104 | BB66: =AV66/AZ66 -> 1.4633933 | BC66: =BA66*BB66 -> 0.13315138 | BD66: 7250.7 | BE66: =(BD66/AS66)^(1/5)-1 -> -0.023758675 | BF66: 21743.9 | BG66: =(BF66/AS66)^(1/5)-1 -> 0.21604232 | BH66: 14 | BI66: 24 | BJ66: =(BD66*BH66+AP66-AQ66)/H66 -> 45.124648 | BK66: =(BF66*BI66+AP66-AQ66)/H66 -> 250.91728 | BL66: =IF($BJ66<=0,-0.99,MAX(-0.99,($BJ66/G66)^(1/5)-1)) -> -0.084955338 | BM66: =IF(BK66<=0,-0.99,MAX(-0.99,(BK66/G66)^(1/5)-1)) -> 0.28963153 | BN66: 2026-09-12 | BO66: 05/08/2026 | BP66: 03/11/2026 | BQ66: 1939 | BR66: 0 | BS66: 8177 | BT66: trimestral. FCF 10.116 - SBC 1.939 = 8.177 (14,8%). Caja/deuda son el balance a 30-jun; PRO FORMA con Delivery Hero (41,50 EUR en efectivo, cierre 2S27): deuda neta ~21.400 (2,0-2,3x EBITDA aj.). Take rate Mobility -500 pb de los que 400 son opticos (UK). Deep dive 12-sep-2026 | 9/15-sep-2026: emision de 4.500 M EUR en bonos (2029-2046), financiacion de Delivery Hero
A67: #VALUE! | B67: {=_FV(A67,"Símbolo bursátil",TRUE())} -> SOM | C67: construction | D67: Special situation | E67: =_FV(A67,"Abreviatura de intercambio",TRUE) -> XLON | F67: =_FV(A67,"Moneda") -> GBp | G67: =_FV(A67,"Precio") -> 282 | H67: =_FV(A67,"Acciones en circulación",TRUE)/1000000 -> 51.59163 | I67: =G67/100*H67 -> 145.4884 | J67: 1 | K67: 5 | L67: 2 | M67: 1 | N67: -2 | O67: -1 | P67: 0 | Q67: -1 | R67: =SUM(J67:N67)+SUM(P67:Q67) -> 6 | S67: =ROUND(R67/16*10,2) -> 3.75 | T67: 11 | U67: 11 | V67: 8 | W67: 6 | X67: 4 | Y67: 9 | Z67: 2 | AA67: -18 | AB67: =SUM(T67:AA67) -> 33 | AC67: =ROUND(AB67/10,2) -> 3.3 | AD67: 10 | AE67: -2 | AF67: 7 | AG67: 9 | AH67: 3 | AI67: 3 | AJ67: 8 | AK67: -7 | AL67: =SUM(AD67:AK67) -> 31 | AM67: =ROUND(AL67/70*10,2) -> 4.43 | AN67: =ROUND(S67*0.2+AC67*0.4+AM67*0.4,2) -> 3.84 | AO67: USD | AP67: 29.6 | AQ67: 0.8 | AR67: =I67*'Framework Notes'!$E$9-AP67+AQ67 -> 164.77231 | AS67: 18.4 | AT67: 13.3 | AU67: 21.2 | AV67: 97.7 | AW67: =AR67/AS67 -> 8.9550169 | AX67: =AR67/AU67 -> 7.7722789 | AY67: =AR67/AV67 -> 1.6865129 | AZ67: 51.47 | BA67: =AT67/AV67 -> 0.13613101 | BB67: =AV67/AZ67 -> 1.8981931 | BC67: =BA67*BB67 -> 0.25840295 | BD67: 16 | BE67: =(BD67/AS67)^(1/5)-1 -> -0.027565335 | BF67: 27 | BG67: =(BF67/AS67)^(1/5)-1 -> 0.079715133 | BH67: 12 | BI67: 22 | BJ67: =((BD67*BH67+$AP67-$AQ67)/$H67)/'Framework Notes'!$E$9*100 -> 321.66584 | BK67: =((BF67*BI67+$AP67-$AQ67)/$H67)/'Framework Notes'!$E$9*100 -> 907.30745 | BL67: =IF($BJ67<=0,-0.99,MAX(-0.99,($BJ67/G67)^(1/5)-1)) -> 0.026670697 | BM67: =IF(BK67<=0,-0.99,MAX(-0.99,(BK67/G67)^(1/5)-1)) -> 0.26328423 | BN67: 2026-09-27 | BO67: 08/09/2026 | BP67: 20/01/2027 | BQ67: 1 | BR67: 0 | BS67: 18.4 | BT67: FUENTE: RNS resultados FY25 + interinos 1S26 (8-sep). LTM = FY25 + 1S26 - 1S25: OCF 20,7 - capex 0,9 - arrend. financ. 0,3 - SBC 1,0 = 18,4. Ingresos 88,857-39,828+48,675. Caja 29,6, sin deuda (0,8 arrend. financieros). Guia FY26 subida a ~95 / EBITDA 19,5. Grupo VN Capital (~44%) entra en el consejo (21-sep). FCF@5y de Roger sin tocar. Proximo: trading update (estimado) | 1-oct-2026: junta extraordinaria el 10-nov para pasar el consejo a mandatos de 2 anios y voto por mayoria (acuerdo con VN Capital)
A68: #VALUE! | B68: {=_FV(A68,"Símbolo bursátil",TRUE())} -> IP | C68: Industrial | D68: Compounder | E68: =_FV(A68,"Abreviatura de intercambio",TRUE) -> XMIL | F68: =_FV(A68,"Moneda") -> EUR | G68: =_FV(A68,"Precio") -> 36.82 | H68: =_FV(A68,"Acciones en circulación",TRUE)/1000000 -> 108.8793 | I68: =G68*H68 -> 4008.9358 | J68: 1 | K68: 5 | L68: 1 | M68: 1 | N68: -1 | O68: 0 | P68: 1 | Q68: 1 | R68: =SUM(J68:N68)+SUM(P68:Q68) -> 9 | S68: =ROUND(R68/16*10,2) -> 5.63 | T68: 13 | U68: 13 | V68: 9 | W68: 8 | X68: 6 | Y68: 10 | Z68: 8 | AA68: -12 | AB68: =SUM(T68:AA68) -> 55 | AC68: =ROUND(AB68/10,2) -> 5.5 | AD68: 12 | AE68: -2 | AF68: 4 | AG68: 9 | AH68: 4 | AI68: 5 | AJ68: 10 | AK68: -6 | AL68: =SUM(AD68:AK68) -> 36 | AM68: =ROUND(AL68/70*10,2) -> 5.14 | AN68: =ROUND(S68*0.2+AC68*0.4+AM68*0.4,2) -> 5.38 | AO68: EUR | AP68: 370 | AQ68: 675 | AR68: =I68-AP68+AQ68 -> 4313.9358 | AS68: 246.1 | AT68: 229 | AU68: 446 | AV68: 2080 | AW68: =AR68/AS68 -> 17.529199 | AX68: =AR68/AU68 -> 9.6725019 | AY68: =AR68/AV68 -> 2.0740076 | AZ68: 2401.1 | BA68: =AT68/AV68 -> 0.11009615 | BB68: =AV68/AZ68 -> 0.86626963 | BC68: =BA68*BB68 -> 0.095372954 | BD68: 211 | BE68: =(BD68/AS68)^(1/5)-1 -> -0.030307206 | BF68: 513.6 | BG68: =(BF68/AS68)^(1/5)-1 -> 0.15851772 | BH68: 16 | BI68: 20.5 | BJ68: =(BD68*BH68+$AP68-$AQ68)/$H68 -> 28.205545 | BK68: =(BF68*BI68+$AP68-$AQ68)/$H68 -> 93.90031 | BL68: =IF($BJ68<=0,-0.99,MAX(-0.99,($BJ68/G68)^(1/5)-1)) -> -0.051908741 | BM68: =IF(BK68<=0,-0.99,MAX(-0.99,(BK68/G68)^(1/5)-1)) -> 0.20591486 | BN68: 2026-08-25 | BO68: 06/08/2026 | BP68: 13/11/2026 | BQ68: 6.6 | BR68: 0 | BS68: 246.1 | BT68: trimestral
A69: #VALUE! | B69: {=_FV(A69,"Símbolo bursátil",TRUE())} -> RBT | C69: Consumo | D69: Compounder | E69: =_FV(A69,"Abreviatura de intercambio",TRUE) -> XPAR | F69: =_FV(A69,"Moneda") -> EUR | G69: =_FV(A69,"Precio") -> 777 | H69: =_FV(A69,"Acciones en circulación",TRUE)/1000000 -> 2.1693 | I69: =G69*H69 -> 1685.5461 | J69: 2 | K69: 6 | L69: 2 | M69: 1 | N69: 0 | O69: 0 | P69: 1 | Q69: 1 | R69: =SUM(J69:N69)+SUM(P69:Q69) -> 13 | S69: =ROUND(R69/16*10,2) -> 8.13 | T69: 13 | U69: 15 | V69: 11 | W69: 9 | X69: 9 | Y69: 11 | Z69: 9 | AA69: -9 | AB69: =SUM(T69:AA69) -> 68 | AC69: =ROUND(AB69/10,2) -> 6.8 | AD69: 14 | AE69: -1 | AF69: 3 | AG69: 11 | AH69: 4 | AI69: 5 | AJ69: 13 | AK69: -3 | AL69: =SUM(AD69:AK69) -> 46 | AM69: =ROUND(AL69/70*10,2) -> 6.57 | AN69: =ROUND(S69*0.2+AC69*0.4+AM69*0.4,2) -> 6.97 | AO69: EUR | AP69: 136.6 | AQ69: 228.4 | AR69: =I69-AP69+AQ69 -> 1777.3461 | AS69: 64.4 | AT69: 99 | AU69: 167.5 | AV69: 841.9 | AW69: =AR69/AS69 -> 27.598542 | AX69: =AR69/AU69 -> 10.611021 | AY69: =AR69/AV69 -> 2.1111131 | AZ69: 713.6 | BA69: =AT69/AV69 -> 0.11759116 | BB69: =AV69/AZ69 -> 1.1797926 | BC69: =BA69*BB69 -> 0.13873318 | BD69: 82.1 | BE69: =(BD69/AS69)^(1/5)-1 -> 0.049763475 | BF69: 145 | BG69: =(BF69/AS69)^(1/5)-1 -> 0.17624131 | BH69: 18 | BI69: 26 | BJ69: =(BD69*BH69+$AP69-$AQ69)/$H69 -> 638.91578 | BK69: =(BF69*BI69+$AP69-$AQ69)/$H69 -> 1695.57 | BL69: =IF($BJ69<=0,-0.99,MAX(-0.99,($BJ69/G69)^(1/5)-1)) -> -0.038377716 | BM69: =IF(BK69<=0,-0.99,MAX(-0.99,(BK69/G69)^(1/5)-1)) -> 0.16890426 | BN69: 2026-09-27 | BO69: 17/09/2026 | BP69: 23/10/2026 | BQ69: 0 | BR69: 13.2 | BS69: 77.6 | BT69: FUENTE: informe financiero semestral 2026 (lleva columna FY25). LTM: OCF 117,8 - capex 45,6 - arrendamientos ~7,8 (2x el semestre; el anual 2025 pendiente del DEU) = 64,4. D&A 32,4 -> capex de crecimiento 13,2 -> 77,6. Deuda financiera 228,4 (sin 28,3 de arrendamientos). EBITDA recurrente 174,1-100,2+93,6. Objetivo 2026 rebajado a 3-5% organico. Proximo: ventas 3T (estimado)
A70: #VALUE! | B70: {=_FV(A70,"Símbolo bursátil",TRUE())} -> ROKO B | C70: Industrial | D70: Compounder | E70: =_FV(A70,"Abreviatura de intercambio",TRUE) -> XSTO | F70: =_FV(A70,"Moneda") -> SEK | G70: =_FV(A70,"Precio") -> 1900 | H70: =_FV(A70,"Acciones en circulación",TRUE)/1000000 -> 12.1365 | I70: =G70*H70 -> 23059.35 | J70: 1 | K70: 5 | L70: 3 | M70: 0 | N70: 0 | O70: 0 | P70: 1 | Q70: 1 | R70: =SUM(J70:N70)+SUM(P70:Q70) -> 11 | S70: =ROUND(R70/16*10,2) -> 6.88 | T70: 12 | U70: 12 | V70: 15 | W70: 8 | X70: 7 | Y70: 12 | Z70: 10 | AA70: -14 | AB70: =SUM(T70:AA70) -> 62 | AC70: =ROUND(AB70/10,2) -> 6.2 | AD70: 12 | AE70: -3 | AF70: 8 | AG70: 12 | AH70: 1 | AI70: 9 | AJ70: 9 | AK70: -7 | AL70: =SUM(AD70:AK70) -> 41 | AM70: =ROUND(AL70/70*10,2) -> 5.86 | AN70: =ROUND(S70*0.2+AC70*0.4+AM70*0.4,2) -> 6.2 | AO70: SEK | AP70: 435 | AQ70: 3020 | AR70: =I70-AP70+AQ70 -> 25644.35 | AS70: 1196 | AT70: 893 | AU70: 1560 | AV70: 7090 | AW70: =AR70/AS70 -> 21.441764 | AX70: =AR70/AU70 -> 16.438686 | AY70: =AR70/AV70 -> 3.6169746 | AZ70: 9895 | BA70: =AT70/AV70 -> 0.12595205 | BB70: =AV70/AZ70 -> 0.7165235 | BC70: =BA70*BB70 -> 0.0902476 | BD70: 1196 | BE70: =(BD70/AS70)^(1/5)-1 -> 0 | BF70: 1976 | BG70: =(BF70/AS70)^(1/5)-1 -> 0.10563341 | BH70: 19 | BI70: 26 | BJ70: =(BD70*BH70+$AP70-$AQ70)/$H70 -> 1659.3746 | BK70: =(BF70*BI70+$AP70-$AQ70)/$H70 -> 4020.187 | BL70: =IF($BJ70<=0,-0.99,MAX(-0.99,($BJ70/G70)^(1/5)-1)) -> -0.026719173 | BM70: =IF(BK70<=0,-0.99,MAX(-0.99,(BK70/G70)^(1/5)-1)) -> 0.16171215 | BN70: 2026-08-25 | BO70: 17/07/2026 | BP70: 22/10/2026 | BQ70: 0 | BR70: 0 | BS70: 1196 | BT70: no reportado (0)
A71: #VALUE! | B71: {=_FV(A71,"Símbolo bursátil",TRUE())} -> USPH | C71: Healthcare | D71: Compounder | E71: =_FV(A71,"Abreviatura de intercambio",TRUE) -> XNYS | F71: =_FV(A71,"Moneda") -> USD | G71: =_FV(A71,"Precio") -> 84.435 | H71: =_FV(A71,"Acciones en circulación",TRUE)/1000000 -> 14.9227 | I71: =G71*H71 -> 1259.9982 | J71: 2 | K71: 4 | L71: 2 | M71: -1 | N71: -1 | O71: 0 | P71: 0 | Q71: -1 | R71: =SUM(J71:N71)+SUM(P71:Q71) -> 5 | S71: =ROUND(R71/16*10,2) -> 3.13 | T71: 8 | U71: 8 | V71: 13 | W71: 7 | X71: 8 | Y71: 9 | Z71: 3 | AA71: -20 | AB71: =SUM(T71:AA71) -> 36 | AC71: =ROUND(AB71/10,2) -> 3.6 | AD71: 12 | AE71: -4 | AF71: 8 | AG71: 6 | AH71: -3 | AI71: 4 | AJ71: 6 | AK71: -9 | AL71: =SUM(AD71:AK71) -> 20 | AM71: =ROUND(AL71/70*10,2) -> 2.86 | AN71: =ROUND(S71*0.2+AC71*0.4+AM71*0.4,2) -> 3.21 | AO71: USD | AP71: 24.9 | AQ71: 385.8 | AR71: =I71-AP71+AQ71 -> 1620.8982 | AS71: 54.2 | AT71: 57 | AU71: 96 | AV71: 804.3 | AW71: =AR71/AS71 -> 29.90587 | AX71: =AR71/AU71 -> 16.884356 | AY71: =AR71/AV71 -> 2.0152905 | AZ71: 1127.6 | BA71: =AT71/AV71 -> 0.070869079 | BB71: =AV71/AZ71 -> 0.71328485 | BC71: =BA71*BB71 -> 0.05054984 | BD71: 52.5 | BE71: =(BD71/AS71)^(1/5)-1 -> -0.0063532798 | BF71: 91.8 | BG71: =(BF71/AS71)^(1/5)-1 -> 0.11113974 | BH71: 19 | BI71: 26 | BJ71: =(BD71*BH71+$AP71-$AQ71)/$H71 -> 42.65984 | BK71: =(BF71*BI71+$AP71-$AQ71)/$H71 -> 135.75961 | BL71: =IF($BJ71<=0,-0.99,MAX(-0.99,($BJ71/G71)^(1/5)-1)) -> -0.12763277 | BM71: =IF(BK71<=0,-0.99,MAX(-0.99,(BK71/G71)^(1/5)-1)) -> 0.099637692 | BN71: 2026-08-21 | BO71: 05/08/2026 | BP71: 05/11/2026 | BQ71: 9.9 | BR71: 0 | BS71: 54.2 | BT71: trimestral
A72: #VALUE! | B72: {=_FV(A72,"Símbolo bursátil",TRUE())} -> SAP | C72: Vertical Saas | D72: Compounder | E72: =_FV(A72,"Abreviatura de intercambio",TRUE) -> XETR | F72: =_FV(A72,"Moneda") -> EUR | G72: =_FV(A72,"Precio") -> 199.84 | H72: =_FV(A72,"Acciones en circulación",TRUE)/1000000 -> 1228.504 | I72: =G72*H72 -> 245504.24 | J72: 1 | K72: 7 | L72: 2 | M72: 1 | N72: 0 | O72: 0 | P72: 0 | Q72: 0 | R72: =SUM(J72:N72)+SUM(P72:Q72) -> 11 | S72: =ROUND(R72/16*10,2) -> 6.88 | T72: 15 | U72: 18 | V72: 12 | W72: 10 | X72: 10 | Y72: 11 | Z72: 5 | AA72: -9 | AB72: =SUM(T72:AA72) -> 72 | AC72: =ROUND(AB72/10,2) -> 7.2 | AD72: 14 | AE72: -2 | AF72: 9 | AG72: 10 | AH72: 4 | AI72: 7 | AJ72: 14 | AK72: -5 | AL72: =SUM(AD72:AK72) -> 51 | AM72: =ROUND(AL72/70*10,2) -> 7.29 | AN72: =ROUND(S72*0.2+AC72*0.4+AM72*0.4,2) -> 7.17 | AO72: EUR | AP72: 11630 | AQ72: 9940 | AR72: =I72-AP72+AQ72 -> 243814.24 | AS72: 7231 | AT72: 7892 | AU72: 11760 | AV72: 38190 | AW72: =AR72/AS72 -> 33.717914 | AX72: =AR72/AU72 -> 20.732503 | AY72: =AR72/AV72 -> 6.384243 | AZ72: 55875 | BA72: =AT72/AV72 -> 0.20665096 | BB72: =AV72/AZ72 -> 0.68348993 | BC72: =BA72*BB72 -> 0.14124385 | BD72: 7951.6 | BE72: =(BD72/AS72)^(1/5)-1 -> 0.019180798 | BF72: 12755.7 | BG72: =(BF72/AS72)^(1/5)-1 -> 0.12021449 | BH72: 16 | BI72: 24 | BJ72: =(BD72*BH72+$AP72-$AQ72)/$H72 -> 104.93706 | BK72: =(BF72*BI72+$AP72-$AQ72)/$H72 -> 250.57045 | BL72: =IF($BJ72<=0,-0.99,MAX(-0.99,($BJ72/G72)^(1/5)-1)) -> -0.1208777 | BM72: =IF(BK72<=0,-0.99,MAX(-0.99,(BK72/G72)^(1/5)-1)) -> 0.046283765 | BN72: 2026-08-26 | BO72: 22/07/2026 | BP72: 21/10/2026 | BQ72: 1499 | BR72: 0 | BS72: 7231 | BT72: trimestral
A73: #VALUE! | B73: {=_FV(A73,"Símbolo bursátil",TRUE())} -> VYLR | C73: Materials | D73: Compounder | E73: =_FV(A73,"Abreviatura de intercambio",TRUE) -> XNYS | F73: =_FV(A73,"Moneda") -> USD | G73: =_FV(A73,"Precio") -> 71.66 | H73: =_FV(A73,"Acciones en circulación",TRUE)/1000000 -> 667.196 | I73: =G73*H73 -> 47811.265 | J73: 1 | K73: 7 | L73: 2 | M73: 0 | N73: -1 | O73: 0 | P73: 0 | Q73: 0 | R73: =SUM(J73:N73)+SUM(P73:Q73) -> 9 | S73: =ROUND(R73/16*10,2) -> 5.63 | T73: 12 | U73: 16 | V73: 12 | W73: 9 | X73: 10 | Y73: 9 | Z73: 5 | AA73: -9 | AB73: =SUM(T73:AA73) -> 64 | AC73: =ROUND(AB73/10,2) -> 6.4 | AD73: 14 | AE73: -1 | AF73: 6 | AG73: 9 | AH73: 2 | AI73: 6 | AJ73: 13 | AK73: -3 | AL73: =SUM(AD73:AK73) -> 46 | AM73: =ROUND(AL73/70*10,2) -> 6.57 | AN73: =ROUND(S73*0.2+AC73*0.4+AM73*0.4,2) -> 6.31 | AO73: USD | AP73: 1100 | AQ73: 5659 | AR73: =I73-AP73+AQ73 -> 52370.265 | AS73: 1195 | AT73: 1172 | AU73: 2931 | AV73: 10209 | AW73: =AR73/AS73 -> 43.82449 | AX73: =AR73/AU73 -> 17.867713 | AY73: =AR73/AV73 -> 5.1298134 | AZ73: 16827 | BA73: =AT73/AV73 -> 0.11480067 | BB73: =AV73/AZ73 -> 0.60670351 | BC73: =BA73*BB73 -> 0.069649967 | BD73: 2200 | BE73: =(BD73/AS73)^(1/5)-1 -> 0.12982441 | BF73: 3320 | BG73: =(BF73/AS73)^(1/5)-1 -> 0.22674426 | BH73: 14 | BI73: 22 | BJ73: =(BD73*BH73+$AP73-$AQ73)/$H73 -> 39.330272 | BK73: =(BF73*BI73+$AP73-$AQ73)/$H73 -> 102.64 | BL73: =IF($BJ73<=0,-0.99,MAX(-0.99,($BJ73/G73)^(1/5)-1)) -> -0.1130686 | BM73: =IF(BK73<=0,-0.99,MAX(-0.99,(BK73/G73)^(1/5)-1)) -> 0.074503838 | BN73: 2026-08-26 | BO73: 05/08/2026 | BP73: 05/11/2026 | BQ73: 47 | BR73: 33 | BS73: 1228 | BT73: VYLOR (semillas de Corteva) desde el 1-oct-2026, sustituye a CTVA por decision de Roger (2-oct). FUENTE: Form 10 de Vylor (EDGAR, 21-sep-2026): estados combinados del negocio de semillas. LTM = FY25 + H1-26 - H1-25. Ventas 9.898 + 7.555 - 7.244 = 10.209. EBITDA operativo del segmento 2.636 + 3.000 - 2.705 = 2.931 (antes de costes corporativos; pro forma FY25 2.503). Flujo de explotacion 2.506 - 2.471 + 1.557 = 1.592 - capex 350 - SBC 47 = 1.195: INCLUYE el pago unico a Bayer por el litigio (cargo de 610 en FY25, pagado en el H1-26); sin el ~1.800; FY25 2.118. Capex de crecimiento 350 - depreciacion 317 = 33 -> BS 1.228. NOPAT ~1.172 (EBIT FY25 sin Bayer 1.562 x 75%). Caja 1.100 y deuda 5.659 pro forma a 30-jun-2026; capital empleado = fondos propios pro forma 12.268 + deuda neta. | 2-oct (Roger: 'rehaz todo con Vylor, sin tocar los multiplos'): FCF@5y 2.200 / 3.320 sobre un FCF limpio de partida ~1.900 (FY25 2.118 y LTM sin Bayer ~1.800, menos ~130 de intereses netos de la deuda de la escision: cargo pro forma 170). Bajista: ventas +2%/anio, margen FCF 19,5% -> 2.200 (+3%/anio). Alcista: ventas +5%/anio (precio +3% como en 2024-26, licencias), margen 25,5% por el giro de regalias (coste neto 439 en 2025 -> neutral en 2026 -> +1.000 en 2035) -> 3.320 (+12%/anio). OJO: el crecimiento implicito de BE/BG se calcula contra AS (1.195, deprimido por Bayer) y sale inflado; contra 1.900 es +3% / +12%. Multiplos 14x / 22x de Roger SIN CAMBIO. Ratings rehechos para semillas: ver Updates Log del 2-oct. Q3: ~5-nov-2026 (estimado)
A74: #VALUE! | B74: {=_FV(A74,"Símbolo bursátil",TRUE())} -> RCL | C74: Consumo | D74: Special situation | E74: =_FV(A74,"Abreviatura de intercambio",TRUE) -> XNYS | F74: =_FV(A74,"Moneda") -> USD | G74: =_FV(A74,"Precio") -> 281.22 | H74: =_FV(A74,"Acciones en circulación",TRUE)/1000000 -> 267.4521 | I74: =G74*H74 -> 75212.88 | J74: 1 | K74: 4.5 | L74: 2 | M74: -0.5 | N74: -1 | P74: 0.5 | Q74: 0 | R74: =SUM(J74:N74)+SUM(P74:Q74) -> 6.5 | S74: =ROUND(R74/16*10,2) -> 4.06 | T74: 10 | U74: 11 | V74: 12 | W74: 8 | X74: 4 | Y74: 8 | Z74: 5 | AA74: -17 | AB74: =SUM(T74:AA74) -> 41 | AC74: =ROUND(AB74/10,2) -> 4.1 | AD74: 10 | AE74: -5 | AF74: 1 | AG74: 7 | AH74: 0 | AI74: 5 | AJ74: 8 | AK74: -8 | AL74: =SUM(AD74:AK74) -> 18 | AM74: =ROUND(AL74/70*10,2) -> 2.57 | AN74: =ROUND(S74*0.2+AC74*0.4+AM74*0.4,2) -> 3.48 | AO74: USD | AP74: 875 | AQ74: 22836 | AR74: =I74-AP74+AQ74 -> 97173.88 | AS74: 4821 | AT74: 4984 | AU74: 6920 | AV74: 18682 | AW74: =AR74/AS74 -> 20.156374 | AX74: =AR74/AU74 -> 14.042468 | AY74: =AR74/AV74 -> 5.2014709 | AZ74: 32197 | BA74: =AT74/AV74 -> 0.26678086 | BB74: =AV74/AZ74 -> 0.5802404 | BC74: =BA74*BB74 -> 0.15479703 | BD74: 5308.7 | BE74: =(BD74/AS74)^(1/5)-1 -> 0.019460047 | BF74: 8908.4 | BG74: =(BF74/AS74)^(1/5)-1 -> 0.13066127 | BH74: 8 | BI74: 11.5 | BJ74: =((BD74*BH74+$AP74-$AQ74)/$H74) -> 76.681395 | BK74: =((BF74*BI74+$AP74-$AQ74)/$H74) -> 300.93463 | BL74: =IF($BJ74<=0,-0.99,MAX(-0.99,($BJ74/G74)^(1/5)-1)) -> -0.22886794 | BM74: =IF(BK74<=0,-0.99,MAX(-0.99,(BK74/G74)^(1/5)-1)) -> 0.013643393 | BN74: 2026-09-27 | BO74: 28/07/2026 | BP74: 27/10/2026 | BQ74: 151 | BR74: 5388 | BS74: 4821 | BT74: FUENTE: 10-Q Q2 2026 (EDGAR XBRL). NORMALIZADO: OCF 6.786 - SBC 151 - D&A 1.814 (mantenimiento); capex de barcos 7.202 = crecimiento. Deuda 21.263 + 1.573 = 22.836 (el 26-sep puse 23.518 de yfinance: error). Proximos estimados | 23-sep-2026 (8-K): compra del 50% de Sandals y Beaches Resorts por ~3.000 M$ (~10x EBITDA futuro), con deuda comprometida (Morgan Stanley); cierre a principios de 2027: la deuda subira ~3.000 al cerrar

Sheet Framework Notes
A1: WATCHLIST RATINGS — METHODOLOGICAL NOTES
A3: Philosophy
A4: Long-term investor framework applied across 61 public equities. | D4: #VALUE! | E4: {=_FV(D4,"Precio")} -> 177.72
A5: Ratings are conservative, designed to surface quality + risk simultaneously. | D5: #VALUE! | E5: {=_FV(D5,"Precio")} -> 1.2098
A6: No hype factor. Revenue growth alone is not quality. | D6: #VALUE! | E6: {=_FV(D6,"Precio")} -> 451.89
D7: #VALUE! | E7: {=_FV(D7,"Precio")} -> 0.7089
A8: RATING 1 - Structural Quality (max 16, normalized to 10) - Glassdoor excluded 21-Aug-2026 | D8: #VALUE! | E8: {=_FV(D8,"Precio")} -> 0.8917
A9: Mission (-1 to 2): Purpose, long-term relevance of the business | C9: USD por GBP (KIST, SOM) - GBP/USD 1,3305 al 19-oct-2026 (yfinance; valor fijo, no vinculado: actualizar a mano) | E9: 1.3305
A10: MOAT (0 to 8): Durable competitive advantages
A11: Optionality (0 to 3): Capacity to open adjacent growth vectors
A12: Financials (-1 to 1): Balance sheet discipline and current health
A13: Concentration (-3 to 0): Customer/product/geography dependency (penalty)
A14: Glassdoor (-1 to 1): RETIRED 21-Aug-2026. Blank in 38 of 68 rows and mixing two scales; column kept but no longer summed. Culture is judged in R2 Mgmt & Culture and R3 Incentives.
A15: Founder/CEO (0 to 1): Leadership quality and founder involvement
A16: Ownership (-1 to 1): Skin in the game alignment
A18: RATING 2 — Economic Quality & Value Creation (max 100, normalized to 10)
A19: Financials (0–17): Financial solidity: margins, FCF, ROIC
A20: MOAT (0–20): Competitive advantage weight on value creation
A21: Potential (0–18): TAM, runway, capacity for compounding
A22: Customers (0–10): Quality, diversification, dependency
... A72: Estado a 25-ago-2026: los cuatro pasos hechos en AMZN, MSFT, CSU, BN, COST, LIFCO B, RAA y LOTB (22-ago); en NTO, ABNB, DNP, LR, STMN, KKR, KRX, SPOT, CPR, TFPM, TREX y SGO (25-ago, resultados nuevos); y en COST, DSGX, ZS, SU, ITX, EVD, VLTO, JDG, META, GOOG, ABBNE, GRMN, NVDA, TSM, SIKA, CHKP, NFLX, NKE, IP, RBT y ROKO B (25-ago, refresco de LTM). Con los pasos 1-3 hechos y el 4 pendiente a proposito: FERG, IPCO, NET y CRWD (estas dos con EV/FCF de 303x y 127x, los multiplos de salida no pueden capturar el precio). Pendientes de publicar: VEEV y NVDA el 26-ago, EVD y S el 27-ago, SOM el 8-sep, DSGX el 10-sep, JDG el 22-sep.

Sheet Dashboard
A1: 📊 INVESTMENT COMMAND CENTER — Portfolio Analytics Dashboard
A2: Calidad del Negocio | Opcionalidad | Antifragilidad | ROIC | Múltiplo | Asimetría — Actualizado: April 2026
A3: 📊 EMPRESAS | C3: ⭐ CALIDAD | E3: 💰 ROIC | G3: 📈 EV/FCF | I3: ✅ ASIMETRÍA + | K3: 🏆 TOP TIER
A4: =COUNTA('Watchlist Ratings'!B4:B71) -> 68 | C4: =ROUND(AVERAGE('Watchlist Ratings'!AN4:AN71),2) -> 5.98 | E4: =TEXT(AVERAGE('Watchlist Ratings'!BC4:BC71),"0.0%") -> 16.4% | G4: =TEXT(AVERAGE('Watchlist Ratings'!AW4:AW71),"0.0x") -> 25.3x | I4: =COUNTIF('Watchlist Ratings'!BM4:BM71,">0") -> 57 | K4: =COUNTIF('Watchlist Ratings'!AN4:AN71,">7.5") -> 16
A5: Total Watchlist | C5: Rating Compuesto | E5: Retorno Capital | G5: Múltiplo Medio | I5: IRR Bull > 0 | K5: Rating > 7.5
A6: ▬▬▬ | C6: ▲ +0.3 | E6: ▲ +2.1% | G6: ▼ -1.2x | I6: ▲ +5 | K6: ═══ | O6: Scatter Data - Composite vs IRR Bull | S6: Top 10 ROIC | V6: MOAT & Optionality | Y6: Múltiplo EV/FCF | AA6: Asimetría IRR | AE6: Ticker | AF6: ROIC % | AH6: Ticker | AI6: ROIC % | AJ6: Ticker | AK6: MOAT | AL6: Optionality | AM6: Ticker | AN6: EV/FCF | AO6: Ticker | AP6: IRR Bear % | AQ6: IRR Bull % | AS6: Ticker | AT6: EV/FCF | AU6: IRR Bull %
A7: # | B7: Ticker | C7: Calidad R1 | D7: Económico R2 | E7: Durabilidad R3 | F7: Composite | G7: MOAT | H7: Optionalidad | I7: ROIC | J7: EV/FCF | O7: Ticker | P7: Composite | Q7: IRR Bull | S7: Ticker | T7: ROIC | V7: Ticker | W7: MOAT | X7: Optionality | Y7: Ticker | Z7: EV/FCF | AA7: Ticker | AB7: IRR Bear | AC7: IRR Bull | AE7: NVDA | AF7: 83.333333 | AH7: NVDA | AI7: 83.3 | AJ7: VEEV | AK7: 8 | AL7: 3 | AM7: AMZN | AN7: 52.2 | AO7: VEEV | AP7: 4.5 | AQ7: 33.6 | AS7: VEEV | AT7: 20.1736 | AU7: 33.701681
A8: 🏆 TOP 15 — RANKING POR CALIDAD COMPUESTA | O8: ='Watchlist Ratings'!B4 -> VEEV | P8: ='Watchlist Ratings'!AN4 -> 8.33 | Q8: ='Watchlist Ratings'!BM4 -> 0.086690219 | S8: ='Watchlist Ratings'!B4 -> VEEV | T8: ='Watchlist Ratings'!BC4 -> 0.52733333 | V8: ='Watchlist Ratings'!B4 -> VEEV | W8: ='Watchlist Ratings'!K4 -> 8 | X8: ='Watchlist Ratings'!L4 -> 2 | Y8: ='Watchlist Ratings'!B4 -> VEEV | Z8: ='Watchlist Ratings'!AW4 -> 38.46297 | AA8: ='Watchlist Ratings'!B4 -> VEEV | AB8: ='Watchlist Ratings'!BL4 -> -0.12371514 | AC8: ='Watchlist Ratings'!BM4 -> 0.086690219 | AE8: CHKP | AF8: 83.333333 | AH8: CHKP | AI8: 83.3 | AJ8: MSFT | AK8: 8 | AL8: 3 | AM8: COST | AN8: 51.1 | AO8: ZS | AP8: 3.7 | AQ8: 32.4 | AS8: MSFT | AT8: 44.572437 | AU8: 10.123218
A9: 2 | B9: ='Watchlist Ratings'!B5 -> MSFT | C9: ='Watchlist Ratings'!S5 -> 8.75 | D9: ='Watchlist Ratings'!AC5 -> 7.7 | E9: ='Watchlist Ratings'!AM5 -> 7.57 | F9: ='Watchlist Ratings'!AN5 -> 7.86 | G9: ='Watchlist Ratings'!K5 -> 8 | H9: ='Watchlist Ratings'!L5 -> 3 | I9: ='Watchlist Ratings'!BC5 -> 0.21224118 | J9: ='Watchlist Ratings'!AW5 -> 72.014527 | O9: ='Watchlist Ratings'!B5 -> MSFT | P9: ='Watchlist Ratings'!AN5 -> 7.86 | Q9: ='Watchlist Ratings'!BM5 -> 0.11210182 | S9: ='Watchlist Ratings'!B5 -> MSFT | T9: ='Watchlist Ratings'!BC5 -> 0.21224118 | V9: ='Watchlist Ratings'!B5 -> MSFT | W9: ='Watchlist Ratings'!K5 -> 8 | X9: ='Watchlist Ratings'!L5 -> 3 | Y9: ='Watchlist Ratings'!B5 -> MSFT | Z9: ='Watchlist Ratings'!AW5 -> 72.014527 | AA9: ='Watchlist Ratings'!B5 -> MSFT | AB9: ='Watchlist Ratings'!BL5 -> -0.055257326 | AC9: ='Watchlist Ratings'!BM5 -> 0.11210182 | AE9: MNST | AF9: 59.375 | AH9: MNST | AI9: 59.4 | AJ9: COST | AK9: 8 | AL9: 1 | AM9: LOTB | AN9: 45.6 | AO9: ADYEN | AP9: 1.1 | AQ9: 28.4 | AS9: ADYEN | AT9: 28.571279 | AU9: 28.414483
A10: 3 | B10: ='Watchlist Ratings'!B6 -> ADYEN | C10: ='Watchlist Ratings'!S6 -> 7.81 | D10: ='Watchlist Ratings'!AC6 -> 7.3 | E10: ='Watchlist Ratings'!AM6 -> 8.29 | F10: ='Watchlist Ratings'!AN6 -> 7.8 | G10: ='Watchlist Ratings'!K6 -> 7 | H10: ='Watchlist Ratings'!L6 -> 2 | I10: ='Watchlist Ratings'!BC6 -> 0.358 | J10: ='Watchlist Ratings'!AW6 -> 24.388813 | O10: ='Watchlist Ratings'!B6 -> ADYEN | P10: ='Watchlist Ratings'!AN6 -> 7.8 | Q10: ='Watchlist Ratings'!BM6 -> 0.20520658 | S10: ='Watchlist Ratings'!B6 -> ADYEN | T10: ='Watchlist Ratings'!BC6 -> 0.358 | V10: ='Watchlist Ratings'!B6 -> ADYEN | W10: ='Watchlist Ratings'!K6 -> 7 | X10: ='Watchlist Ratings'!L6 -> 2 | Y10: ='Watchlist Ratings'!B6 -> ADYEN | Z10: ='Watchlist Ratings'!AW6 -> 24.388813 | AA10: ='Watchlist Ratings'!B6 -> ADYEN | AB10: ='Watchlist Ratings'!BL6 -> -0.079445419 | AC10: ='Watchlist Ratings'!BM6 -> 0.20520658 | AE10: VEEV | AF10: 54 | AH10: VEEV | AI10: 54 | AJ10: AMZN | AK10: 8 | AL10: 3 | AM10: MSFT | AN10: 44.8 | AO10: ABNB | AP10: 1.8 | AQ10: 25 | AS10: BN | AT10: 24.369254 | AU10: 23.486341
A11: 4 | B11: ='Watchlist Ratings'!B7 -> BN | C11: ='Watchlist Ratings'!S7 -> 8.44 | D11: ='Watchlist Ratings'!AC7 -> 8 | E11: ='Watchlist Ratings'!AM7 -> 7.71 | F11: ='Watchlist Ratings'!AN7 -> 7.97 | G11: ='Watchlist Ratings'!K7 -> 7 | H11: ='Watchlist Ratings'!L7 -> 3 | I11: ='Watchlist Ratings'!BC7 -> 0.13417132 | J11: ='Watchlist Ratings'!AW7 -> 15.963148 | O11: ='Watchlist Ratings'!B7 -> BN | P11: ='Watchlist Ratings'!AN7 -> 7.97 | Q11: ='Watchlist Ratings'!BM7 -> 0.24983313 | S11: ='Watchlist Ratings'!B7 -> BN | T11: ='Watchlist Ratings'!BC7 -> 0.13417132 | V11: ='Watchlist Ratings'!B7 -> BN | W11: ='Watchlist Ratings'!K7 -> 7 | X11: ='Watchlist Ratings'!L7 -> 3 | Y11: ='Watchlist Ratings'!B7 -> BN | Z11: ='Watchlist Ratings'!AW7 -> 15.963148 | AA11: ='Watchlist Ratings'!B7 -> BN | AB11: ='Watchlist Ratings'!BL7 -> 0.042057947 | AC11: ='Watchlist Ratings'!BM7 -> 0.24983313 | AE11: TSM | AF11: 41.666667 | AH11: TSM | AI11: 41.7 | AJ11: FICO | AK11: 8 | AL11: 2 | AM11: HLMA | AN11: 43.6 | AO11: BN | AP11: 0.6 | AQ11: 23.3 | AS11: COST | AT11: 51.179748 | AU11: 0.80673235
A12: 5 | B12: ='Watchlist Ratings'!B8 -> COST | C12: ='Watchlist Ratings'!S8 -> 7.81 | D12: ='Watchlist Ratings'!AC8 -> 8 | E12: ='Watchlist Ratings'!AM8 -> 8.43 | F12: ='Watchlist Ratings'!AN8 -> 8.13 | G12: ='Watchlist Ratings'!K8 -> 8 | H12: ='Watchlist Ratings'!L8 -> 1 | I12: ='Watchlist Ratings'!BC8 -> 0.19860061 | J12: ='Watchlist Ratings'!AW8 -> 50.198485 | O12: ='Watchlist Ratings'!B8 -> COST | P12: ='Watchlist Ratings'!AN8 -> 8.13 | Q12: ='Watchlist Ratings'!BM8 -> -0.0037574755 | S12: ='Watchlist Ratings'!B8 -> COST | T12: ='Watchlist Ratings'!BC8 -> 0.19860061 | V12: ='Watchlist Ratings'!B8 -> COST | W12: ='Watchlist Ratings'!K8 -> 8 | X12: ='Watchlist Ratings'!L8 -> 1 | Y12: ='Watchlist Ratings'!B8 -> COST | Z12: ='Watchlist Ratings'!AW8 -> 50.198485 | AA12: ='Watchlist Ratings'!B8 -> COST | AB12: ='Watchlist Ratings'!BL8 -> -0.12471291 | AC12: ='Watchlist Ratings'!BM8 -> -0.0037574755 | AE12: RAA | AF12: 38.333333 | AH12: RAA | AI12: 38.3 | AJ12: ADYEN | AK12: 7 | AL12: 3 | AM12: MNST | AN12: 40.3 | AO12: DSGX | AP12: -0.1 | AQ12: 20.8 | AS12: DSGX | AT12: 25.703927 | AU12: 20.950673
A13: 6 | B13: ='Watchlist Ratings'!B9 -> DSGX | C13: ='Watchlist Ratings'!S9 -> 7.19 | D13: ='Watchlist Ratings'!AC9 -> 7.5 | E13: ='Watchlist Ratings'!AM9 -> 8.71 | F13: ='Watchlist Ratings'!AN9 -> 7.92 | G13: ='Watchlist Ratings'!K9 -> 7 | H13: ='Watchlist Ratings'!L9 -> 2 | I13: ='Watchlist Ratings'!BC9 -> 0.10620525 | J13: ='Watchlist Ratings'!AW9 -> 26.91351 | L13: Tier | M13: Count | O13: ='Watchlist Ratings'!B9 -> DSGX | P13: ='Watchlist Ratings'!AN9 -> 7.92 | Q13: ='Watchlist Ratings'!BM9 -> 0.1578811 | S13: ='Watchlist Ratings'!B9 -> DSGX | T13: ='Watchlist Ratings'!BC9 -> 0.10620525 | V13: ='Watchlist Ratings'!B9 -> DSGX | W13: ='Watchlist Ratings'!K9 -> 7 | X13: ='Watchlist Ratings'!L9 -> 2 | Y13: ='Watchlist Ratings'!B9 -> DSGX | Z13: ='Watchlist Ratings'!AW9 -> 26.91351 | AA13: ='Watchlist Ratings'!B9 -> DSGX | AB13: ='Watchlist Ratings'!BL9 -> -0.072863983 | AC13: ='Watchlist Ratings'!BM9 -> 0.1578811 | AE13: ABNB | AF13: 37.5 | AH13: ABNB | AI13: 37.5 | AJ13: BN | AK13: 7 | AL13: 3 | AM13: LIFCO B | AN13: 38.9 | AO13: EVD | AP13: 4.7 | AQ13: 32.9 | AS13: RAA | AT13: 29.589673 | AU13: 13.487713
A14: 7 | B14: ='Watchlist Ratings'!B10 -> RAA | C14: ='Watchlist Ratings'!S10 -> 7.5 | D14: ='Watchlist Ratings'!AC10 -> 7.4 | E14: ='Watchlist Ratings'!AM10 -> 8.29 | F14: ='Watchlist Ratings'!AN10 -> 7.78 | G14: ='Watchlist Ratings'!K10 -> 7 | H14: ='Watchlist Ratings'!L10 -> 2 | I14: ='Watchlist Ratings'!BC10 -> 0.38333333 | J14: ='Watchlist Ratings'!AW10 -> 28.467622 | L14: Tier 1 (+8) | M14: =COUNTIF('Watchlist Ratings'!AN4:AN71,">=8") -> 3 | O14: ='Watchlist Ratings'!B10 -> RAA | P14: ='Watchlist Ratings'!AN10 -> 7.78 | Q14: ='Watchlist Ratings'!BM10 -> 0.11451 | S14: ='Watchlist Ratings'!B10 -> RAA | T14: ='Watchlist Ratings'!BC10 -> 0.38333333 | V14: ='Watchlist Ratings'!B10 -> RAA | W14: ='Watchlist Ratings'!K10 -> 7 | X14: ='Watchlist Ratings'!L10 -> 2 | Y14: ='Watchlist Ratings'!B10 -> RAA | Z14: ='Watchlist Ratings'!AW10 -> 28.467622 | AA14: ='Watchlist Ratings'!B10 -> RAA | AB14: ='Watchlist Ratings'!BL10 -> -0.072872488 | AC14: ='Watchlist Ratings'!BM10 -> 0.11451 | AE14: MIPS | AF14: 37.142857 | AH14: MIPS | AI14: 37.1 | AJ14: DSGX | AK14: 7 | AL14: 2 | AM14: FICO | AN14: 38.5 | AO14: ITX | AP14: -4.2 | AQ14: 13.7 | AS14: ZS | AT14: 26.244955 | AU14: 32.575211
A15: 8 | B15: ='Watchlist Ratings'!B11 -> ZS | C15: ='Watchlist Ratings'!S11 -> 7.5 | D15: ='Watchlist Ratings'!AC11 -> 7 | E15: ='Watchlist Ratings'!AM11 -> 7.29 | F15: ='Watchlist Ratings'!AN11 -> 7.22 | G15: ='Watchlist Ratings'!K11 -> 6 | H15: ='Watchlist Ratings'!L11 -> 2 | I15: ='Watchlist Ratings'!BC11 -> -0.028997172 | J15: ='Watchlist Ratings'!AW11 -> -772.14958 | L15: ⭐ Tier 2 (7-8) | M15: =COUNTIFS('Watchlist Ratings'!AN4:AN71,">=7",'Watchlist Ratings'!AN4:AN71,"<8") -> 19 | O15: ='Watchlist Ratings'!B11 -> ZS | P15: ='Watchlist Ratings'!AN11 -> 7.22 | Q15: ='Watchlist Ratings'!BM11 -> -0.20245465 | S15: ='Watchlist Ratings'!B11 -> ZS | T15: ='Watchlist Ratings'!BC11 -> -0.028997172 | V15: ='Watchlist Ratings'!B11 -> ZS | W15: ='Watchlist Ratings'!K11 -> 6 | X15: ='Watchlist Ratings'!L11 -> 2 | Y15: ='Watchlist Ratings'!B11 -> ZS | Z15: ='Watchlist Ratings'!AW11 -> -772.14958 | AA15: ='Watchlist Ratings'!B11 -> ZS | AB15: ='Watchlist Ratings'!BL11 -> -0.34225635 | AC15: ='Watchlist Ratings'!BM11 -> -0.20245465 | AE15: ITX | AF15: 36.111111 | AH15: ITX | AI15: 36.1 | AJ15: RAA | AK15: 7 | AL15: 2 | AM15: SU | AN15: 37.7 | AO15: RAA | AP15: -8 | AQ15: 13.5 | AS15: NTO | AT15: 27.905545 | AU15: 8.8031472
A16: 9 | B16: ='Watchlist Ratings'!B12 -> NTO | C16: ='Watchlist Ratings'!S12 -> 7.5 | D16: ='Watchlist Ratings'!AC12 -> 7.5 | E16: ='Watchlist Ratings'!AM12 -> 8.14 | F16: ='Watchlist Ratings'!AN12 -> 7.76 | G16: ='Watchlist Ratings'!K12 -> 7 | H16: ='Watchlist Ratings'!L12 -> 3 | I16: ='Watchlist Ratings'!BC12 -> 0.203375 | J16: ='Watchlist Ratings'!AW12 -> 34.302663 | L16: Tier 3 (6-7) | M16: =COUNTIFS('Watchlist Ratings'!AN4:AN71,">=6",'Watchlist Ratings'!AN4:AN71,"<7") -> 15 | O16: ='Watchlist Ratings'!B12 -> NTO | P16: ='Watchlist Ratings'!AN12 -> 7.76 | Q16: ='Watchlist Ratings'!BM12 -> 0.03209665 | S16: ='Watchlist Ratings'!B12 -> NTO | T16: ='Watchlist Ratings'!BC12 -> 0.203375 | V16: ='Watchlist Ratings'!B12 -> NTO | W16: ='Watchlist Ratings'!K12 -> 7 | X16: ='Watchlist Ratings'!L12 -> 3 | Y16: ='Watchlist Ratings'!B12 -> NTO | Z16: ='Watchlist Ratings'!AW12 -> 34.302663 | AA16: ='Watchlist Ratings'!B12 -> NTO | AB16: ='Watchlist Ratings'!BL12 -> -0.11654611 | AC16: ='Watchlist Ratings'!BM12 -> 0.03209665 | AE16: MSFT | AF16: 32.142857 | AH16: MSFT | AI16: 32.1 | AJ16: NTO | AK16: 7 | AL16: 3 | AM16: RAA | AN16: 29.6 | AO16: FICO | AP16: -7.9 | AQ16: 12.3 | AS16: AMZN | AT16: 52.22295 | AU16: 4.7817206
A17: 10 | B17: ='Watchlist Ratings'!B13 -> AMZN | C17: ='Watchlist Ratings'!S13 -> 9.38 | D17: ='Watchlist Ratings'!AC13 -> 7.7 | E17: ='Watchlist Ratings'!AM13 -> 7.14 | F17: ='Watchlist Ratings'!AN13 -> 7.81 | G17: ='Watchlist Ratings'!K13 -> 8 | H17: ='Watchlist Ratings'!L13 -> 3 | I17: ='Watchlist Ratings'!BC13 -> 0.18333333 | J17: ='Watchlist Ratings'!AW13 -> 49.409643 | L17: ⚠️ Below 6 | M17: =COUNTIF('Watchlist Ratings'!AN4:AN71,"<6") -> 31 | O17: ='Watchlist Ratings'!B13 -> AMZN | P17: ='Watchlist Ratings'!AN13 -> 7.81 | Q17: ='Watchlist Ratings'!BM13 -> 0.050624228 | S17: ='Watchlist Ratings'!B13 -> AMZN | T17: ='Watchlist Ratings'!BC13 -> 0.18333333 | V17: ='Watchlist Ratings'!B13 -> AMZN | W17: ='Watchlist Ratings'!K13 -> 8 | X17: ='Watchlist Ratings'!L13 -> 3 | Y17: ='Watchlist Ratings'!B13 -> AMZN | Z17: ='Watchlist Ratings'!AW13 -> 49.409643 | AA17: ='Watchlist Ratings'!B13 -> AMZN | AB17: ='Watchlist Ratings'!BL13 -> -0.11409134 | AC17: ='Watchlist Ratings'!BM13 -> 0.050624228 | AS17: SU | AT17: 37.736708 | AU17: 5.374427
A18: 11 | B18: ='Watchlist Ratings'!B14 -> SU | C18: ='Watchlist Ratings'!S14 -> 8.13 | D18: ='Watchlist Ratings'!AC14 -> 7.7 | E18: ='Watchlist Ratings'!AM14 -> 7.57 | F18: ='Watchlist Ratings'!AN14 -> 7.73 | G18: ='Watchlist Ratings'!K14 -> 7 | H18: ='Watchlist Ratings'!L14 -> 3 | I18: ='Watchlist Ratings'!BC14 -> 0.13238864 | J18: ='Watchlist Ratings'!AW14 -> 35.406648 | O18: ='Watchlist Ratings'!B14 -> SU | P18: ='Watchlist Ratings'!AN14 -> 7.73 | Q18: ='Watchlist Ratings'!BM14 -> 0.059401232 | V18: ='Watchlist Ratings'!B14 -> SU | W18: ='Watchlist Ratings'!K14 -> 7 | X18: ='Watchlist Ratings'!L14 -> 3 | Y18: ='Watchlist Ratings'!B14 -> SU | Z18: ='Watchlist Ratings'!AW14 -> 35.406648 | AA18: ='Watchlist Ratings'!B14 -> SU | AB18: ='Watchlist Ratings'!BL14 -> -0.10026238 | AC18: ='Watchlist Ratings'!BM14 -> 0.059401232 | AS18: ITX | AT18: 24.61203 | AU18: 13.683807
A19: 12 | B19: ='Watchlist Ratings'!B15 -> ITX | C19: ='Watchlist Ratings'!S15 -> 6.88 | D19: ='Watchlist Ratings'!AC15 -> 7.7 | E19: ='Watchlist Ratings'!AM15 -> 8.29 | F19: ='Watchlist Ratings'!AN15 -> 7.77 | G19: ='Watchlist Ratings'!K15 -> 6.5 | H19: ='Watchlist Ratings'!L15 -> 1.5 | I19: ='Watchlist Ratings'!BC15 -> 0.2597927 | J19: ='Watchlist Ratings'!AW15 -> 28.44845 | O19: ='Watchlist Ratings'!B15 -> ITX | P19: ='Watchlist Ratings'!AN15 -> 7.77 | Q19: ='Watchlist Ratings'!BM15 -> 0.054598831 | V19: ='Watchlist Ratings'!B15 -> ITX | W19: ='Watchlist Ratings'!K15 -> 6.5 | X19: ='Watchlist Ratings'!L15 -> 1.5 | Y19: ='Watchlist Ratings'!B15 -> ITX | Z19: ='Watchlist Ratings'!AW15 -> 28.44845 | AA19: ='Watchlist Ratings'!B15 -> ITX | AB19: ='Watchlist Ratings'!BL15 -> -0.064601836 | AC19: ='Watchlist Ratings'!BM15 -> 0.054598831 | AS19: LOTB | AT19: 45.617441 | AU19: 3.6173393
A20: 13 | B20: ='Watchlist Ratings'!B16 -> LOTB | C20: ='Watchlist Ratings'!S16 -> 7.5 | D20: ='Watchlist Ratings'!AC16 -> 8 | E20: ='Watchlist Ratings'!AM16 -> 7.86 | F20: ='Watchlist Ratings'!AN16 -> 7.84 | G20: ='Watchlist Ratings'!K16 -> 7 | H20: ='Watchlist Ratings'!L16 -> 3 | I20: ='Watchlist Ratings'!BC16 -> 0.14514897 | J20: ='Watchlist Ratings'!AW16 -> 118.31641 | O20: ='Watchlist Ratings'!B16 -> LOTB | P20: ='Watchlist Ratings'!AN16 -> 7.84 | Q20: ='Watchlist Ratings'!BM16 -> -0.17507049 | V20: ='Watchlist Ratings'!B16 -> LOTB | W20: ='Watchlist Ratings'!K16 -> 7 | X20: ='Watchlist Ratings'!L16 -> 3 | Y20: ='Watchlist Ratings'!B16 -> LOTB | Z20: ='Watchlist Ratings'!AW16 -> 118.31641 | AA20: ='Watchlist Ratings'!B16 -> LOTB | AB20: ='Watchlist Ratings'!BL16 -> -0.3004252 | AC20: ='Watchlist Ratings'!BM16 -> -0.17507049 | AS20: HLMA | AT20: 43.630937 | AU20: 4.348286
A21: 14 | B21: ='Watchlist Ratings'!B17 -> HLMA | C21: ='Watchlist Ratings'!S17 -> 8.13 | D21: ='Watchlist Ratings'!AC17 -> 7.1 | E21: ='Watchlist Ratings'!AM17 -> 8.29 | F21: ='Watchlist Ratings'!AN17 -> 7.78 | G21: ='Watchlist Ratings'!K17 -> 6 | H21: ='Watchlist Ratings'!L17 -> 3 | I21: ='Watchlist Ratings'!BC17 -> 0.1262927 | J21: ='Watchlist Ratings'!AW17 -> 34.973236 | O21: ='Watchlist Ratings'!B17 -> HLMA | P21: ='Watchlist Ratings'!AN17 -> 7.78 | Q21: ='Watchlist Ratings'!BM17 -> 0.084928539 | V21: ='Watchlist Ratings'!B17 -> HLMA | W21: ='Watchlist Ratings'!K17 -> 6 | X21: ='Watchlist Ratings'!L17 -> 3 | Y21: ='Watchlist Ratings'!B17 -> HLMA | Z21: ='Watchlist Ratings'!AW17 -> 34.973236 | AA21: ='Watchlist Ratings'!B17 -> HLMA | AB21: ='Watchlist Ratings'!BL17 -> -0.086403555 | AC21: ='Watchlist Ratings'!BM17 -> 0.084928539 | AS21: FICO | AT21: 38.120501 | AU21: 12.615576
A22: 15 | B22: ='Watchlist Ratings'!B18 -> FICO | C22: ='Watchlist Ratings'!S18 -> 6.88 | D22: ='Watchlist Ratings'!AC18 -> 6.4 | E22: ='Watchlist Ratings'!AM18 -> 8 | F22: ='Watchlist Ratings'!AN18 -> 7.14 | G22: ='Watchlist Ratings'!K18 -> 8 | H22: ='Watchlist Ratings'!L18 -> 2 | I22: ='Watchlist Ratings'!BC18 -> 0.43 | J22: ='Watchlist Ratings'!AW18 -> 28.169913 | O22: ='Watchlist Ratings'!B18 -> FICO | P22: ='Watchlist Ratings'!AN18 -> 7.14 | Q22: ='Watchlist Ratings'!BM18 -> 0.17751075 | V22: ='Watchlist Ratings'!B18 -> FICO | W22: ='Watchlist Ratings'!K18 -> 8 | X22: ='Watchlist Ratings'!L18 -> 2 | Y22: ='Watchlist Ratings'!B18 -> FICO | Z22: ='Watchlist Ratings'!AW18 -> 28.169913 | AA22: ='Watchlist Ratings'!B18 -> FICO | AB22: ='Watchlist Ratings'!BL18 -> -0.14237484 | AC22: ='Watchlist Ratings'!BM18 -> 0.17751075
O23: ='Watchlist Ratings'!B19 -> LIFCO B | P23: ='Watchlist Ratings'!AN19 -> 7.9 | Q23: ='Watchlist Ratings'!BM19 -> 0.083253464
A24: 📈 VISUALIZACIÓN DE DATOS — Gráficos Interactivos
O25: ='Watchlist Ratings'!B21 -> MNST | P25: ='Watchlist Ratings'!AN21 -> 7.58 | Q25: ='Watchlist Ratings'!BM21 -> 0.0023750284
O26: ='Watchlist Ratings'!B22 -> ABNB | P26: ='Watchlist Ratings'!AN22 -> 7.3 | Q26: ='Watchlist Ratings'!BM22 -> 0.094100927
O27: ='Watchlist Ratings'!B23 -> DNP | P27: ='Watchlist Ratings'!AN23 -> 7.48 | Q27: ='Watchlist Ratings'!BM23 -> -0.066923039
A62: 📈 ANÁLISIS DE ASIMETRÍA — Rango de Valoración | J62: 🛡️ ANTIFRAGILIDAD — Durabilidad & Riesgo
A63: Ticker | B63: Precio | C63: FVE Min | D63: FVE Max | E63: IRR Bear | F63: IRR Bull | G63: Spread | H63: Señal | J63: Ticker | K63: R3 Score | L63: Cap.Intens. | M63: Cap.Alloc. | N63: Term.Risk | O63: MOAT | P63: Option. | Q63: Rating
A64: ='Watchlist Ratings'!B4 -> VEEV | B64: ='Watchlist Ratings'!G4 -> 316.55 | C64: ='Watchlist Ratings'!BJ4 -> 163.55689 | D64: ='Watchlist Ratings'!BK4 -> 479.70154 | E64: ='Watchlist Ratings'!BL4 -> -0.12371514 | F64: ='Watchlist Ratings'!BM4 -> 0.086690219 | G64: =F64-E64 -> 0.21040536 | H64: =IF(E64>0,"🟢 BUY",IF(E64>-0.05,"🟡 HOLD","🔴 PASS")) -> 🔴 PASS | J64: ='Watchlist Ratings'!B4 -> VEEV | K64: ='Watchlist Ratings'!AM4 -> 8.57 | L64: ='Watchlist Ratings'!AF4 -> 10 | M64: ='Watchlist Ratings'!AG4 -> 14 | N64: ='Watchlist Ratings'!AK4 -> -5 | O64: ='Watchlist Ratings'!K4 -> 8 | P64: ='Watchlist Ratings'!L4 -> 2 | Q64: =IF(K64>=8,"🟢 ALTO",IF(K64>=7,"🟡 MEDIO","🔴 BAJO")) -> 🟢 ALTO
A65: ='Watchlist Ratings'!B5 -> MSFT | B65: ='Watchlist Ratings'!G5 -> 534.27 | C65: ='Watchlist Ratings'!BJ5 -> 402.0948 | D65: ='Watchlist Ratings'!BK5 -> 908.83188 | E65: ='Watchlist Ratings'!BL5 -> -0.055257326 | F65: ='Watchlist Ratings'!BM5 -> 0.11210182 | G65: =F65-E65 -> 0.16735915 | H65: =IF(E65>0,"🟢 BUY",IF(E65>-0.05,"🟡 HOLD","🔴 PASS")) -> 🔴 PASS | J65: ='Watchlist Ratings'!B5 -> MSFT | K65: ='Watchlist Ratings'!AM5 -> 7.57 | L65: ='Watchlist Ratings'!AF5 -> 4 | M65: ='Watchlist Ratings'!AG5 -> 14 | N65: ='Watchlist Ratings'!AK5 -> -6 | O65: ='Watchlist Ratings'!K5 -> 8 | P65: ='Watchlist Ratings'!L5 -> 3 | Q65: =IF(K65>=8,"🟢 ALTO",IF(K65>=7,"🟡 MEDIO","🔴 BAJO")) -> 🟡 MEDIO
A66: ='Watchlist Ratings'!B6 -> ADYEN | B66: ='Watchlist Ratings'!G6 -> 930.4 | C66: ='Watchlist Ratings'!BJ6 -> 615.05991 | D66: ='Watchlist Ratings'!BK6 -> 2365.7954 | E66: ='Watchlist Ratings'!BL6 -> -0.079445419 | F66: ='Watchlist Ratings'!BM6 -> 0.20520658 | G66: =F66-E66 -> 0.284652 | H66: =IF(E66>0,"🟢 BUY",IF(E66>-0.05,"🟡 HOLD","🔴 PASS")) -> 🔴 PASS | J66: ='Watchlist Ratings'!B6 -> ADYEN | K66: ='Watchlist Ratings'!AM6 -> 8.29 | L66: ='Watchlist Ratings'!AF6 -> 9 | M66: ='Watchlist Ratings'!AG6 -> 14 | N66: ='Watchlist Ratings'!AK6 -> -6 | O66: ='Watchlist Ratings'!K6 -> 7 | P66: ='Watchlist Ratings'!L6 -> 2 | Q66: =IF(K66>=8,"🟢 ALTO",IF(K66>=7,"🟡 MEDIO","🔴 BAJO")) -> 🟢 ALTO
A67: ='Watchlist Ratings'!B7 -> BN | B67: ='Watchlist Ratings'!G7 -> 36.395 | C67: ='Watchlist Ratings'!BJ7 -> 44.719926 | D67: ='Watchlist Ratings'!BK7 -> 110.99461 | E67: ='Watchlist Ratings'!BL7 -> 0.042057947 | F67: ='Watchlist Ratings'!BM7 -> 0.24983313 | G67: =F67-E67 -> 0.20777518 | H67: =IF(E67>0,"🟢 BUY",IF(E67>-0.05,"🟡 HOLD","🔴 PASS")) -> 🟢 BUY | J67: ='Watchlist Ratings'!B7 -> BN | K67: ='Watchlist Ratings'!AM7 -> 7.71 | L67: ='Watchlist Ratings'!AF7 -> 5 | M67: ='Watchlist Ratings'!AG7 -> 15 | N67: ='Watchlist Ratings'!AK7 -> -5 | O67: ='Watchlist Ratings'!K7 -> 7 | P67: ='Watchlist Ratings'!L7 -> 3 | Q67: =IF(K67>=8,"🟢 ALTO",IF(K67>=7,"🟡 MEDIO","🔴 BAJO")) -> 🟡 MEDIO
A68: ='Watchlist Ratings'!B8 -> COST | B68: ='Watchlist Ratings'!G8 -> 994.68 | C68: ='Watchlist Ratings'!BJ8 -> 511.01777 | D68: ='Watchlist Ratings'!BK8 -> 976.13248 | E68: ='Watchlist Ratings'!BL8 -> -0.12471291 | F68: ='Watchlist Ratings'!BM8 -> -0.0037574755 | G68: =F68-E68 -> 0.12095543 | H68: =IF(E68>0,"🟢 BUY",IF(E68>-0.05,"🟡 HOLD","🔴 PASS")) -> 🔴 PASS | J68: ='Watchlist Ratings'!B8 -> COST | K68: ='Watchlist Ratings'!AM8 -> 8.43 | L68: ='Watchlist Ratings'!AF8 -> 6 | M68: ='Watchlist Ratings'!AG8 -> 13 | N68: ='Watchlist Ratings'!AK8 -> -3 | O68: ='Watchlist Ratings'!K8 -> 8 | P68: ='Watchlist Ratings'!L8 -> 1 | Q68: =IF(K68>=8,"🟢 ALTO",IF(K68>=7,"🟡 MEDIO","🔴 BAJO")) -> 🟢 ALTO
A69: ='Watchlist Ratings'!B9 -> DSGX | B69: ='Watchlist Ratings'!G9 -> 87.415 | C69: ='Watchlist Ratings'!BJ9 -> 59.882955 | D69: ='Watchlist Ratings'!BK9 -> 181.93061 | E69: ='Watchlist Ratings'!BL9 -> -0.072863983 | F69: ='Watchlist Ratings'!BM9 -> 0.1578811 | G69: =F69-E69 -> 0.23074508 | H69: =IF(E69>0,"🟢 BUY",IF(E69>-0.05,"🟡 HOLD","🔴 PASS")) -> 🔴 PASS | J69: ='Watchlist Ratings'!B9 -> DSGX | K69: ='Watchlist Ratings'!AM9 -> 8.71 | L69: ='Watchlist Ratings'!AF9 -> 10 | M69: ='Watchlist Ratings'!AG9 -> 13 | N69: ='Watchlist Ratings'!AK9 -> -3 | O69: ='Watchlist Ratings'!K9 -> 7 | P69: ='Watchlist Ratings'!L9 -> 2 | Q69: =IF(K69>=8,"🟢 ALTO",IF(K69>=7,"🟡 MEDIO","🔴 BAJO")) -> 🟢 ALTO
A70: ='Watchlist Ratings'!B10 -> RAA | B70: ='Watchlist Ratings'!G10 -> 612.5 | C70: ='Watchlist Ratings'!BJ10 -> 419.56904 | D70: ='Watchlist Ratings'!BK10 -> 1053.2366 | E70: ='Watchlist Ratings'!BL10 -> -0.072872488 | F70: ='Watchlist Ratings'!BM10 -> 0.11451 | G70: =F70-E70 -> 0.18738249 | H70: =IF(E70>0,"🟢 BUY",IF(E70>-0.05,"🟡 HOLD","🔴 PASS")) -> 🔴 PASS | J70: ='Watchlist Ratings'!B10 -> RAA | K70: ='Watchlist Ratings'!AM10 -> 8.29 | L70: ='Watchlist Ratings'!AF10 -> 8 | M70: ='Watchlist Ratings'!AG10 -> 13 | N70: ='Watchlist Ratings'!AK10 -> -3 | O70: ='Watchlist Ratings'!K10 -> 7 | P70: ='Watchlist Ratings'!L10 -> 2 | Q70: =IF(K70>=8,"🟢 ALTO",IF(K70>=7,"🟡 MEDIO","🔴 BAJO")) -> 🟢 ALTO
A71: ='Watchlist Ratings'!B11 -> ZS | B71: ='Watchlist Ratings'!G11 -> 213.11 | C71: ='Watchlist Ratings'!BJ11 -> 26.235368 | D71: ='Watchlist Ratings'!BK11 -> 68.767107 | E71: ='Watchlist Ratings'!BL11 -> -0.34225635 | F71: ='Watchlist Ratings'!BM11 -> -0.20245465 | G71: =F71-E71 -> 0.13980169 | H71: =IF(E71>0,"🟢 BUY",IF(E71>-0.05,"🟡 HOLD","🔴 PASS")) -> 🔴 PASS | J71: ='Watchlist Ratings'!B11 -> ZS | K71: ='Watchlist Ratings'!AM11 -> 7.29 | L71: ='Watchlist Ratings'!AF11 -> 9 | M71: ='Watchlist Ratings'!AG11 -> 11 | N71: ='Watchlist Ratings'!AK11 -> -5 | O71: ='Watchlist Ratings'!K11 -> 6 | P71: ='Watchlist Ratings'!L11 -> 2 | Q71: =IF(K71>=8,"🟢 ALTO",IF(K71>=7,"🟡 MEDIO","🔴 BAJO")) -> 🟡 MEDIO
A72: ='Watchlist Ratings'!B12 -> NTO | J72: ='Watchlist Ratings'!B12 -> NTO
A73: ='Watchlist Ratings'!B13 -> AMZN | B73: ='Watchlist Ratings'!G13 -> 262.278 | C73: ='Watchlist Ratings'!BJ13 -> 143.12207 | D73: ='Watchlist Ratings'!BK13 -> 335.73678 | E73: ='Watchlist Ratings'!BL13 -> -0.11409134 | F73: ='Watchlist Ratings'!BM13 -> 0.050624228 | G73: =F73-E73 -> 0.16471557 | H73: =IF(E73>0,"🟢 BUY",IF(E73>-0.05,"🟡 HOLD","🔴 PASS")) -> 🔴 PASS | J73: ='Watchlist Ratings'!B13 -> AMZN | K73: ='Watchlist Ratings'!AM13 -> 7.14 | L73: ='Watchlist Ratings'!AF13 -> 3 | M73: ='Watchlist Ratings'!AG13 -> 13 | N73: ='Watchlist Ratings'!AK13 -> -5 | O73: ='Watchlist Ratings'!K13 -> 8 | P73: ='Watchlist Ratings'!L13 -> 3 | Q73: =IF(K73>=8,"🟢 ALTO",IF(K73>=7,"🟡 MEDIO","🔴 BAJO")) -> 🟡 MEDIO
A74: VEEV | B74: =VLOOKUP(A74,'Watchlist Ratings'!$B$4:$BM$71,4,FALSE()) -> XNYS | C74: =VLOOKUP(A74,'Watchlist Ratings'!$B$4:$BM$71,59,FALSE()) -> 18 | D74: =VLOOKUP(A74,'Watchlist Ratings'!$B$4:$BM$71,60,FALSE()) -> 30 | E74: =VLOOKUP(A74,'Watchlist Ratings'!$B$4:$BM$71,61,FALSE()) -> 163.55689 | F74: =VLOOKUP(A74,'Watchlist Ratings'!$B$4:$BM$71,64,FALSE()) -> 0.086690219 | G74: =F74-E74 -> -163.4702 | H74: =IF(E74>0,"🟢 BUY",IF(E74>-0.05,"🟡 HOLD","🔴 PASS")) -> 🟢 BUY | J74: VEEV | K74: =VLOOKUP(J74,'Watchlist Ratings'!$B$4:$BM$71,36,FALSE()) -> -5 | L74: =VLOOKUP(J74,'Watchlist Ratings'!$B$4:$BM$71,29,FALSE()) -> 14 | M74: =VLOOKUP(J74,'Watchlist Ratings'!$B$4:$BM$71,30,FALSE()) -> 0 | N74: =VLOOKUP(J74,'Watchlist Ratings'!$B$4:$BM$71,34,FALSE()) -> 8 | O74: =VLOOKUP(J74,'Watchlist Ratings'!$B$4:$BM$71,8,FALSE()) -> 51252.231 | P74: =VLOOKUP(J74,'Watchlist Ratings'!$B$4:$BM$71,9,FALSE()) -> 1.5 | Q74: =IF(K74>=8.5,"🟢 ALTO",IF(K74>=7.5,"🟡 MEDIO","🔴 BAJO")) -> 🔴 BAJO
A75: MSFT | B75: =VLOOKUP(A75,'Watchlist Ratings'!$B$4:$BM$71,4,FALSE()) -> XNAS | C75: =VLOOKUP(A75,'Watchlist Ratings'!$B$4:$BM$71,59,FALSE()) -> 20 | D75: =VLOOKUP(A75,'Watchlist Ratings'!$B$4:$BM$71,60,FALSE()) -> 30 | E75: =VLOOKUP(A75,'Watchlist Ratings'!$B$4:$BM$71,61,FALSE()) -> 402.0948 | F75: =VLOOKUP(A75,'Watchlist Ratings'!$B$4:$BM$71,64,FALSE()) -> 0.11210182 | G75: =F75-E75 -> -401.98269 | H75: =IF(E75>0,"🟢 BUY",IF(E75>-0.05,"🟡 HOLD","🔴 PASS")) -> 🟢 BUY | J75: MSFT | K75: =VLOOKUP(J75,'Watchlist Ratings'!$B$4:$BM$71,36,FALSE()) -> -6 | L75: =VLOOKUP(J75,'Watchlist Ratings'!$B$4:$BM$71,29,FALSE()) -> 14 | M75: =VLOOKUP(J75,'Watchlist Ratings'!$B$4:$BM$71,30,FALSE()) -> 0 | N75: =VLOOKUP(J75,'Watchlist Ratings'!$B$4:$BM$71,34,FALSE()) -> 9 | O75: =VLOOKUP(J75,'Watchlist Ratings'!$B$4:$BM$71,8,FALSE()) -> 3967245.9 | P75: =VLOOKUP(J75,'Watchlist Ratings'!$B$4:$BM$71,9,FALSE()) -> 1 | Q75: =IF(K75>=8.5,"🟢 ALTO",IF(K75>=7.5,"🟡 MEDIO","🔴 BAJO")) -> 🔴 BAJO
A76: 📋 RESUMEN EJECUTIVO — Los Mejores en Cada Categoría
A77: BN | B77: =VLOOKUP(A77,'Watchlist Ratings'!$B$4:$BM$71,4,FALSE()) -> XNYS | C77: =VLOOKUP(A77,'Watchlist Ratings'!$B$4:$BM$71,59,FALSE()) -> 17.5 | D77: =VLOOKUP(A77,'Watchlist Ratings'!$B$4:$BM$71,60,FALSE()) -> 25 | E77: =VLOOKUP(A77,'Watchlist Ratings'!$B$4:$BM$71,61,FALSE()) -> 44.719926 | F77: =VLOOKUP(A77,'Watchlist Ratings'!$B$4:$BM$71,64,FALSE()) -> 0.24983313 | G77: =F77-E77 -> -44.470093 | H77: =IF(E77>0,"🟢 BUY",IF(E77>-0.05,"🟡 HOLD","🔴 PASS")) -> 🟢 BUY | J77: BN | K77: =VLOOKUP(J77,'Watchlist Ratings'!$B$4:$BM$71,36,FALSE()) -> -5 | L77: =VLOOKUP(J77,'Watchlist Ratings'!$B$4:$BM$71,29,FALSE()) -> 14 | M77: =VLOOKUP(J77,'Watchlist Ratings'!$B$4:$BM$71,30,FALSE()) -> -1 | N77: =VLOOKUP(J77,'Watchlist Ratings'!$B$4:$BM$71,34,FALSE()) -> 10 | O77: =VLOOKUP(J77,'Watchlist Ratings'!$B$4:$BM$71,8,FALSE()) -> 89240.94 | P77: =VLOOKUP(J77,'Watchlist Ratings'!$B$4:$BM$71,9,FALSE()) -> 1 | Q77: =IF(K77>=8.5,"🟢 ALTO",IF(K77>=7.5,"🟡 MEDIO","🔴 BAJO")) -> 🔴 BAJO
A78: 🏆 MEJOR CALIDAD | C78: 📈 MEJOR IRR BULL | E78: 💰 MAYOR ROIC | G78: 🏰 MEJOR MOAT | I78: 🎯 MÁS OPCIONALIDAD | K78: 🛡️ MÁS ANTIFRAGIL | M78: 💵 MENOR MÚLTIPLO | O78: ⚠️ MAYOR SPREAD | Q78: =IF(K78>=8.5,"🟢 ALTO",IF(K78>=7.5,"🟡 MEDIO","🔴 BAJO")) -> 🟢 ALTO
A79: =INDEX('Watchlist Ratings'!B:B,MATCH(MAX('Watchlist Ratings'!AN:AN),'Watchlist Ratings'!AN:AN,0)) -> CSU | C79: =INDEX('Watchlist Ratings'!B:B,MATCH(MAX('Watchlist Ratings'!BM:BM),'Watchlist Ratings'!BM:BM,0)) -> BFIT | E79: =INDEX('Watchlist Ratings'!B:B,MATCH(MAX('Watchlist Ratings'!BC:BC),'Watchlist Ratings'!BC:BC,0)) -> NVDA | G79: =INDEX('Watchlist Ratings'!B:B,MATCH(MAX('Watchlist Ratings'!K:K),'Watchlist Ratings'!K:K,0)) -> VEEV | I79: =INDEX('Watchlist Ratings'!B:B,MATCH(MAX('Watchlist Ratings'!L:L),'Watchlist Ratings'!L:L,0)) -> MSFT | K79: =INDEX('Watchlist Ratings'!B:B,MATCH(MAX('Watchlist Ratings'!AM:AM),'Watchlist Ratings'!AM:AM,0)) -> DSGX | M79: {=INDEX('Watchlist Ratings'!B:B,MATCH(MIN('Watchlist Ratings'!AW4:AW64),'Watchlist Ratings'!AW4:AW64,0)+3)} -> ZS | O79: {=INDEX('Watchlist Ratings'!B:B,MATCH(MAX('Watchlist Ratings'!BM4:BM64-'Watchlist Ratings'!BL4:BL64),'Watchlist Ratings'!BM4:BM64-'Watchlist Ratings'!BL4:BL64,0)+3)} -> OTLY | Q79: =IF(K79>=8.5,"🟢 ALTO",IF(K79>=7.5,"🟡 MEDIO","🔴 BAJO")) -> 🟢 ALTO
A80: =MAX('Watchlist Ratings'!AN:AN) -> 8.45 | C80: =MAX('Watchlist Ratings'!BM:BM) -> 0.46189106 | E80: =MAX('Watchlist Ratings'!BC:BC) -> 0.76982235 | G80: =MAX('Watchlist Ratings'!K:K)&"/8" -> 8/8 | I80: =MAX('Watchlist Ratings'!L:L)&"/3" -> 3/3 | K80: =MAX('Watchlist Ratings'!AM:AM) -> 8.71 | M80: =MIN('Watchlist Ratings'!AW4:AW64)&"x" -> -772.149581194379x | O80: {=TEXT(MAX('Watchlist Ratings'!BM4:BM64-'Watchlist Ratings'!BL4:BL64),"0.0%")} -> 122.4% | Q80: =IF(K80>=8.5,"🟢 ALTO",IF(K80>=7.5,"🟡 MEDIO","🔴 BAJO")) -> 🟢 ALTO
A81: ZS | B81: =VLOOKUP(A81,'Watchlist Ratings'!$B$4:$BM$71,4,FALSE()) -> XNAS | C81: =VLOOKUP(A81,'Watchlist Ratings'!$B$4:$BM$71,59,FALSE()) -> 20 | D81: =VLOOKUP(A81,'Watchlist Ratings'!$B$4:$BM$71,60,FALSE()) -> 30 | E81: =VLOOKUP(A81,'Watchlist Ratings'!$B$4:$BM$71,61,FALSE()) -> 26.235368 | F81: =VLOOKUP(A81,'Watchlist Ratings'!$B$4:$BM$71,64,FALSE()) -> -0.20245465 | G81: =F81-E81 -> -26.437822 | H81: =IF(E81>0,"🟢 BUY",IF(E81>-0.05,"🟡 HOLD","🔴 PASS")) -> 🟢 BUY | J81: ZS | K81: =VLOOKUP(J81,'Watchlist Ratings'!$B$4:$BM$71,36,FALSE()) -> -5 | L81: =VLOOKUP(J81,'Watchlist Ratings'!$B$4:$BM$71,29,FALSE()) -> 13 | M81: =VLOOKUP(J81,'Watchlist Ratings'!$B$4:$BM$71,30,FALSE()) -> -2 | N81: =VLOOKUP(J81,'Watchlist Ratings'!$B$4:$BM$71,34,FALSE()) -> 9 | O81: =VLOOKUP(J81,'Watchlist Ratings'!$B$4:$BM$71,8,FALSE()) -> 34748.587 | P81: =VLOOKUP(J81,'Watchlist Ratings'!$B$4:$BM$71,9,FALSE()) -> 1 | Q81: =IF(K81>=8.5,"🟢 ALTO",IF(K81>=7.5,"🟡 MEDIO","🔴 BAJO")) -> 🔴 BAJO
A82: Dashboard generado automáticamente | Datos: April 2026 | Framework: JP Morgan Equity Research
A83: AMZN | B83: =VLOOKUP(A83,'Watchlist Ratings'!$B$4:$BM$71,4,FALSE()) -> XNAS | C83: =VLOOKUP(A83,'Watchlist Ratings'!$B$4:$BM$71,59,FALSE()) -> 22.5 | D83: =VLOOKUP(A83,'Watchlist Ratings'!$B$4:$BM$71,60,FALSE()) -> 30 | E83: =VLOOKUP(A83,'Watchlist Ratings'!$B$4:$BM$71,61,FALSE()) -> 143.12207 | F83: =VLOOKUP(A83,'Watchlist Ratings'!$B$4:$BM$71,64,FALSE()) -> 0.050624228 | G83: =F83-E83 -> -143.07144 | H83: =IF(E83>0,"🟢 BUY",IF(E83>-0.05,"🟡 HOLD","🔴 PASS")) -> 🟢 BUY | J83: AMZN | K83: =VLOOKUP(J83,'Watchlist Ratings'!$B$4:$BM$71,36,FALSE()) -> -5 | L83: =VLOOKUP(J83,'Watchlist Ratings'!$B$4:$BM$71,29,FALSE()) -> 14 | M83: =VLOOKUP(J83,'Watchlist Ratings'!$B$4:$BM$71,30,FALSE()) -> -1 | N83: =VLOOKUP(J83,'Watchlist Ratings'!$B$4:$BM$71,34,FALSE()) -> 8 | O83: =VLOOKUP(J83,'Watchlist Ratings'!$B$4:$BM$71,8,FALSE()) -> 2829011.8 | P83: =VLOOKUP(J83,'Watchlist Ratings'!$B$4:$BM$71,9,FALSE()) -> 1.5 | Q83: =IF(K83>=8.5,"🟢 ALTO",IF(K83>=7.5,"🟡 MEDIO","🔴 BAJO")) -> 🔴 BAJO
A85: 📋 RESUMEN EJECUTIVO — Los Mejores en Cada Categoría
A87: 🏆 MEJOR CALIDAD | C87: 📈 MEJOR IRR BULL | E87: 💰 MAYOR ROIC | G87: 🏰 MEJOR MOAT | I87: 🎯 MÁS OPCIONALIDAD | K87: 🛡️ MÁS ANTIFRAGIL | M87: 💵 MENOR MÚLTIPLO | O87: ⚠️ MAYOR SPREAD
A88: =INDEX('Watchlist Ratings'!B$4:B$71,MATCH(MAX('Watchlist Ratings'!AN$4:AN$71),'Watchlist Ratings'!AN$4:AN$71,0)) -> CSU | C88: =INDEX('Watchlist Ratings'!B$4:B$71,MATCH(MAX('Watchlist Ratings'!BM$4:BM$71),'Watchlist Ratings'!BM$4:BM$71,0)) -> BFIT | E88: =INDEX('Watchlist Ratings'!B$4:B$71,MATCH(MAX('Watchlist Ratings'!BC$4:BC$71),'Watchlist Ratings'!BC$4:BC$71,0)) -> NVDA | G88: =INDEX('Watchlist Ratings'!B$4:B$71,MATCH(MAX('Watchlist Ratings'!K$4:K$71),'Watchlist Ratings'!K$4:K$71,0)) -> VEEV | I88: =INDEX('Watchlist Ratings'!B$4:B$71,MATCH(MAX('Watchlist Ratings'!L$4:L$71),'Watchlist Ratings'!L$4:L$71,0)) -> MSFT | K88: =INDEX('Watchlist Ratings'!B$4:B$71,MATCH(MAX('Watchlist Ratings'!AM$4:AM$71),'Watchlist Ratings'!AM$4:AM$71,0)) -> DSGX | M88: {=INDEX('Watchlist Ratings'!B$4:B$64,MATCH(MIN(IF('Watchlist Ratings'!AW$4:AW$64>0,'Watchlist Ratings'!AW$4:AW$64)),IF('Watchlist Ratings'!AW$4:AW$64>0,'Watchlist Ratings'!AW$4:AW$64),0))} -> KIST | O88: {=INDEX('Watchlist Ratings'!B$4:B$64,MATCH(MAX('Watchlist Ratings'!BM$4:BM$64-'Watchlist Ratings'!BL$4:BL$64),'Watchlist Ratings'!BM$4:BM$64-'Watchlist Ratings'!BL$4:BL$64,0))} -> OTLY
A89: =MAX('Watchlist Ratings'!AN$4:AN$71) -> 8.45 | C89: =MAX('Watchlist Ratings'!BM$4:BM$64) -> 0.46189106 | E89: =MAX('Watchlist Ratings'!BC$4:BC$71) -> 0.76982235 | G89: =MAX('Watchlist Ratings'!K$4:K$71)&"/8" -> 8/8 | I89: =MAX('Watchlist Ratings'!L$4:L$71)&"/3" -> 3/3 | K89: =MAX('Watchlist Ratings'!AM$4:AM$71) -> 8.71 | M89: {=MIN(IF('Watchlist Ratings'!AW$4:AW$64>0,'Watchlist Ratings'!AW$4:AW$64))&"x"} -> 2.90969106433356x | O89: {=MAX('Watchlist Ratings'!BM$4:BM$64-'Watchlist Ratings'!BL$4:BL$64)} -> 1.2242726
A91: Dashboard generado automáticamente | Datos: April 2026 | Framework: JP Morgan Equity Research

Sheet Updates Log
A1: Ticker | B1: Fecha | C1: Campos cambiados | D1: Fuente | E1: Resumen
A2: NFLX | B2: 2026-04-26 | C2: No financial changes — LTM figures already reflect Q1 2026 results | D2: Q1 2026 Earnings (April 16, 2026) — ir.netflix.net | E2: Q1 2026 rev $12.25B (+16.2% YoY), LTM figures ya actualizados. Guía FY26 $50.7-51.7B, FCF elevado a $12.5B por termination fee WBD. Q2 guía decepcionó (-9% AH).
A3: MIPS | B3: 2026-04-26 | C3: UPDATED [AP] Cash & Equivalents: 200 → 180; UPDATED [AV] Revenue LTM: 450 → 485; UPDATED [AU] EBITDA LTM: 165 → 182; UPDATED [AT] NOPAT LTM: 130 → 143; UPDATED [AS] FCF LTM (unlevered): 110 → 118 | D3: Q1 2026 Interim Report (mipscorp.com) | E3: Ventas +30% (SEK 151M), crecimiento orgánico +25%. EBIT adj SEK 50M (margen 33.2%). Caja baja a SEK 180M por adquisición Koroyd. Guía de >30% org growth mantenida.
A4: JFN | B4: 2026-04-26 | C4: UPDATED [AV] Revenue LTM: 225 → 306; UPDATED [AU] EBITDA LTM: 85 → 138; UPDATED [AS] FCF LTM (unlevered): 50 → 75; UPDATED [AT] NOPAT LTM: 35 → 78 | D4: FY 2025 Annual Results (jungfrau.ch / webdisclosure.com) | E4: FY25: ingresos operativos CHF 305.7M (+3.7%), EBITDA CHF 138.4M (+3%), FCF CHF 74.5M (+9.6%), EBIT CHF 98.9M. Dividendo propuesto CHF 8.50 (+). Nota: Revenue actualizado a total operativo vs. transport previo.
A5: KIST | B5: 2026-04-26 | C5: UPDATED manually on Bond presentation | D5: Bond Presetation on IR Kistos | E5: Net cash & Eq and DCF updated
A6: CSU | B6: 2026-05-18 | C6: A; AA; AD; AE; AF; AG; AH; AI; AJ; AK; AO; AP; AQ; AS; AT; AU; AV; AZ; B; BD; BF; BH; BI; BN; BO; BP; C; D; E; F; G; H; J; K; L; M; N; O; P; Q; T; U; V; W; X; Y; Z | D6: Q1 2026 Earnings (12/05/2026) + FY2025 Annual Report + Análisis fundamental | E6: Nueva entrada CSU (TSX): VMS serial acquirer. Rev LTM $12.1B USD, EBITDA $3.4B, FCF ~$2.7B. Rating cualitativo top (MOAT=8, Capital Allocation=15). Vigilar: M&A a mayor escala y riesgo IA en nichos VMS.
A7: NVDA | B7: 2026-06-10 | C7: BN Última actualización; BO Últimos resultados; BP Próximos resultados (est.) | D7: Q1 FY27 press release + CNBC (20/05/2026) | E7: Q1 FY27: rev $81.6B (+85%), Data Center $75.2B (+92%), EPS adj $1.87 beat; guía Q2 $91B; dividendo x25 a $0.25/trim. Vigilar digestión de expectativas (acción cayó pese al beat).
A8: CRWD | B8: 2026-06-10 | C8: BN Última actualización; BO Últimos resultados; BP Próximos resultados (est.) | D8: Q1 FY27 press release + transcript (03/06/2026) | E8: Q1 FY27: ARR $5.51B, NNARR $256M (+32%), FCF $469M récord; sube guía NNARR FY27 +$50M; split 4:1 (jul). AIDR ARR +250% QoQ. Tesis de plataforma intacta.
A9: VEEV | B9: 2026-06-10 | C9: BN Última actualización; BO Últimos resultados; BP Próximos resultados (est.) | D9: Q1 FY27 press release + IR (03/06/2026) | E9: Q1 FY27: rev $882.9M (+16%), subs +15%, EPS adj $2.24 beat; sube guía FY27. Pivot estratégico a AI agents (Vault CRM 150+ live). Vigilar ejecución Veeva AI.
A10: COST | B10: 2026-06-10 | C10: BN Última actualización; BO Últimos resultados; BP Próximos resultados (est.) | D10: Q3 FY26 press release (28/05/2026) | E10: Q3 FY26: ventas $69.2B (+11.6%), comps +9.8% (+6.6% adj), EPS $4.93 (+15%), e-comm +21.5%, renovación US/CA 92.2%. Calidad operativa intacta.
A11: ZS | B11: 2026-06-10 | C11: BN Última actualización; BO Últimos resultados; BP Próximos resultados (est.) | D11: Q3 FY26 press release (28/05/2026) | E11: Q3 FY26: rev $850.5M (+25%), ARR $3.525B (+25%), NNARR $166M, margen op. non-GAAP récord 23%; guía FY26 ARR ~$3.74B (+24%).
A12: S | B12: 2026-06-10 | C12: BN Última actualización; BO Últimos resultados; BP Próximos resultados (est.) | D12: Q1 FY27 press release (28/05/2026) | E12: Q1 FY27: aceleración rev +21% ($277M), ARR $1.163B (+23%), NNARR récord $44M (+55%), margen op. +550bps a 4%. Inflexión crecimiento+rentabilidad.
... A110: OTLY | B110: 2026-08-17 | C110: AP; AQ; BN | D110: Sintesis tesis Oatly + Q2 (22/07/2026) | E110: Balance actualizado al Q2: caja 44,6M vs deuda 517,8M (convertibles PIK 9,25% acretando hacia ~844M en 2028 + Nordic Bonds), patrimonio neto NEGATIVO. Operativo valida (+15,2%, guia FY26 +8-10% cc) pero muro 2028 sin avances: hueco 550-700M. Doc sugiere recortar/cerrar posicion-opcion y no perseguir.
A111: PRY | B111: 46254 | C111: Cash & Equivalents; Total Debt; FCF LTM; NOPAT LTM; EBITDA LTM; Revenue LTM; Capital Employed; Ultima actualizacion | D111: Deep dive propio 19-ago-2026 (Prysmian_Deep_Dive.md), datos FY2025 reportados + Q2/1H2026 (30-jul-2026) | E111: LTM refrescado a cifras FY2025 auditadas (Rev 19.650M, Adj EBITDA 2.398M, margen 14,2%). Deuda neta bajo control (0,9x EBITDA guiado a cierre 2026). Vigilar CMD 2027 y despliegue de 2.600M de M&A pendiente.
A112: SOM | B112: 46254 | C112: ALTA NUEVA: Company Name; Ticker; Category; Estilo inversion; Exchange; Currency; Price; Shares Outstanding; Market Cap; FX Reporting; Cash & Equivalents; Total Debt; FCF LTM; NOPAT LTM; EBITDA LTM; Revenue LTM; Enterprise Value; EV/FCF; EV/EBITDA; EV/Sales; NOPAT M% | D112: Tesis de Somero.docx + Somero_Operating_Model_2022_2030.xlsx (hojas Dashboard/Valuation/P&L/Assumptions) | E112: Alta nueva. Lider de nicho (Laser Screed hormigon), balance sin deuda neta (caja neta ~30M USD), ciclico en fondo de ciclo (Revenue -33% y EBITDA -60% pico-2022 a 2025). AGM jun-2026 con voto mayoritario EN CONTRA en 4 resoluciones (gobierno corporativo) - bandera roja pendiente de resolver. Ratings cualitativos (Rating 1/2/3, columnas J:AK) sin rellenar: la tesis no incluye scores 0-10, quedan pendientes de tu criterio.
A113: SOM | B113: 46254 | C113: Rating 1 (J:S completo); Rating 2 (T:AC completo); Rating 3 (AD:AM completo); Composite (AN); A67 vinculado como Stocks data type (B,E,F,G,H,I ahora formulas en vivo); Ultimos/Proximos resultados | D113: Tesis de Somero.docx (texto completo) + Somero_Operating_Model + investigacion web: Investegate (resultado AGM 17-jun-2026), TradingView/Investing.com (governance review 8-jul-2026), Johan Lunau Substack (moat/market share historico), busquedas Glassdoor/insider ownership | E113: Ratings calibrados contra Kistos/WOSG/Judges/Rational ya existentes en la hoja. Composite 3.56 (tier especial situacion, coherente con Estilo asignado). Puntos clave que penalizan: escandalo de voto en AGM jun-2026 (VN Capital denuncia 8.3M votos excluidos por cambio de fecha limite en Computershare/CREST), Remuneration Policy rechazada 61.35%, presidente L.Horsch 90 anos forzado a dimitir, sin stake verificable del CEO, Glassdoor negativo (equipo UK). Puntos que suman: caja neta sin deuda, >80% cuota estimada en screed automatizado, >100 patentes, board ya en revision de gobierno (QCA code) desde jul-2026.
A114: PRY | B114: 46254 | C114: Rating 1: Optionality, Concentration, Glassdoor, Ownership. Rating 2: Potential, Risks. Rating 3: Capital Allocation, Financing Source, Terminal Risk. FVE inputs: FCF @5y Min/Max (BD/BF) | D114: Deep dive propio 19-ago-2026 + toggle de escenarios del modelo Prysmian_Model_2019-2030.xlsx (Assumptions!B4, lectura Valuation!M14/M18 2030E por escenario) + investigacion web: anuncio adquisicion Atkore (prysmian.com, ~1-ago-2026), insider ownership (<5%, disperso), Glassdoor (3.7/5, 72% recomienda) | E114: Composite 5.24 -> 5.16 (practicamente estable). Hallazgo relevante no recogido en el deep dive: Prysmian anuncio compra de Atkore por 3.800M USD en efectivo (95 USD/accion), 9.8x EV/EBITDA 2025A o 7.1x con sinergias (150M USD/año en 3 años) - POR DEBAJO del umbral de alerta de 12x que el propio deep dive marcaba como limite de disciplina. Cierre esperado a finales de 2026; financiado con deuda+hibridos+autocartera manteniendo rating IG. Sube Optionality y Capital Allocation por la disciplina de precio; sube Concentration (penaliza) y Terminal Risk por la mayor exposicion a EEUU y el riesgo de integracion de una segunda gran adquisicion tan pronto tras Encore Wire. Ownership baja a -1: confirmado externamente insider ownership <5% disperso, sin comprador relevante en mercado abierto. FVE inputs (BD/BF) recalculados directamente alternando el toggle de escenario del modelo propio (Assumptions!B4=1/2/3) y leyendo el FCF 2030E resultante (5 anios vista): conservador 1.701M€, base 2.506M€ (sin cambio), alcista 3.496M€. FVE resultante: 93,76€ (min) - 252,93€ (max) con multiplos de salida 18x-22,5x FCF (sin cambio respecto al default de la hoja). IMPORTANTE: este FVE es standalone, NO incorpora el pro forma de Atkore (deal aun no cerrado, sin modelo combinado propio).
A115: IP | B115: 46255 | C115: ALTA NUEVA fila 68: A-I (mercado); J-Q Rating 1; T-AA Rating 2; AD-AK Rating 3; AO-AV financieros; AZ capital empleado; BD/BF FCF 5y; BH/BI múltiplos de salida; BN-BP fechas | D115: Deep dive propio 21-ago-2026 (Interpump_Deep_Dive.md + Interpump_Model_2019-2030.xlsx). Fuentes: nota de prensa FY2025 (20-mar-2026), resultados Q2/1S 2026 (6-ago-2026), earnings call Q2 2026, Highlights de IR, S&P Global vía stockanalysis | E115: Alta nueva. Compounder industrial italiano: bombas de alta presion y componentes hidraulicos moviles, lider mundial en tomas de fuerza para camion. Margen EBITDA 22-24% durante siete anos; balance a 0,63x EBITDA con objetivo de deuda cero en 2028; sin dilucion. Composite 5,31. PUNTOS QUE PENALIZAN: ROIC 10,0% en el valle (13,4% en el pico de 2023) y ROIIC 2019-2025 del 7% - el crecimiento es M&A, no reinversion organica; sucesion sin resolver (Montipo, 82 anos, sigue de presidente ejecutivo con poderes delegados); no publica cartera ni book-to-bill; cilindros hidraulicos (18% de ventas) sin moat. PUNTOS QUE SUMAN: no publica ningun EBITDA ajustado (contabilidad limpia); recompro 95 M EUR en 2022 con la accion cara y volvio a recomprar 22 M EUR en el 1S 2026 con la accion barata; una sola compra grande evitada en el ciclo caro. AS/AT/AU/AV son LTM a jun-2026; AP/AQ son del cierre de 2025. BD/BF = FCF 2030E conservador (260) y alcista (480) del modelo propio; BH/BI son multiplos EV/FCF calibrados para reproducir las TIR del modelo (0,0% / +26,8%). Asimetria prudente 2,98:1 sobre un bajista construido a mano de 26 EUR; el escenario conservador del modelo (36,50) queda POR ENCIMA del precio actual. Sizing 2,0-2,5%, entrada escalonada.
A116: RBT | B116: 46255 | C116: ALTA NUEVA fila 69: A-I (mercado); J-Q Rating 1; T-AA Rating 2; AD-AK Rating 3; AO-AV financieros; AZ capital empleado; BD/BF FCF 5y; BH/BI múltiplos de salida; BN-BP fechas | D116: Deep dive propio 21-ago-2026 (Robertet_Deep_Dive.md + Robertet_Model_2019-2030.xlsx). Fuentes: resultados anuales 2025 y presentacion (9-abr-2026), ventas 1S 2026 (6-ago-2026), texto de resoluciones de la junta 2026, nota Robertet/Peugeot Invest/FSP (nov-2024), S&P Global via stockanalysis | E116: Alta nueva y la de MAYOR CALIDAD de la tanda de agosto de 2026. Casa familiar de Grasse fundada en 1850, lider mundial en ingredientes naturales de perfumeria y aroma; es a la vez proveedor y competidor de Givaudan, IFF, dsm-firmenich y Symrise. Composite 7,01. PUNTOS QUE SUMAN: moat de aprovisionamiento agricola no replicable con dinero (red en ~50 paises, destilerias propias); margen EBITDA del 17,3% (2019) al 20,6% (2025) y margen bruto +3,7 pt desde 2022; ROIC 15,0% y ROIIC 2021-2025 del 15,5% sobre inversion ORGANICA, no comprando empresas; circulante bajado del 60,9% al 48,4% de ventas (~100 M EUR liberados) desde que Jerome Bruhat es director general en 2022; familia Maubert con 38% del capital y 62% de los votos; sin metricas ajustadas; balance a 0,64x. PUNTOS QUE PENALIZAN: el director general no tiene participacion relevante (quien ejecuta no es dueno); transparencia muy pobre (sin margen por division, sin call trimestral, resultados semestrales); iliquidez real (2.169.297 titulos, 40% de free float); objetivo de +5% organico de 2026 en riesgo (1S en +2,8%, Q2 en +0,7%). OPCIONALIDAD NO MODELIZADA: Givaudan posee el 4,68% comprado en mercado sin negociacion previa. AP/AQ/AU/AV/AZ del cierre de 2025 (ultimo periodo completo reportado). BD/BF = FCF 2030E conservador (92) y alcista (145). Asimetria prudente 2,66:1 sobre un bajista de 588 EUR. Sizing 2,5-3,0%, candidata a nucleo resiliente; iniciar 1,5% y ampliar tras los resultados completos del 1S el 17-sep-2026.
A117: ROKO B | B117: 46255 | C117: ALTA NUEVA fila 70: A-I (mercado); J-Q Rating 1; T-AA Rating 2; AD-AK Rating 3; AO-AV financieros; AZ capital empleado; BD/BF FCF 5y; BH/BI múltiplos de salida; BN-BP fechas | D117: Deep dive propio 21-ago-2026 (Roko_Deep_Dive.md + Roko_Model_2019-2030.xlsx). Fuentes: informe anual 2025, year-end report 2025, informe intermedio ene-jun 2026 y presentacion, nota de cambio de CEO (8-mar-2026), prospecto de la salida a bolsa (mar-2025), stockanalysis y MarketScreener | E117: Alta nueva. Consolidador nordico fundado en 2019 por Fredrik Karlsson (CEO de Lifco 1998-2019) y Tomas Billing. 34 companias de nicho en 8 paises, 1.829 empleados y OCHO personas en la oficina central. Composite 5,98. PUNTOS QUE SUMAN: el mejor alineamiento de la watchlist - 21% del capital y 65% de los votos en manos de los tres ejecutivos, y Karlsson ha comprado acciones por 97 MSEK tras la salida a bolsa; compra por debajo de 8x EBITA lo que el mercado le valora a 21x; ROCE sube cinco anos seguidos (9,2% a 14,8%) MIENTRAS compra; ROCE sin fondo de comercio 127%; capex 1% de ventas y conversion de caja 72%; una sola adquisicion en 2023, el ano caro (la disciplina que Storskogen no tuvo). PUNTOS QUE PENALIZAN: solo 17 meses de historia publica (salida a bolsa 11-mar-2025) y una sola memoria anual; cambio de consejero delegado el 22-abr-2026 (Johan Bladh sustituye a Karlsson, que sigue como adjunto y presidente del Comite de Inversiones) SIN QUE LA COMPANIA HAYA EXPLICADO POR QUE AHORA; apalancamiento de 2,0x (dic-25) a 2,6x (jun-26) contra un techo declarado de 3,0x; el 32% de las ventas es B2C de retail especializado, el segmento con peor economia de la cartera. TRAMPA CONTABLE IMPORTANTE: hay DOS cifras de deuda. La deuda neta con intereses es 1.817 MSEK; la deuda financiera neta es 4.387 MSEK e incluye 2.570 MSEK de opciones de venta, earn-outs y pagos aplazados a los minoritarios de las filiales, que CRECEN cuando las filiales van bien. AQ=4.887 y AP=500 estan puestos para que AR reproduzca el EV correcto de 31.617 MSEK. Con esa deuda el descuento en EV/EBITA frente a Lifco casi desaparece (21,5x vs 22-24x), aunque en P/E siga pareciendo barata. AU es EBITDA estimado (adj. EBITA LTM 1.473 + amortizacion de tangibles); la compania reporta adj. EBITA, no EBITDA. Asimetria 3,02:1, la mejor de la tanda. Sizing 1,5-2,0%, media posicion ahora. Fechas BO/BP estimadas.
A118: USPH | B118: 46255 | C118: ALTA NUEVA fila 71: A-I (mercado); J-Q Rating 1; T-AA Rating 2; AD-AK Rating 3; AO-AV financieros; AZ capital empleado; BD/BF FCF 5y; BH/BI múltiplos de salida; BN-BP fechas | D118: Deep dive propio 21-ago-2026 (USPH_Deep_Dive.md + USPH_Model_2019-2030.xlsx). Fuentes: 8-K de resultados Q2 2026 (5-ago-2026) y Q1 2026 (5-may-2026), presentacion de inversores Q4 2025, CMS/APTA sobre el Medicare Physician Fee Schedule 2026 y 2027, S&P Global via stockanalysis | E118: Alta nueva. Unico operador cotizado puro de fisioterapia ambulatoria de EE.UU.: 780 clinicas en 44 estados mas un negocio de prevencion de lesiones laborales (15% de ingresos, sin exposicion al reembolso sanitario). Mercado de mas de 40.000 M USD tan fragmentado que ningun operador supera el 10%. Composite 2,94, el mas bajo de la tanda. AVISO CRITICO: el BPA GAAP de USPH NO SIGNIFICA NADA. Los fundadores de cada clinica conservan el 20-50% en participaciones REDIMIBLES que se revalorizan cada trimestre, y esa revalorizacion se resta del BPA sin pasar por el beneficio neto; en el Q1 2026 hubo beneficio neto positivo (5,0 M USD) y BPA NEGATIVO (-0,12 USD), y el PER oficial LTM es de 437x. Solo sirven el EBITDA ajustado y los Operating Results per share. PUNTOS QUE PENALIZAN: el margen NO expande (EBITDA ajustado 12,9% en 2023, 12,2% en 2024 y 2025) y el margen bruto de clinica ha caido del 23,9% (2021) al 19,9% (Q2 2026); tijera estructural entre el ingreso por visita (+2,1%) y el coste salarial por visita (~+4,1%); ROIIC 2023-2025 de ~7% despues de impuestos porque compra clinicas a 8-10x contra cuatro fondos de private equity; apalancamiento de 1,36x (2023) a 3,47x (jun-26) MAS 318 M USD de participaciones redimibles fuera de esa cifra; dividendo (27,4 M USD) MAYOR que el flujo de caja atribuible al accionista de USPH (~20-25 M USD tras la salida hacia los socios de clinica), financiado con deuda; ampliacion de capital del 15% en 2023; insiders con solo 2-3% del capital. PUNTOS QUE SUMAN: demanda demografica garantizada, la mejor transparencia operativa de la tanda (visitas, visitas diarias por clinica, ingreso por visita por pagador, salarios sobre ingresos), CEO con 22 anos en el puesto, circulante practicamente cero y capex del 1,8% de ventas, y las afiliaciones hospitalarias (NYU Langone y un sistema de la Costa del Golfo, 70 clinicas integrandose en 2026) como opcionalidad que crece sin capital. AZ excluye las participaciones redimibles. AU=96 es EBITDA AJUSTADO LTM (metrica de la compania, ya neta de minoritarios); por eso el EV de AR no les suma los 318 M USD. Asimetria 1,75:1, POR DEBAJO del minimo de 2:1: sizing HOY 0%. Alerta de precio en 75,72 USD (2:1) y compra en 72 USD (2,5:1); por debajo de 65 USD, 2,5-3% - es donde recompro la propia compania en el 1S 2026 (media 62,80 USD). Q3 2026 en noviembre es el trimestre decisivo: el margen bruto de clinica tiene que volver por encima del 21% y la guia de EBITDA ajustado de 102-106 M USD exige un 2S de ~57 M USD frente a 47 en el 1S.
A119: PRY | B119: 46255 | C119: M (Financials); P (Founder/CEO); Q (Ownership); K (MOAT) | D119: Auditoria cualitativa de ratings contra el checklist del deep dive de Prysmian | E119: Financials 0>1 por deuda neta 0,9x EBITDA. Founder/CEO 0>1: la columna se aplica como calidad del liderazgo y el equipo cumplio los seis objetivos del CMD con adelanto. Ownership -1>0 para igualar el criterio de ABB, Schneider, Legrand y Veralto. MOAT 5>5,5 por la posicion en HVDC.
A120: GOOG | B120: 46255 | C120: P (Founder/CEO); Y (Mgmt & Culture) | D120: Auditoria cualitativa de ratings contra el checklist del deep dive de Prysmian | E120: Founder/CEO 0>1: los fundadores conservan el control de voto via acciones B. Mgmt & Culture 9>11: un 9 sobre 14 lo ponia por debajo de Airbnb y Descartes.
A121: NET | B121: 46255 | C121: J (Mission); T (R2 Financials) | D121: Auditoria cualitativa de ratings contra el checklist del deep dive de Prysmian | E121: Mission 2>1: el maximo de la columna para un vendedor de CDN/SSE mientras Inditex y Lifco estan en 0. R2 Financials 10>8 con ROIC 1,4% y EV/FCF 369x.
A122: CRWD | B122: 46255 | C122: J (Mission) | D122: Auditoria cualitativa de ratings contra el checklist del deep dive de Prysmian | E122: Mission 2>1, mismo criterio que Cloudflare y Zscaler.
... A262: MSFT; META; GOOG | B262: 46299 | C262: BD; BF; BE; BG (formula contra BS); BT | D262: Decision de Roger, 4-oct-2026 (P4 de la Carta de vientos macro) | E262: Normalizacion del FCF@5y de las Mag-7 (P4 de la Carta de vientos, decision de Roger 4-oct-2026). Desde el 8-sep BD/BF estaban en base FCF-SBC (escalados con AS), es decir, DESPUES del capex de IA, mientras el EV/FCF de hoy ya usaba el normalizado (BS) desde el 11-sep: la TIR mezclaba bases. Ahora BD/BF = valores del 8-sep x BS/AS, que conserva las CAGR de Roger y devuelve las filas a la base del 22-ago. MSFT x2,328: BD 63.334,9 -> 147.461,2; BF 96.094,3 -> 223.734,1. META x5,204: BD 12.030,4 -> 62.609,7; BF 33.269,4 -> 173.143,7. GOOG x5,265: BD 32.067,8 -> 168.840,3; BF 50.537,4 -> 266.084,7. BE/BG de las tres pasan a (BD/BS)^(1/5)-1. MULTIPLOS SIN CAMBIO (MSFT 20/30, META 18/26, GOOG 20/30) POR DECISION DE ROGER, excepcion consciente a la regla Lotus: se le ofrecio recortarlos con multiplo x (1 - g/ROIC) y prefirio mantenerlos porque se calibraron sobre FCF normalizado. TIR peor/mejor: MSFT -19,4/-5,3 -> -4,9/+11,9; META -36,3/-14,6 -> -9,8/+19,3; GOOG -28,8/-17,0 -> -3,4/+14,3. AMZN ya estaba normalizada desde el 11-sep (sin cambio, -10,7/+5,9). NVDA no se normaliza: capex 7.354 = 1,99x D&A, por debajo del umbral de 2x de la regla.
